Workbook

Sheet List of Assets
A1: LEGENDA | G1: Category | H1: ID Category | J1: Site | K1: ID Site
B2: Lost/ Missing | G2: Elektronik | H2: I | J2: BSD | K2: 01
B3: Broken | G3: Furniture | H3: II | J3: Deltamas 1 | K3: 02
B4: Sell | G4: Laptop and Komp | H4: III | J4: Deltamas 2 | K4: 03
B5: Odd (See Comment) | G5: Kendaraan | H5: IV
B6: Belum diinput Finance | G6: Machine and Tooling | H6: V
B9: ID | C9: Category | D9: ID Category | E9: Asset ID | F9: Asset Name | G9: Purchase Date | H9: Cost (Finance) | I9: Cost (GA & Supply Chain) | J9: PIC | K9: Department | L9: Site | M9: ID Site | N9: Brand | O9: Model | P9: Serial Number | Q9: Notes | R9: Status | S9: Price
A10: 1 | B10: FA001 | C10: Elektronik | D10: =if(C10=$G$2,$H$2, if(C10=$G$3,$H$3, if(C10=$G$4,$H$4, if(C10=$G$5,$H$5,if(C10=$G$6,$H$6, " "))))) -> I | E10: =CONCATENATE(B10,"/",D10,"/",M10) -> FA001/I/02 | F10: MONITOR DELL P2314H 23 INC | G10: 42005 | H10: 3150000 | L10: Deltamas 1 | M10: =if(L10=$J$2,$K$2,if(L10=$J$3,$K$3,if(L10=$J$4,$K$4," "))) -> 02 | N10: Dell | R10: Lost/ Missing
A11: 2 | B11: FA002 | C11: Laptop and Komp | D11: =if(C11=$G$2,$H$2, if(C11=$G$3,$H$3, if(C11=$G$4,$H$4, if(C11=$G$5,$H$5,if(C11=$G$6,$H$6, " "))))) -> III | E11: =CONCATENATE(B11,"/",D11,"/",M11) -> FA002/III/01 | F11: LAPTOP | G11: 42135 | H11: 6900000 | J11: Diki | K11: Supply Chain | L11: BSD | M11: =if(L11=$J$2,$K$2,if(L11=$J$3,$K$3,if(L11=$J$4,$K$4," "))) -> 01 | R11: Lost/ Missing
A12: 3 | B12: FA003 | C12: Elektronik | D12: =if(C12=$G$2,$H$2, if(C12=$G$3,$H$3, if(C12=$G$4,$H$4, if(C12=$G$5,$H$5,if(C12=$G$6,$H$6, " "))))) -> I | E12: =CONCATENATE(B12,"/",D12,"/",M12) -> FA003/I/01 | F12: HARDISK SEAGATE SRD0NF1 | G12: 42135 | H12: 580000 | J12: Adi Kusumah | K12: Engineering | L12: BSD | M12: =if(L12=$J$2,$K$2,if(L12=$J$3,$K$3,if(L12=$J$4,$K$4," "))) -> 01 | R12: Active
A13: 4 | B13: FA004 | C13: Furniture | D13: =if(C13=$G$2,$H$2, if(C13=$G$3,$H$3, if(C13=$G$4,$H$4, if(C13=$G$5,$H$5,if(C13=$G$6,$H$6, " "))))) -> II | E13: =CONCATENATE(B13,"/",D13,"/",M13) -> FA004/II/01 | F13: BANGKU | G13: 42249 | H13: 2500000 | L13: BSD | M13: =if(L13=$J$2,$K$2,if(L13=$J$3,$K$3,if(L13=$J$4,$K$4," "))) -> 01 | R13: Lost/ Missing
A14: 5 | B14: FA005 | C14: Furniture | D14: =if(C14=$G$2,$H$2, if(C14=$G$3,$H$3, if(C14=$G$4,$H$4, if(C14=$G$5,$H$5,if(C14=$G$6,$H$6, " "))))) -> II | E14: =CONCATENATE(B14,"/",D14,"/",M14) -> FA005/II/01 | F14: RAK | G14: 42252 | H14: 1787190 | L14: BSD | M14: =if(L14=$J$2,$K$2,if(L14=$J$3,$K$3,if(L14=$J$4,$K$4," "))) -> 01 | R14: Broken
A15: 6 | B15: FA006 | C15: Furniture | D15: =if(C15=$G$2,$H$2, if(C15=$G$3,$H$3, if(C15=$G$4,$H$4, if(C15=$G$5,$H$5,if(C15=$G$6,$H$6, " "))))) -> II | E15: =CONCATENATE(B15,"/",D15,"/",M15) -> FA006/II/01 | F15: MEJA PRINTER KOTAK | G15: 42254 | H15: 3034500 | J15: Herfian | K15: Engineering | L15: BSD | M15: =if(L15=$J$2,$K$2,if(L15=$J$3,$K$3,if(L15=$J$4,$K$4," "))) -> 01 | R15: Active
A16: 7 | B16: FA007 | C16: Furniture | D16: =if(C16=$G$2,$H$2, if(C16=$G$3,$H$3, if(C16=$G$4,$H$4, if(C16=$G$5,$H$5,if(C16=$G$6,$H$6, " "))))) -> II | E16: =CONCATENATE(B16,"/",D16,"/",M16) -> FA007/II/01 | F16: LEMARI | G16: 42278 | H16: 570000 | L16: BSD | M16: =if(L16=$J$2,$K$2,if(L16=$J$3,$K$3,if(L16=$J$4,$K$4," "))) -> 01 | R16: Broken
A17: 8 | B17: FA008 | C17: Furniture | D17: =if(C17=$G$2,$H$2, if(C17=$G$3,$H$3, if(C17=$G$4,$H$4, if(C17=$G$5,$H$5,if(C17=$G$6,$H$6, " "))))) -> II | E17: =CONCATENATE(B17,"/",D17,"/",M17) -> FA008/II/01 | F17: KIPAS | G17: 42279 | H17: 220000 | L17: BSD | M17: =if(L17=$J$2,$K$2,if(L17=$J$3,$K$3,if(L17=$J$4,$K$4," "))) -> 01 | R17: Broken
A18: 9 | B18: FA009 | C18: Elektronik | D18: =if(C18=$G$2,$H$2, if(C18=$G$3,$H$3, if(C18=$G$4,$H$4, if(C18=$G$5,$H$5,if(C18=$G$6,$H$6, " "))))) -> I | E18: =CONCATENATE(B18,"/",D18,"/",M18) -> FA009/I/01 | F18: HP SAMSUNG GALAXY | G18: 42338 | H18: 2950000 | L18: BSD | M18: =if(L18=$J$2,$K$2,if(L18=$J$3,$K$3,if(L18=$J$4,$K$4," "))) -> 01 | N18: Samsung | R18: Lost/ Missing
A19: 10 | B19: FA010 | C19: Elektronik | D19: =if(C19=$G$2,$H$2, if(C19=$G$3,$H$3, if(C19=$G$4,$H$4, if(C19=$G$5,$H$5,if(C19=$G$6,$H$6, " "))))) -> I | E19: =CONCATENATE(B19,"/",D19,"/",M19) -> FA010/I/01 | F19: TV | G19: 42403 | H19: 300000 | L19: BSD | M19: =if(L19=$J$2,$K$2,if(L19=$J$3,$K$3,if(L19=$J$4,$K$4," "))) -> 01 | R19: Lost/ Missing
A20: 11 | B20: FA011 | C20: Laptop and Komp | D20: =if(C20=$G$2,$H$2, if(C20=$G$3,$H$3, if(C20=$G$4,$H$4, if(C20=$G$5,$H$5,if(C20=$G$6,$H$6, " "))))) -> III | E20: =CONCATENATE(B20,"/",D20,"/",M20) -> FA011/III/01 | F20: LAPTOP HP I3 | G20: 42675 | H20: 6540000 | K20: Engineering | L20: BSD | M20: =if(L20=$J$2,$K$2,if(L20=$J$3,$K$3,if(L20=$J$4,$K$4," "))) -> 01 | N20: HP | R20: Active
A21: 12 | B21: FA012 | C21: Elektronik | D21: =if(C21=$G$2,$H$2, if(C21=$G$3,$H$3, if(C21=$G$4,$H$4, if(C21=$G$5,$H$5,if(C21=$G$6,$H$6, " "))))) -> I | E21: =CONCATENATE(B21,"/",D21,"/",M21) -> FA012/I/01 | F21: MESIN ABSEN | G21: 42522 | H21: 1500000 | L21: BSD | M21: =if(L21=$J$2,$K$2,if(L21=$J$3,$K$3,if(L21=$J$4,$K$4," "))) -> 01 | R21: Broken
A22: 13 | B22: FA013 | C22: Elektronik | D22: =if(C22=$G$2,$H$2, if(C22=$G$3,$H$3, if(C22=$G$4,$H$4, if(C22=$G$5,$H$5,if(C22=$G$6,$H$6, " "))))) -> I | E22: =CONCATENATE(B22,"/",D22,"/",M22) -> FA013/I/01 | F22: PRINTER | G22: 42566 | H22: 660000 | L22: BSD | M22: =if(L22=$J$2,$K$2,if(L22=$J$3,$K$3,if(L22=$J$4,$K$4," "))) -> 01 | R22: Lost/ Missing
A23: 14 | B23: FA014 | C23: Furniture | D23: =if(C23=$G$2,$H$2, if(C23=$G$3,$H$3, if(C23=$G$4,$H$4, if(C23=$G$5,$H$5,if(C23=$G$6,$H$6, " "))))) -> II | E23: =CONCATENATE(B23,"/",D23,"/",M23) -> FA014/II/01 | F23: KURSI STAFF | G23: 42466 | H23: 900000 | L23: BSD | M23: =if(L23=$J$2,$K$2,if(L23=$J$3,$K$3,if(L23=$J$4,$K$4," "))) -> 01 | R23: Lost/ Missing
A24: 15 | B24: FA015 | C24: Furniture | D24: =if(C24=$G$2,$H$2, if(C24=$G$3,$H$3, if(C24=$G$4,$H$4, if(C24=$G$5,$H$5,if(C24=$G$6,$H$6, " "))))) -> II | E24: =CONCATENATE(B24,"/",D24,"/",M24) -> FA015/II/01 | F24: HECTOR OFFICE TABLE WALNUT BLACK | G24: 42461 | H24: 750000 | J24: Corneleo | K24: Sales & Marketing | L24: BSD | M24: =if(L24=$J$2,$K$2,if(L24=$J$3,$K$3,if(L24=$J$4,$K$4," "))) -> 01 | R24: Active
A25: 16 | B25: FA016 | C25: Laptop and Komp | D25: =if(C25=$G$2,$H$2, if(C25=$G$3,$H$3, if(C25=$G$4,$H$4, if(C25=$G$5,$H$5,if(C25=$G$6,$H$6, " "))))) -> III | E25: =CONCATENATE(B25,"/",D25,"/",M25) -> FA016/III/01 | F25: LAPTOP ASUS ROG GL553V | G25: 42736 | H25: 21000000 | J25: Adi Kusumah | K25: Engineering | L25: BSD | M25: =if(L25=$J$2,$K$2,if(L25=$J$3,$K$3,if(L25=$J$4,$K$4," "))) -> 01 | N25: Asus | R25: Active
A26: 17 | B26: FA017 | C26: Elektronik | D26: =if(C26=$G$2,$H$2, if(C26=$G$3,$H$3, if(C26=$G$4,$H$4, if(C26=$G$5,$H$5,if(C26=$G$6,$H$6, " "))))) -> I | E26: =CONCATENATE(B26,"/",D26,"/",M26) -> FA017/I/01 | F26: PC. DELL PRECISION TOWER 5810 | G26: 42736 | H26: 37505000 | K26: Engineering | L26: BSD | M26: =if(L26=$J$2,$K$2,if(L26=$J$3,$K$3,if(L26=$J$4,$K$4," "))) -> 01 | N26: Dell | R26: Lost/ Missing
A27: 18 | B27: FA018 | C27: Laptop and Komp | D27: =if(C27=$G$2,$H$2, if(C27=$G$3,$H$3, if(C27=$G$4,$H$4, if(C27=$G$5,$H$5,if(C27=$G$6,$H$6, " "))))) -> III | E27: =CONCATENATE(B27,"/",D27,"/",M27) -> FA018/III/01 | F27: LAPTOP ROG GL552VX | G27: 42979 | H27: 13050000 | K27: Engineering | L27: BSD | M27: =if(L27=$J$2,$K$2,if(L27=$J$3,$K$3,if(L27=$J$4,$K$4," "))) -> 01 | N27: Asus | R27: Active
A28: 19 | B28: FA019 | C28: Machine and Tooling | D28: =if(C28=$G$2,$H$2, if(C28=$G$3,$H$3, if(C28=$G$4,$H$4, if(C28=$G$5,$H$5,if(C28=$G$6,$H$6, " "))))) -> V | E28: =CONCATENATE(B28,"/",D28,"/",M28) -> FA019/V/02 | F28: PRINTER 3D | G28: 42979 | H28: 3275000 | L28: Deltamas 1 | M28: =if(L28=$J$2,$K$2,if(L28=$J$3,$K$3,if(L28=$J$4,$K$4," "))) -> 02
A29: 20 | B29: FA020 | C29: Elektronik | D29: =if(C29=$G$2,$H$2, if(C29=$G$3,$H$3, if(C29=$G$4,$H$4, if(C29=$G$5,$H$5,if(C29=$G$6,$H$6, " "))))) -> I | E29: =CONCATENATE(B29,"/",D29,"/",M29) -> FA020/I/02 | F29: AC POLYTRON | G29: 43049 | H29: 3000000 | L29: Deltamas 1 | M29: =if(L29=$J$2,$K$2,if(L29=$J$3,$K$3,if(L29=$J$4,$K$4," "))) -> 02 | N29: Polytron | R29: Lost/ Missing
A30: 21 | B30: FA021 | C30: Furniture | D30: =if(C30=$G$2,$H$2, if(C30=$G$3,$H$3, if(C30=$G$4,$H$4, if(C30=$G$5,$H$5,if(C30=$G$6,$H$6, " "))))) -> II | E30: =CONCATENATE(B30,"/",D30,"/",M30) -> FA021/II/01 | F30: HECTOR OFFICE TABLE WALNUT BLACK | G30: 43132 | H30: 1400000 | K30: HRGA & Legal | L30: BSD | M30: =if(L30=$J$2,$K$2,if(L30=$J$3,$K$3,if(L30=$J$4,$K$4," "))) -> 01 | R30: Active
A31: 22 | B31: FA022 | C31: Laptop and Komp | D31: =if(C31=$G$2,$H$2, if(C31=$G$3,$H$3, if(C31=$G$4,$H$4, if(C31=$G$5,$H$5,if(C31=$G$6,$H$6, " "))))) -> III | E31: =CONCATENATE(B31,"/",D31,"/",M31) -> FA022/III/01 | F31: LAPTOP | G31: 43132 | H31: 14548800 | J31: Hari TM | K31: Engineering | L31: BSD | M31: =if(L31=$J$2,$K$2,if(L31=$J$3,$K$3,if(L31=$J$4,$K$4," "))) -> 01 | R31: Active
A32: 23 | B32: FA023 | C32: Elektronik | D32: =if(C32=$G$2,$H$2, if(C32=$G$3,$H$3, if(C32=$G$4,$H$4, if(C32=$G$5,$H$5,if(C32=$G$6,$H$6, " "))))) -> I | E32: =CONCATENATE(B32,"/",D32,"/",M32) -> FA023/I/01 | F32: Laptop Dell G5590 | G32: 43160 | H32: 31200000 | J32: Agus RH | K32: Engineering | L32: BSD | M32: =if(L32=$J$2,$K$2,if(L32=$J$3,$K$3,if(L32=$J$4,$K$4," "))) -> 01 | N32: Asus | R32: Active
A33: 24 | B33: FA024 | C33: Laptop and Komp | D33: =if(C33=$G$2,$H$2, if(C33=$G$3,$H$3, if(C33=$G$4,$H$4, if(C33=$G$5,$H$5,if(C33=$G$6,$H$6, " "))))) -> III | E33: =CONCATENATE(B33,"/",D33,"/",M33) -> FA024/III/01 | F33: ACER PREDATOR NITRO | G33: 43160 | H33: 10999000 | L33: BSD | M33: =if(L33=$J$2,$K$2,if(L33=$J$3,$K$3,if(L33=$J$4,$K$4," "))) -> 01 | N33: Acer | R33: Lost/ Missing
A34: 25 | B34: FA025 | C34: Elektronik | D34: =if(C34=$G$2,$H$2, if(C34=$G$3,$H$3, if(C34=$G$4,$H$4, if(C34=$G$5,$H$5,if(C34=$G$6,$H$6, " "))))) -> I | E34: =CONCATENATE(B34,"/",D34,"/",M34) -> FA025/I/02 | F34: AC POLYTRON | G34: 43221 | H34: 3000000 | L34: Deltamas 1 | M34: =if(L34=$J$2,$K$2,if(L34=$J$3,$K$3,if(L34=$J$4,$K$4," "))) -> 02 | N34: Polytron | R34: Lost/ Missing
A35: 26 | B35: FA026 | C35: Laptop and Komp | D35: =if(C35=$G$2,$H$2, if(C35=$G$3,$H$3, if(C35=$G$4,$H$4, if(C35=$G$5,$H$5,if(C35=$G$6,$H$6, " "))))) -> III | E35: =CONCATENATE(B35,"/",D35,"/",M35) -> FA026/III/01 | F35: 3 MONITOR + KEYBOARD 2 + MOUSE 2 + ACC + KABEL VGA + KABEL USG EXT STD | G35: 43221 | H35: 4920000 | J35: Bilkis Ismail | K35: PITD | L35: BSD | M35: =if(L35=$J$2,$K$2,if(L35=$J$3,$K$3,if(L35=$J$4,$K$4," "))) -> 01 | R35: Active
A36: 26 | B36: FA026.1 | C36: Laptop and Komp | D36: =if(C36=$G$2,$H$2, if(C36=$G$3,$H$3, if(C36=$G$4,$H$4, if(C36=$G$5,$H$5,if(C36=$G$6,$H$6, " "))))) -> III | E36: =CONCATENATE(B36,"/",D36,"/",M36) -> FA026.1/III/01 | F36: 3 MONITOR + KEYBOARD 2 + MOUSE 2 + ACC + KABEL VGA + KABEL USG EXT STD | G36: 43221 | H36: 4920000 | J36: Rifky Fauzi | K36: Engineering | L36: BSD | M36: =if(L36=$J$2,$K$2,if(L36=$J$3,$K$3,if(L36=$J$4,$K$4," "))) -> 01 | R36: Active
A37: 26 | B37: FA026.2 | C37: Laptop and Komp | D37: =if(C37=$G$2,$H$2, if(C37=$G$3,$H$3, if(C37=$G$4,$H$4, if(C37=$G$5,$H$5,if(C37=$G$6,$H$6, " "))))) -> III | E37: =CONCATENATE(B37,"/",D37,"/",M37) -> FA026.2/III/01 | F37: 3 MONITOR + KEYBOARD 2 + MOUSE 2 + ACC + KABEL VGA + KABEL USG EXT STD | G37: 43221 | H37: 4920000 | J37: Dimas | K37: HRGA & Legal | L37: BSD | M37: =if(L37=$J$2,$K$2,if(L37=$J$3,$K$3,if(L37=$J$4,$K$4," "))) -> 01 | R37: Active
A38: 27 | B38: FA027 | C38: Elektronik | D38: =if(C38=$G$2,$H$2, if(C38=$G$3,$H$3, if(C38=$G$4,$H$4, if(C38=$G$5,$H$5,if(C38=$G$6,$H$6, " "))))) -> I | E38: =CONCATENATE(B38,"/",D38,"/",M38) -> FA027/I/01 | F38: Camera Sony A6400 | G38: 43256 | H38: 9500032 | J38: Yogie | K38: Business & Digital Development | L38: BSD | M38: =if(L38=$J$2,$K$2,if(L38=$J$3,$K$3,if(L38=$J$4,$K$4," "))) -> 01 | N38: Sony | R38: Active
A39: 28 | B39: FA028 | C39: Laptop and Komp | D39: =if(C39=$G$2,$H$2, if(C39=$G$3,$H$3, if(C39=$G$4,$H$4, if(C39=$G$5,$H$5,if(C39=$G$6,$H$6, " "))))) -> III | E39: =CONCATENATE(B39,"/",D39,"/",M39) -> FA028/III/01 | F39: Lenovo IP1205 | G39: 43287 | H39: 3900000 | J39: Rispandi | K39: HRGA & Legal | L39: BSD | M39: =if(L39=$J$2,$K$2,if(L39=$J$3,$K$3,if(L39=$J$4,$K$4," "))) -> 01 | N39: Lenovo | Q39: Tidak terpakai ada di lemari HRGA | R39: Active
A40: 29 | B40: FA029 | C40: Machine and Tooling | D40: =if(C40=$G$2,$H$2, if(C40=$G$3,$H$3, if(C40=$G$4,$H$4, if(C40=$G$5,$H$5,if(C40=$G$6,$H$6, " "))))) -> V | E40: =CONCATENATE(B40,"/",D40,"/",M40) -> FA029/V/02 | F40: 3D PRINTER | G40: 43314 | H40: 2953007 | L40: Deltamas 1 | M40: =if(L40=$J$2,$K$2,if(L40=$J$3,$K$3,if(L40=$J$4,$K$4," "))) -> 02
A41: 30 | B41: FA030 | C41: Elektronik | D41: =if(C41=$G$2,$H$2, if(C41=$G$3,$H$3, if(C41=$G$4,$H$4, if(C41=$G$5,$H$5,if(C41=$G$6,$H$6, " "))))) -> I | E41: =CONCATENATE(B41,"/",D41,"/",M41) -> FA030/I/01 | F41: HP XIAOMI | G41: 43313 | H41: 1320000 | K41: Engineering | L41: BSD | M41: =if(L41=$J$2,$K$2,if(L41=$J$3,$K$3,if(L41=$J$4,$K$4," "))) -> 01 | N41: Xiaomi | R41: Lost/ Missing
A42: 31 | B42: FA031 | C42: Machine and Tooling | D42: =if(C42=$G$2,$H$2, if(C42=$G$3,$H$3, if(C42=$G$4,$H$4, if(C42=$G$5,$H$5,if(C42=$G$6,$H$6, " "))))) -> V | E42: =CONCATENATE(B42,"/",D42,"/",M42) -> FA031/V/01 | F42: 3D PRINTER ANYCUBIC PHOTON | G42: 43378 | H42: 8190000 | J42: Agus RH | K42: Engineering | L42: BSD | M42: =if(L42=$J$2,$K$2,if(L42=$J$3,$K$3,if(L42=$J$4,$K$4," "))) -> 01 | N42: Anycubic | R42: Active
A43: 32 | B43: FA032 | C43: Elektronik | D43: =if(C43=$G$2,$H$2, if(C43=$G$3,$H$3, if(C43=$G$4,$H$4, if(C43=$G$5,$H$5,if(C43=$G$6,$H$6, " "))))) -> I | E43: =CONCATENATE(B43,"/",D43,"/",M43) -> FA032/I/01 | F43: LEMARI & TURN TABLE U/ 3D SCANNING IMAJIN | G43: 43383 | H43: 898900 | L43: BSD | M43: =if(L43=$J$2,$K$2,if(L43=$J$3,$K$3,if(L43=$J$4,$K$4," "))) -> 01 | R43: Lost/ Missing
A44: 33 | B44: FA033 | C44: Elektronik | D44: =if(C44=$G$2,$H$2, if(C44=$G$3,$H$3, if(C44=$G$4,$H$4, if(C44=$G$5,$H$5,if(C44=$G$6,$H$6, " "))))) -> I | E44: =CONCATENATE(B44,"/",D44,"/",M44) -> FA033/I/01 | F44: MESIN ABSEN FINGER SPOA REVO 163BNC | G44: 43557 | H44: 1200000 | L44: BSD | M44: =if(L44=$J$2,$K$2,if(L44=$J$3,$K$3,if(L44=$J$4,$K$4," "))) -> 01 | N44: Revo | R44: Lost/ Missing
A45: 34 | B45: FA034 | C45: Laptop and Komp | D45: =if(C45=$G$2,$H$2, if(C45=$G$3,$H$3, if(C45=$G$4,$H$4, if(C45=$G$5,$H$5,if(C45=$G$6,$H$6, " "))))) -> III | E45: =CONCATENATE(B45,"/",D45,"/",M45) -> FA034/III/02 | F45: LAPTOP ASUS A407 MA N4000 4GB 128 SSD 14' | G45: 43563 | H45: 4116265 | J45: Rino | K45: Supply Chain | L45: Deltamas 1 | M45: =if(L45=$J$2,$K$2,if(L45=$J$3,$K$3,if(L45=$J$4,$K$4," "))) -> 02 | N45: Asus | R45: Active
A46: 35 | B46: FA035 | C46: Elektronik | D46: =if(C46=$G$2,$H$2, if(C46=$G$3,$H$3, if(C46=$G$4,$H$4, if(C46=$G$5,$H$5,if(C46=$G$6,$H$6, " "))))) -> I | E46: =CONCATENATE(B46,"/",D46,"/",M46) -> FA035/I/02 | F46: AC GREE GWC 05C3E INDOOR + OUTDOOR (1/2 PK) | G46: 43679 | H46: 2799000 | J46: Rino | K46: HRGA & Legal | L46: Deltamas 1 | M46: =if(L46=$J$2,$K$2,if(L46=$J$3,$K$3,if(L46=$J$4,$K$4," "))) -> 02 | N46: Gree | R46: Active
A47: 36 | B47: FA036.1 | C47: Elektronik | D47: =if(C47=$G$2,$H$2, if(C47=$G$3,$H$3, if(C47=$G$4,$H$4, if(C47=$G$5,$H$5,if(C47=$G$6,$H$6, " "))))) -> I | E47: =CONCATENATE(B47,"/",D47,"/",M47) -> FA036.1/I/02 | F47: AC GREE GWC 09C3E INDOOR + OUTDOOR (1 PK) | G47: 43679 | H47: 3049000 | J47: Rino | K47: HRGA & Legal | L47: Deltamas 1 | M47: =if(L47=$J$2,$K$2,if(L47=$J$3,$K$3,if(L47=$J$4,$K$4," "))) -> 02 | N47: Gree | R47: Active
A48: 37 | B48: FA036.2 | C48: Elektronik | D48: =if(C48=$G$2,$H$2, if(C48=$G$3,$H$3, if(C48=$G$4,$H$4, if(C48=$G$5,$H$5,if(C48=$G$6,$H$6, " "))))) -> I | E48: =CONCATENATE(B48,"/",D48,"/",M48) -> FA036.2/I/02 | F48: AC GREE GWC 09C3E INDOOR + OUTDOOR (1 PK) | G48: 43679 | H48: 3049000 | J48: Rino | K48: HRGA & Legal | L48: Deltamas 1 | M48: =if(L48=$J$2,$K$2,if(L48=$J$3,$K$3,if(L48=$J$4,$K$4," "))) -> 02 | N48: Gree | R48: Active
A49: 38 | B49: FA036.3 | C49: Elektronik | D49: =if(C49=$G$2,$H$2, if(C49=$G$3,$H$3, if(C49=$G$4,$H$4, if(C49=$G$5,$H$5,if(C49=$G$6,$H$6, " "))))) -> I | E49: =CONCATENATE(B49,"/",D49,"/",M49) -> FA036.3/I/03 | F49: AC GREE GWC 09C3E INDOOR + OUTDOOR (1 PK) | G49: 43679 | H49: 3049000 | J49: Rino | K49: HRGA & Legal | L49: Deltamas 2 | M49: =if(L49=$J$2,$K$2,if(L49=$J$3,$K$3,if(L49=$J$4,$K$4," "))) -> 03 | N49: Gree | R49: Active
A50: 39 | B50: FA037 | C50: Elektronik | D50: =if(C50=$G$2,$H$2, if(C50=$G$3,$H$3, if(C50=$G$4,$H$4, if(C50=$G$5,$H$5,if(C50=$G$6,$H$6, " "))))) -> I | E50: =CONCATENATE(B50,"/",D50,"/",M50) -> FA037/I/02 | F50: AC GREE GKH 48K3H INDDOOR + OUTDOOR (5 PK) | G50: 43679 | L50: Deltamas 1 | M50: =if(L50=$J$2,$K$2,if(L50=$J$3,$K$3,if(L50=$J$4,$K$4," "))) -> 02 | N50: Gree | R50: Sell | S50: 22500000
A51: 40 | B51: FA038.1 | C51: Furniture | D51: =if(C51=$G$2,$H$2, if(C51=$G$3,$H$3, if(C51=$G$4,$H$4, if(C51=$G$5,$H$5,if(C51=$G$6,$H$6, " "))))) -> II | E51: =CONCATENATE(B51,"/",D51,"/",M51) -> FA038.1/II/02 | F51: KNOXHULT BASE CB W DRS/DRW 120 WHI | G51: 43690 | H51: 2550000 | L51: Deltamas 1 | M51: =if(L51=$J$2,$K$2,if(L51=$J$3,$K$3,if(L51=$J$4,$K$4," "))) -> 02 | R51: Broken
A52: 41 | B52: FA038.2 | C52: Furniture | D52: =if(C52=$G$2,$H$2, if(C52=$G$3,$H$3, if(C52=$G$4,$H$4, if(C52=$G$5,$H$5,if(C52=$G$6,$H$6, " "))))) -> II | E52: =CONCATENATE(B52,"/",D52,"/",M52) -> FA038.2/II/03 | F52: KNOXHULT BASE CB W DOORS 80X85 WHITE AP | G52: 43690 | H52: 1500000 | J52: Rino | K52: HRGA & Legal | L52: Deltamas 2 | M52: =if(L52=$J$2,$K$2,if(L52=$J$3,$K$3,if(L52=$J$4,$K$4," "))) -> 03 | N52: Knoxhult | R52: Active
A53: 42 | B53: FA039.1 | C53: Furniture | D53: =if(C53=$G$2,$H$2, if(C53=$G$3,$H$3, if(C53=$G$4,$H$4, if(C53=$G$5,$H$5,if(C53=$G$6,$H$6, " "))))) -> II | E53: =CONCATENATE(B53,"/",D53,"/",M53) -> FA039.1/II/01 | F53: LOMO WORKING CHAIR LOW BACK BL 15 | G53: 43692 | H53: 799500 | J53: Herfian | K53: Engineering | L53: BSD | M53: =if(L53=$J$2,$K$2,if(L53=$J$3,$K$3,if(L53=$J$4,$K$4," "))) -> 01 | N53: Informa | R53: Active
A54: 43 | B54: FA039.2 | C54: Furniture | D54: =if(C54=$G$2,$H$2, if(C54=$G$3,$H$3, if(C54=$G$4,$H$4, if(C54=$G$5,$H$5,if(C54=$G$6,$H$6, " "))))) -> II | E54: =CONCATENATE(B54,"/",D54,"/",M54) -> FA039.2/II/01 | F54: LOMO WORKING CHAIR LOW BACK BL 15 | G54: 43692 | H54: 799500 | J54: Bilkis Ismail | K54: PITD | L54: BSD | M54: =if(L54=$J$2,$K$2,if(L54=$J$3,$K$3,if(L54=$J$4,$K$4," "))) -> 01 | N54: Informa | R54: Active
A55: 44 | B55: FA039.3 | C55: Furniture | D55: =if(C55=$G$2,$H$2, if(C55=$G$3,$H$3, if(C55=$G$4,$H$4, if(C55=$G$5,$H$5,if(C55=$G$6,$H$6, " "))))) -> II | E55: =CONCATENATE(B55,"/",D55,"/",M55) -> FA039.3/II/01 | F55: LOMO WORKING CHAIR LOW BACK BL 15 | G55: 43692 | H55: 799500 | K55: Finance & Accounting | L55: BSD | M55: =if(L55=$J$2,$K$2,if(L55=$J$3,$K$3,if(L55=$J$4,$K$4," "))) -> 01 | N55: Informa | R55: Active
A56: 45 | B56: FA039.4 | C56: Furniture | D56: =if(C56=$G$2,$H$2, if(C56=$G$3,$H$3, if(C56=$G$4,$H$4, if(C56=$G$5,$H$5,if(C56=$G$6,$H$6, " "))))) -> II | E56: =CONCATENATE(B56,"/",D56,"/",M56) -> FA039.4/II/01 | F56: LOMO WORKING CHAIR LOW BACK BL 15 | G56: 43692 | H56: 799500 | J56: Audrey | K56: Finance & Accounting | L56: BSD | M56: =if(L56=$J$2,$K$2,if(L56=$J$3,$K$3,if(L56=$J$4,$K$4," "))) -> 01 | N56: Informa | R56: Active
A57: 46 | B57: FA039.5 | C57: Furniture | D57: =if(C57=$G$2,$H$2, if(C57=$G$3,$H$3, if(C57=$G$4,$H$4, if(C57=$G$5,$H$5,if(C57=$G$6,$H$6, " "))))) -> II | E57: =CONCATENATE(B57,"/",D57,"/",M57) -> FA039.5/II/01 | F57: LOMO WORKING CHAIR LOW BACK BL 15 | G57: 43692 | H57: 799500 | J57: Daniella | K57: HRGA & Legal | L57: BSD | M57: =if(L57=$J$2,$K$2,if(L57=$J$3,$K$3,if(L57=$J$4,$K$4," "))) -> 01 | N57: Informa | R57: Active
A58: 47 | B58: FA039.6 | C58: Furniture | D58: =if(C58=$G$2,$H$2, if(C58=$G$3,$H$3, if(C58=$G$4,$H$4, if(C58=$G$5,$H$5,if(C58=$G$6,$H$6, " "))))) -> II | E58: =CONCATENATE(B58,"/",D58,"/",M58) -> FA039.6/II/01 | F58: LOMO WORKING CHAIR LOW BACK BL 15 | G58: 43692 | H58: 799500 | K58: PITD | L58: BSD | M58: =if(L58=$J$2,$K$2,if(L58=$J$3,$K$3,if(L58=$J$4,$K$4," "))) -> 01 | N58: Informa | R58: Active
A59: 48 | B59: FA039.7 | C59: Furniture | D59: =if(C59=$G$2,$H$2, if(C59=$G$3,$H$3, if(C59=$G$4,$H$4, if(C59=$G$5,$H$5,if(C59=$G$6,$H$6, " "))))) -> II | E59: =CONCATENATE(B59,"/",D59,"/",M59) -> FA039.7/II/01 | F59: LOMO WORKING CHAIR LOW BACK BL 15 | G59: 43692 | H59: 799500 | J59: Hari TM | K59: Engineering | L59: BSD | M59: =if(L59=$J$2,$K$2,if(L59=$J$3,$K$3,if(L59=$J$4,$K$4," "))) -> 01 | N59: Informa
A60: 49 | B60: FA039.8 | C60: Furniture | D60: =if(C60=$G$2,$H$2, if(C60=$G$3,$H$3, if(C60=$G$4,$H$4, if(C60=$G$5,$H$5,if(C60=$G$6,$H$6, " "))))) -> II | E60: =CONCATENATE(B60,"/",D60,"/",M60) -> FA039.8/II/01 | F60: LOMO WORKING CHAIR LOW BACK BL 15 | G60: 43692 | H60: 799500 | J60: Arina | K60: HRGA & Legal | L60: BSD | M60: =if(L60=$J$2,$K$2,if(L60=$J$3,$K$3,if(L60=$J$4,$K$4," "))) -> 01 | N60: Informa | R60: Active
A61: 50 | B61: FA039.9 | C61: Furniture | D61: =if(C61=$G$2,$H$2, if(C61=$G$3,$H$3, if(C61=$G$4,$H$4, if(C61=$G$5,$H$5,if(C61=$G$6,$H$6, " "))))) -> II | E61: =CONCATENATE(B61,"/",D61,"/",M61) -> FA039.9/II/01 | F61: NEWVY 4 TIER BLACK | G61: 43692 | H61: 759000 | J61: Chendy | K61: BOD | L61: BSD | M61: =if(L61=$J$2,$K$2,if(L61=$J$3,$K$3,if(L61=$J$4,$K$4," "))) -> 01 | N61: Informa | R61: Active
A62: 51 | B62: FA040.1 | C62: Furniture | D62: =if(C62=$G$2,$H$2, if(C62=$G$3,$H$3, if(C62=$G$4,$H$4, if(C62=$G$5,$H$5,if(C62=$G$6,$H$6, " "))))) -> II | E62: =CONCATENATE(B62,"/",D62,"/",M62) -> FA040.1/II/01 | F62: ZEDD STAFF CHAIR LOW BACK GREY | G62: 43692 | H62: 899500 | K62: HRGA & Legal | L62: BSD | M62: =if(L62=$J$2,$K$2,if(L62=$J$3,$K$3,if(L62=$J$4,$K$4," "))) -> 01 | N62: Informa | R62: Active
A63: 52 | B63: FA040.2 | C63: Furniture | D63: =if(C63=$G$2,$H$2, if(C63=$G$3,$H$3, if(C63=$G$4,$H$4, if(C63=$G$5,$H$5,if(C63=$G$6,$H$6, " "))))) -> II | E63: =CONCATENATE(B63,"/",D63,"/",M63) -> FA040.2/II/01 | F63: ZEDD STAFF CHAIR LOW BACK GREY | G63: 43692 | H63: 899500 | J63: Chendy | K63: BOD | L63: BSD | M63: =if(L63=$J$2,$K$2,if(L63=$J$3,$K$3,if(L63=$J$4,$K$4," "))) -> 01 | N63: Informa | R63: Active
A64: 53 | B64: FA040.3 | C64: Furniture | D64: =if(C64=$G$2,$H$2, if(C64=$G$3,$H$3, if(C64=$G$4,$H$4, if(C64=$G$5,$H$5,if(C64=$G$6,$H$6, " "))))) -> II | E64: =CONCATENATE(B64,"/",D64,"/",M64) -> FA040.3/II/01 | F64: ZEDD STAFF CHAIR LOW BACK GREY | G64: 43692 | H64: 899500 | J64: Rubi | K64: PITD | L64: BSD | M64: =if(L64=$J$2,$K$2,if(L64=$J$3,$K$3,if(L64=$J$4,$K$4," "))) -> 01 | N64: Informa | R64: Active
A65: 54 | B65: FA040.4 | C65: Furniture | D65: =if(C65=$G$2,$H$2, if(C65=$G$3,$H$3, if(C65=$G$4,$H$4, if(C65=$G$5,$H$5,if(C65=$G$6,$H$6, " "))))) -> II | E65: =CONCATENATE(B65,"/",D65,"/",M65) -> FA040.4/II/01 | F65: ZEDD STAFF CHAIR LOW BACK GREY | G65: 43692 | H65: 899500 | K65: Business & Digital Development | L65: BSD | M65: =if(L65=$J$2,$K$2,if(L65=$J$3,$K$3,if(L65=$J$4,$K$4," "))) -> 01 | N65: Informa | R65: Active
A66: 55 | B66: FA040.5 | C66: Furniture | D66: =if(C66=$G$2,$H$2, if(C66=$G$3,$H$3, if(C66=$G$4,$H$4, if(C66=$G$5,$H$5,if(C66=$G$6,$H$6, " "))))) -> II | E66: =CONCATENATE(B66,"/",D66,"/",M66) -> FA040.5/II/01 | F66: ZEDD STAFF CHAIR LOW BACK GREY | G66: 43692 | H66: 899500 | L66: BSD | M66: =if(L66=$J$2,$K$2,if(L66=$J$3,$K$3,if(L66=$J$4,$K$4," "))) -> 01 | N66: Informa | R66: Broken
A67: 56 | B67: FA040.6 | C67: Furniture | D67: =if(C67=$G$2,$H$2, if(C67=$G$3,$H$3, if(C67=$G$4,$H$4, if(C67=$G$5,$H$5,if(C67=$G$6,$H$6, " "))))) -> II | E67: =CONCATENATE(B67,"/",D67,"/",M67) -> FA040.6/II/01 | F67: ZEDD STAFF CHAIR LOW BACK GREY | G67: 43692 | H67: 899500 | L67: BSD | M67: =if(L67=$J$2,$K$2,if(L67=$J$3,$K$3,if(L67=$J$4,$K$4," "))) -> 01 | N67: Informa | R67: Broken
A68: 57 | B68: FA040.7 | C68: Furniture | D68: =if(C68=$G$2,$H$2, if(C68=$G$3,$H$3, if(C68=$G$4,$H$4, if(C68=$G$5,$H$5,if(C68=$G$6,$H$6, " "))))) -> II | E68: =CONCATENATE(B68,"/",D68,"/",M68) -> FA040.7/II/01 | F68: ZEDD STAFF CHAIR LOW BACK GREY | G68: 43692 | H68: 899500 | L68: BSD | M68: =if(L68=$J$2,$K$2,if(L68=$J$3,$K$3,if(L68=$J$4,$K$4," "))) -> 01 | N68: Informa | R68: Broken
A69: 58 | B69: FA040.8 | C69: Furniture | D69: =if(C69=$G$2,$H$2, if(C69=$G$3,$H$3, if(C69=$G$4,$H$4, if(C69=$G$5,$H$5,if(C69=$G$6,$H$6, " "))))) -> II | E69: =CONCATENATE(B69,"/",D69,"/",M69) -> FA040.8/II/01 | F69: ZEDD STAFF CHAIR LOW BACK GREY | G69: 43692 | H69: 899500 | L69: BSD | M69: =if(L69=$J$2,$K$2,if(L69=$J$3,$K$3,if(L69=$J$4,$K$4," "))) -> 01 | N69: Informa | R69: Broken
A70: 59 | B70: FA040.9 | C70: Furniture | D70: =if(C70=$G$2,$H$2, if(C70=$G$3,$H$3, if(C70=$G$4,$H$4, if(C70=$G$5,$H$5,if(C70=$G$6,$H$6, " "))))) -> II | E70: =CONCATENATE(B70,"/",D70,"/",M70) -> FA040.9/II/01 | F70: MELVILLE BAR TABLE 180X70X105 CM BROWN | G70: 43692 | H70: 2999000 | J70: Dimas | K70: HRGA & Legal | L70: BSD | M70: =if(L70=$J$2,$K$2,if(L70=$J$3,$K$3,if(L70=$J$4,$K$4," "))) -> 01 | R70: Active
A71: 60 | B71: FA040.10 | C71: Furniture | D71: =if(C71=$G$2,$H$2, if(C71=$G$3,$H$3, if(C71=$G$4,$H$4, if(C71=$G$5,$H$5,if(C71=$G$6,$H$6, " "))))) -> II | E71: =CONCATENATE(B71,"/",D71,"/",M71) -> FA040.10/II/01 | F71: LAREDO BAR CHAIR BLACK | G71: 43692 | H71: 389000 | J71: Dimas | K71: HRGA & Legal | L71: BSD | M71: =if(L71=$J$2,$K$2,if(L71=$J$3,$K$3,if(L71=$J$4,$K$4," "))) -> 01 | N71: Informa | R71: Active
A72: 61 | B72: FA040.11 | C72: Furniture | D72: =if(C72=$G$2,$H$2, if(C72=$G$3,$H$3, if(C72=$G$4,$H$4, if(C72=$G$5,$H$5,if(C72=$G$6,$H$6, " "))))) -> II | E72: =CONCATENATE(B72,"/",D72,"/",M72) -> FA040.11/II/01 | F72: LAREDO BAR CHAIR BLACK | G72: 43692 | H72: 389000 | J72: Dimas | K72: HRGA & Legal | L72: BSD | M72: =if(L72=$J$2,$K$2,if(L72=$J$3,$K$3,if(L72=$J$4,$K$4," "))) -> 01 | N72: Informa | R72: Active
A73: 62 | B73: FA040.12 | C73: Furniture | D73: =if(C73=$G$2,$H$2, if(C73=$G$3,$H$3, if(C73=$G$4,$H$4, if(C73=$G$5,$H$5,if(C73=$G$6,$H$6, " "))))) -> II | E73: =CONCATENATE(B73,"/",D73,"/",M73) -> FA040.12/II/01 | F73: LAREDO BAR CHAIR BLACK | G73: 43692 | H73: 389000 | J73: Dimas | K73: HRGA & Legal | L73: BSD | M73: =if(L73=$J$2,$K$2,if(L73=$J$3,$K$3,if(L73=$J$4,$K$4," "))) -> 01 | N73: Informa | R73: Active
A74: 63 | B74: FA040.13 | C74: Furniture | D74: =if(C74=$G$2,$H$2, if(C74=$G$3,$H$3, if(C74=$G$4,$H$4, if(C74=$G$5,$H$5,if(C74=$G$6,$H$6, " "))))) -> II | E74: =CONCATENATE(B74,"/",D74,"/",M74) -> FA040.13/II/01 | F74: LAREDO BAR CHAIR BLACK | G74: 43692 | H74: 389000 | J74: Dimas | K74: HRGA & Legal | L74: BSD | M74: =if(L74=$J$2,$K$2,if(L74=$J$3,$K$3,if(L74=$J$4,$K$4," "))) -> 01 | N74: Informa | R74: Active
A75: 64 | B75: FA040.14 | C75: Furniture | D75: =if(C75=$G$2,$H$2, if(C75=$G$3,$H$3, if(C75=$G$4,$H$4, if(C75=$G$5,$H$5,if(C75=$G$6,$H$6, " "))))) -> II | E75: =CONCATENATE(B75,"/",D75,"/",M75) -> FA040.14/II/01 | F75: LAREDO BAR CHAIR BLACK | G75: 43692 | H75: 389000 | J75: Dimas | K75: HRGA & Legal | L75: BSD | M75: =if(L75=$J$2,$K$2,if(L75=$J$3,$K$3,if(L75=$J$4,$K$4," "))) -> 01 | N75: Informa | R75: Active
A76: 65 | B76: FA040.15 | C76: Furniture | D76: =if(C76=$G$2,$H$2, if(C76=$G$3,$H$3, if(C76=$G$4,$H$4, if(C76=$G$5,$H$5,if(C76=$G$6,$H$6, " "))))) -> II | E76: =CONCATENATE(B76,"/",D76,"/",M76) -> FA040.15/II/01 | F76: LAREDO BAR CHAIR BLACK | G76: 43692 | H76: 389000 | J76: Dimas | K76: HRGA & Legal | L76: BSD | M76: =if(L76=$J$2,$K$2,if(L76=$J$3,$K$3,if(L76=$J$4,$K$4," "))) -> 01 | N76: Informa | R76: Active
A77: 66 | B77: FA040.16 | C77: Furniture | D77: =if(C77=$G$2,$H$2, if(C77=$G$3,$H$3, if(C77=$G$4,$H$4, if(C77=$G$5,$H$5,if(C77=$G$6,$H$6, " "))))) -> II | E77: =CONCATENATE(B77,"/",D77,"/",M77) -> FA040.16/II/01 | F77: HECTOR OFFICE TABLE WALNUT BLACK | G77: 43692 | H77: 999000 | J77: Hari TM | K77: Engineering | L77: BSD | M77: =if(L77=$J$2,$K$2,if(L77=$J$3,$K$3,if(L77=$J$4,$K$4," "))) -> 01 | N77: Informa | R77: Active
A78: 67 | B78: FA040.17 | C78: Furniture | D78: =if(C78=$G$2,$H$2, if(C78=$G$3,$H$3, if(C78=$G$4,$H$4, if(C78=$G$5,$H$5,if(C78=$G$6,$H$6, " "))))) -> II | E78: =CONCATENATE(B78,"/",D78,"/",M78) -> FA040.17/II/01 | F78: HECTOR OFFICE TABLE WALNUT BLACK | G78: 43692 | H78: 999000 | K78: PITD | L78: BSD | M78: =if(L78=$J$2,$K$2,if(L78=$J$3,$K$3,if(L78=$J$4,$K$4," "))) -> 01 | N78: Informa | R78: Active
A79: 68 | B79: FA040.18 | C79: Furniture | D79: =if(C79=$G$2,$H$2, if(C79=$G$3,$H$3, if(C79=$G$4,$H$4, if(C79=$G$5,$H$5,if(C79=$G$6,$H$6, " "))))) -> II | E79: =CONCATENATE(B79,"/",D79,"/",M79) -> FA040.18/II/01 | F79: HECTOR OFFICE TABLE WALNUT BLACK | G79: 43692 | H79: 999000 | K79: Finance & Accounting | L79: BSD | M79: =if(L79=$J$2,$K$2,if(L79=$J$3,$K$3,if(L79=$J$4,$K$4," "))) -> 01 | N79: Informa | R79: Active
A80: 69 | B80: FA040.19 | C80: Furniture | D80: =if(C80=$G$2,$H$2, if(C80=$G$3,$H$3, if(C80=$G$4,$H$4, if(C80=$G$5,$H$5,if(C80=$G$6,$H$6, " "))))) -> II | E80: =CONCATENATE(B80,"/",D80,"/",M80) -> FA040.19/II/01 | F80: HECTOR OFFICE TABLE WALNUT BLACK | G80: 43692 | H80: 999000 | J80: Rubi | K80: PITD | L80: BSD | M80: =if(L80=$J$2,$K$2,if(L80=$J$3,$K$3,if(L80=$J$4,$K$4," "))) -> 01 | N80: Informa | R80: Active
A81: 70 | B81: FA040.20 | C81: Furniture | D81: =if(C81=$G$2,$H$2, if(C81=$G$3,$H$3, if(C81=$G$4,$H$4, if(C81=$G$5,$H$5,if(C81=$G$6,$H$6, " "))))) -> II | E81: =CONCATENATE(B81,"/",D81,"/",M81) -> FA040.20/II/01 | F81: HECTOR OFFICE TABLE WALNUT BLACK | G81: 43692 | H81: 999000 | J81: Marcel | K81: PITD | L81: BSD | M81: =if(L81=$J$2,$K$2,if(L81=$J$3,$K$3,if(L81=$J$4,$K$4," "))) -> 01 | N81: Informa | R81: Active
A82: 71 | B82: FA040.21 | C82: Furniture | D82: =if(C82=$G$2,$H$2, if(C82=$G$3,$H$3, if(C82=$G$4,$H$4, if(C82=$G$5,$H$5,if(C82=$G$6,$H$6, " "))))) -> II | E82: =CONCATENATE(B82,"/",D82,"/",M82) -> FA040.21/II/01 | F82: HECTOR OFFICE TABLE WALNUT BLACK | G82: 43692 | H82: 999000 | J82: Rifky Fauzi | K82: Engineering | L82: BSD | M82: =if(L82=$J$2,$K$2,if(L82=$J$3,$K$3,if(L82=$J$4,$K$4," "))) -> 01 | N82: Informa | R82: Active
A83: 72 | B83: FA040.22 | C83: Furniture | D83: =if(C83=$G$2,$H$2, if(C83=$G$3,$H$3, if(C83=$G$4,$H$4, if(C83=$G$5,$H$5,if(C83=$G$6,$H$6, " "))))) -> II | E83: =CONCATENATE(B83,"/",D83,"/",M83) -> FA040.22/II/01 | F83: HECTOR OFFICE TABLE WALNUT BLACK | G83: 43692 | H83: 999000 | J83: Fitria | K83: Finance & Accounting | L83: BSD | M83: =if(L83=$J$2,$K$2,if(L83=$J$3,$K$3,if(L83=$J$4,$K$4," "))) -> 01 | N83: Informa | R83: Active
A84: 73 | B84: FA040.23 | C84: Furniture | D84: =if(C84=$G$2,$H$2, if(C84=$G$3,$H$3, if(C84=$G$4,$H$4, if(C84=$G$5,$H$5,if(C84=$G$6,$H$6, " "))))) -> II | E84: =CONCATENATE(B84,"/",D84,"/",M84) -> FA040.23/II/01 | F84: MAINE DSTP+MDSTY MGR DESK 160 KW-R(P1/3) | G84: 43692 | H84: 1942000 | L84: BSD | M84: =if(L84=$J$2,$K$2,if(L84=$J$3,$K$3,if(L84=$J$4,$K$4," "))) -> 01
A85: 74 | B85: FA040.24 | C85: Furniture | D85: =if(C85=$G$2,$H$2, if(C85=$G$3,$H$3, if(C85=$G$4,$H$4, if(C85=$G$5,$H$5,if(C85=$G$6,$H$6, " "))))) -> II | E85: =CONCATENATE(B85,"/",D85,"/",M85) -> FA040.24/II/01 | F85: MAINE LEG+HRDWR MGR DESK 160 KW-R (P2/3) | G85: 43692 | H85: 771000 | L85: BSD | M85: =if(L85=$J$2,$K$2,if(L85=$J$3,$K$3,if(L85=$J$4,$K$4," "))) -> 01 | R85: Lost/ Missing
A86: 75 | B86: FA040.25 | C86: Furniture | D86: =if(C86=$G$2,$H$2, if(C86=$G$3,$H$3, if(C86=$G$4,$H$4, if(C86=$G$5,$H$5,if(C86=$G$6,$H$6, " "))))) -> II | E86: =CONCATENATE(B86,"/",D86,"/",M86) -> FA040.25/II/01 | F86: MAINE RETURN MANAGER DESK 160 KW-R(P3/3 | G86: 43692 | H86: 1286000 | L86: BSD | M86: =if(L86=$J$2,$K$2,if(L86=$J$3,$K$3,if(L86=$J$4,$K$4," "))) -> 01 | R86: Lost/ Missing
A87: 76 | B87: FA040.26 | C87: Furniture | D87: =if(C87=$G$2,$H$2, if(C87=$G$3,$H$3, if(C87=$G$4,$H$4, if(C87=$G$5,$H$5,if(C87=$G$6,$H$6, " "))))) -> II | E87: =CONCATENATE(B87,"/",D87,"/",M87) -> FA040.26/II/01 | F87: MAINE DESKTOP+MDSTY STFDSK 140KW (P1/3) | G87: 43692 | H87: 1016000 | J87: Joseline | K87: BOD | L87: BSD | M87: =if(L87=$J$2,$K$2,if(L87=$J$3,$K$3,if(L87=$J$4,$K$4," "))) -> 01 | R87: Active
A88: 77 | B88: FA040.27 | C88: Furniture | D88: =if(C88=$G$2,$H$2, if(C88=$G$3,$H$3, if(C88=$G$4,$H$4, if(C88=$G$5,$H$5,if(C88=$G$6,$H$6, " "))))) -> II | E88: =CONCATENATE(B88,"/",D88,"/",M88) -> FA040.27/II/01 | F88: MAINE PEDESTAL STAFF DSK 140 KW (P3/3) | G88: 43692 | H88: 883000 | J88: Joseline | K88: BOD | L88: BSD | M88: =if(L88=$J$2,$K$2,if(L88=$J$3,$K$3,if(L88=$J$4,$K$4," "))) -> 01 | R88: Active
A89: 78 | B89: FA040.28 | C89: Furniture | D89: =if(C89=$G$2,$H$2, if(C89=$G$3,$H$3, if(C89=$G$4,$H$4, if(C89=$G$5,$H$5,if(C89=$G$6,$H$6, " "))))) -> II | E89: =CONCATENATE(B89,"/",D89,"/",M89) -> FA040.28/II/01 | F89: MAINE LEG+HRDWR STF DESK 140 KW (P2/3) | G89: 43692 | H89: 800000 | J89: Joseline | K89: BOD | L89: BSD | M89: =if(L89=$J$2,$K$2,if(L89=$J$3,$K$3,if(L89=$J$4,$K$4," "))) -> 01 | R89: Active
A90: 79 | B90: FA040.29 | C90: Furniture | D90: =if(C90=$G$2,$H$2, if(C90=$G$3,$H$3, if(C90=$G$4,$H$4, if(C90=$G$5,$H$5,if(C90=$G$6,$H$6, " "))))) -> II | E90: =CONCATENATE(B90,"/",D90,"/",M90) -> FA040.29/II/01 | F90: DESKTOP SIEBEN RECT MTG 2412 CO (P1/3) | G90: 43692 | H90: 2099000 | J90: Hari TM | K90: Engineering | L90: BSD | M90: =if(L90=$J$2,$K$2,if(L90=$J$3,$K$3,if(L90=$J$4,$K$4," "))) -> 01 | R90: Active
A91: 80 | B91: FA040.30 | C91: Furniture | D91: =if(C91=$G$2,$H$2, if(C91=$G$3,$H$3, if(C91=$G$4,$H$4, if(C91=$G$5,$H$5,if(C91=$G$6,$H$6, " "))))) -> II | E91: =CONCATENATE(B91,"/",D91,"/",M91) -> FA040.30/II/01 | F91: LEG SIEBEN RECT MTG 2412 CO (P2/3) | G91: 43692 | H91: 1600000 | L91: BSD | M91: =if(L91=$J$2,$K$2,if(L91=$J$3,$K$3,if(L91=$J$4,$K$4," "))) -> 01 | R91: Lost/ Missing
A92: 81 | B92: FA040.31 | C92: Furniture | D92: =if(C92=$G$2,$H$2, if(C92=$G$3,$H$3, if(C92=$G$4,$H$4, if(C92=$G$5,$H$5,if(C92=$G$6,$H$6, " "))))) -> II | E92: =CONCATENATE(B92,"/",D92,"/",M92) -> FA040.31/II/01 | F92: BEAM SIEBEN RECT MTG 2412 CO (P3/3) | G92: 43692 | H92: 900000 | L92: BSD | M92: =if(L92=$J$2,$K$2,if(L92=$J$3,$K$3,if(L92=$J$4,$K$4," "))) -> 01 | R92: Lost/ Missing
A93: 82 | B93: FA041 | C93: Elektronik | D93: =if(C93=$G$2,$H$2, if(C93=$G$3,$H$3, if(C93=$G$4,$H$4, if(C93=$G$5,$H$5,if(C93=$G$6,$H$6, " "))))) -> I | E93: =CONCATENATE(B93,"/",D93,"/",M93) -> FA041/I/01 | F93: MICROWAVE | G93: 43313 | H93: 1250000 | J93: Dimas | K93: HRGA & Legal | L93: BSD | M93: =if(L93=$J$2,$K$2,if(L93=$J$3,$K$3,if(L93=$J$4,$K$4," "))) -> 01 | R93: Active
A94: 83 | B94: FA042 | C94: Elektronik | D94: =if(C94=$G$2,$H$2, if(C94=$G$3,$H$3, if(C94=$G$4,$H$4, if(C94=$G$5,$H$5,if(C94=$G$6,$H$6, " "))))) -> I | E94: =CONCATENATE(B94,"/",D94,"/",M94) -> FA042/I/01 | F94: DISPENSER | G94: 43678 | H94: 290000 | L94: BSD | M94: =if(L94=$J$2,$K$2,if(L94=$J$3,$K$3,if(L94=$J$4,$K$4," "))) -> 01 | R94: Broken | S94: Bocor
A95: 84 | B95: FA043 | C95: Elektronik | D95: =if(C95=$G$2,$H$2, if(C95=$G$3,$H$3, if(C95=$G$4,$H$4, if(C95=$G$5,$H$5,if(C95=$G$6,$H$6, " "))))) -> I | E95: =CONCATENATE(B95,"/",D95,"/",M95) -> FA043/I/02 | F95: CCTV CAMERA (6) + DVR 8 TITIK + HARDISK 500GB | G95: 43711 | H95: 3270000 | L95: Deltamas 1 | M95: =if(L95=$J$2,$K$2,if(L95=$J$3,$K$3,if(L95=$J$4,$K$4," "))) -> 02 | R95: Broken
A96: 85 | B96: FA044 | C96: Elektronik | D96: =if(C96=$G$2,$H$2, if(C96=$G$3,$H$3, if(C96=$G$4,$H$4, if(C96=$G$5,$H$5,if(C96=$G$6,$H$6, " "))))) -> I | E96: =CONCATENATE(B96,"/",D96,"/",M96) -> FA044/I/01 | F96: HP PRINTER 2135 | G96: 43711 | H96: 565000 | J96: Chendy | K96: BOD | L96: BSD | M96: =if(L96=$J$2,$K$2,if(L96=$J$3,$K$3,if(L96=$J$4,$K$4," "))) -> 01 | N96: HP | Q96: Rumah Pak Chendy | R96: Active
A97: 86 | B97: FA045 | C97: Machine and Tooling | D97: =if(C97=$G$2,$H$2, if(C97=$G$3,$H$3, if(C97=$G$4,$H$4, if(C97=$G$5,$H$5,if(C97=$G$6,$H$6, " "))))) -> V | E97: =CONCATENATE(B97,"/",D97,"/",M97) -> FA045/V/01 | F97: SHARK COMPRESSOR OIL FREE | G97: 43711 | H97: 1300000 | J97: Chendy | K97: BOD | L97: BSD | M97: =if(L97=$J$2,$K$2,if(L97=$J$3,$K$3,if(L97=$J$4,$K$4," "))) -> 01 | N97: Shark | Q97: Rumah Pak Chendy | R97: Active
A98: 87 | B98: FA046 | C98: Elektronik | D98: =if(C98=$G$2,$H$2, if(C98=$G$3,$H$3, if(C98=$G$4,$H$4, if(C98=$G$5,$H$5,if(C98=$G$6,$H$6, " "))))) -> I | E98: =CONCATENATE(B98,"/",D98,"/",M98) -> FA046/I/01 | F98: PHONE TAB A 8" + SILICON TAB A8" SAMSUNG | G98: 43713 | H98: 3860000 | J98: Dimas | K98: HRGA & Legal | L98: BSD | M98: =if(L98=$J$2,$K$2,if(L98=$J$3,$K$3,if(L98=$J$4,$K$4," "))) -> 01 | N98: Samsung | O98: Galaxy | R98: Active
A99: 88 | B99: FA047 | C99: Elektronik | D99: =if(C99=$G$2,$H$2, if(C99=$G$3,$H$3, if(C99=$G$4,$H$4, if(C99=$G$5,$H$5,if(C99=$G$6,$H$6, " "))))) -> I | E99: =CONCATENATE(B99,"/",D99,"/",M99) -> FA047/I/01 | F99: GIANT - TV LED 40 " (2UNIT) + BREKET (2PC) | G99: 43713 | H99: =4898000/2 -> 2449000 | J99: Daniella | K99: HRGA & Legal | L99: BSD | M99: =if(L99=$J$2,$K$2,if(L99=$J$3,$K$3,if(L99=$J$4,$K$4," "))) -> 01 | N99: TCL | R99: Active
A100: 88 | B100: FA047.1 | C100: Elektronik | D100: =if(C100=$G$2,$H$2, if(C100=$G$3,$H$3, if(C100=$G$4,$H$4, if(C100=$G$5,$H$5,if(C100=$G$6,$H$6, " "))))) -> I | E100: =CONCATENATE(B100,"/",D100,"/",M100) -> FA047.1/I/01 | F100: GIANT - TV LED 40 " (2UNIT) + BREKET (2PC) | G100: 43713 | H100: =4898000/2 -> 2449000 | J100: Daniella | K100: HRGA & Legal | L100: BSD | M100: =if(L100=$J$2,$K$2,if(L100=$J$3,$K$3,if(L100=$J$4,$K$4," "))) -> 01 | N100: TCL | Q100: Proses repair di Pak Chendy | R100: Active
A101: 88 | B101: FA047.2 | C101: Elektronik | D101: =if(C101=$G$2,$H$2, if(C101=$G$3,$H$3, if(C101=$G$4,$H$4, if(C101=$G$5,$H$5,if(C101=$G$6,$H$6, " "))))) -> I | E101: =CONCATENATE(B101,"/",D101,"/",M101) -> FA047.2/I/01 | F101: GIANT - TV LED 40 " (2UNIT) + BREKET (2PC) | G101: 43713 | H101: 4898000 | J101: Daniella | L101: BSD | M101: =if(L101=$J$2,$K$2,if(L101=$J$3,$K$3,if(L101=$J$4,$K$4," "))) -> 01
A102: 89 | B102: FA048 | C102: Elektronik | D102: =if(C102=$G$2,$H$2, if(C102=$G$3,$H$3, if(C102=$G$4,$H$4, if(C102=$G$5,$H$5,if(C102=$G$6,$H$6, " "))))) -> I | E102: =CONCATENATE(B102,"/",D102,"/",M102) -> FA048/I/01 | F102: OCULUS QUEST 64 GB | G102: 43720 | H102: 7320000 | L102: BSD | M102: =if(L102=$J$2,$K$2,if(L102=$J$3,$K$3,if(L102=$J$4,$K$4," "))) -> 01 | N102: Oculus | R102: Lost/ Missing
...

Sheet Tag Asset
B2: FA027/I/01 | D2: FA107/I/01 | F2: FA040.10/II/01 | H2: FA040.11/II/01 | J2: FA040.11/II/01 | P2: FA442/I/01 | R2: FA443/I/01 | T2: FA444/I/02 | V2: FA445/I/02
B3: =image("https://image-charts.com/chart?chs=150x150&cht=qr&choe=UTF-8&chl="&ENCODEURL(B2)) | D3: =image("https://image-charts.com/chart?chs=150x150&cht=qr&choe=UTF-8&chl="&ENCODEURL(D2)) | F3: =image("https://image-charts.com/chart?chs=150x150&cht=qr&choe=UTF-8&chl="&ENCODEURL(F2)) | H3: =image("https://image-charts.com/chart?chs=150x150&cht=qr&choe=UTF-8&chl="&ENCODEURL(H2)) | J3: =image("https://image-charts.com/chart?chs=150x150&cht=qr&choe=UTF-8&chl="&ENCODEURL(J2)) | N3: =image("https://image-charts.com/chart?chs=150x150&cht=qr&choe=UTF-8&chl="&ENCODEURL(N2)) | P3: =image("https://image-charts.com/chart?chs=150x150&cht=qr&choe=UTF-8&chl="&ENCODEURL(P2)) | R3: =image("https://image-charts.com/chart?chs=150x150&cht=qr&choe=UTF-8&chl="&ENCODEURL(R2)) | T3: =image("https://image-charts.com/chart?chs=150x150&cht=qr&choe=UTF-8&chl="&ENCODEURL(T2)) | V3: =image("https://image-charts.com/chart?chs=150x150&cht=qr&choe=UTF-8&chl="&ENCODEURL(V2))
B6: FA040.13/II/01 | D6: FA040.14/II/01 | F6: FA040.15/II/01 | H6: FA044/I/01 | J6: FA050/I/01 | N6: FA446/V/01 | P6: FA447/V/02 | R6: FA448/V/02 | T6: FA448/V/02 | V6: FA449/V/02
B7: =image("https://image-charts.com/chart?chs=150x150&cht=qr&choe=UTF-8&chl="&ENCODEURL(B6)) | D7: =image("https://image-charts.com/chart?chs=150x150&cht=qr&choe=UTF-8&chl="&ENCODEURL(D6)) | F7: =image("https://image-charts.com/chart?chs=150x150&cht=qr&choe=UTF-8&chl="&ENCODEURL(F6)) | H7: =image("https://image-charts.com/chart?chs=150x150&cht=qr&choe=UTF-8&chl="&ENCODEURL(H6)) | J7: =image("https://image-charts.com/chart?chs=150x150&cht=qr&choe=UTF-8&chl="&ENCODEURL(J6)) | N7: =image("https://image-charts.com/chart?chs=150x150&cht=qr&choe=UTF-8&chl="&ENCODEURL(N6)) | P7: =image("https://image-charts.com/chart?chs=150x150&cht=qr&choe=UTF-8&chl="&ENCODEURL(P6)) | R7: =image("https://image-charts.com/chart?chs=150x150&cht=qr&choe=UTF-8&chl="&ENCODEURL(R6)) | T7: =image("https://image-charts.com/chart?chs=150x150&cht=qr&choe=UTF-8&chl="&ENCODEURL(T6)) | V7: =image("https://image-charts.com/chart?chs=150x150&cht=qr&choe=UTF-8&chl="&ENCODEURL(V6))
B10: FA063/I/01 | D10: FA070/III/01 | F10: FA108/I/01 | H10: FA177/II/01 | J10: FA212/II/01 | N10: FA450/V/02 | P10: FA451/V/02 | R10: FA452/V/02 | T10: FA453/V/02 | V10: FA454/V/02
B11: =image("https://image-charts.com/chart?chs=150x150&cht=qr&choe=UTF-8&chl="&ENCODEURL(B10)) | D11: =image("https://image-charts.com/chart?chs=150x150&cht=qr&choe=UTF-8&chl="&ENCODEURL(D10)) | F11: =image("https://image-charts.com/chart?chs=150x150&cht=qr&choe=UTF-8&chl="&ENCODEURL(F10)) | H11: =image("https://image-charts.com/chart?chs=150x150&cht=qr&choe=UTF-8&chl="&ENCODEURL(H10)) | J11: =image("https://image-charts.com/chart?chs=150x150&cht=qr&choe=UTF-8&chl="&ENCODEURL(J10)) | N11: =image("https://image-charts.com/chart?chs=150x150&cht=qr&choe=UTF-8&chl="&ENCODEURL(N10)) | P11: =image("https://image-charts.com/chart?chs=150x150&cht=qr&choe=UTF-8&chl="&ENCODEURL(P10)) | R11: =image("https://image-charts.com/chart?chs=150x150&cht=qr&choe=UTF-8&chl="&ENCODEURL(R10)) | T11: =image("https://image-charts.com/chart?chs=150x150&cht=qr&choe=UTF-8&chl="&ENCODEURL(T10)) | V11: =image("https://image-charts.com/chart?chs=150x150&cht=qr&choe=UTF-8&chl="&ENCODEURL(V10))
B14: FA414/V/01 | D14: FA415/II/01 | F14: FA416/II/01 | H14: FA417/III/01 | J14: FA418/V/02 | N14: FA460/V/02 | P14: FA461/V/02 | R14: FA462/V/02 | T14: FA463/V/02 | V14: FA464/V/02
B15: =image("https://image-charts.com/chart?chs=150x150&cht=qr&choe=UTF-8&chl="&ENCODEURL(B14)) | D15: =image("https://image-charts.com/chart?chs=150x150&cht=qr&choe=UTF-8&chl="&ENCODEURL(D14)) | F15: =image("https://image-charts.com/chart?chs=150x150&cht=qr&choe=UTF-8&chl="&ENCODEURL(F14)) | H15: =image("https://image-charts.com/chart?chs=150x150&cht=qr&choe=UTF-8&chl="&ENCODEURL(H14)) | J15: =image("https://image-charts.com/chart?chs=150x150&cht=qr&choe=UTF-8&chl="&ENCODEURL(J14)) | N15: =image("https://image-charts.com/chart?chs=150x150&cht=qr&choe=UTF-8&chl="&ENCODEURL(N14)) | P15: =image("https://image-charts.com/chart?chs=150x150&cht=qr&choe=UTF-8&chl="&ENCODEURL(P14)) | R15: =image("https://image-charts.com/chart?chs=150x150&cht=qr&choe=UTF-8&chl="&ENCODEURL(R14)) | T15: =image("https://image-charts.com/chart?chs=150x150&cht=qr&choe=UTF-8&chl="&ENCODEURL(T14)) | V15: =image("https://image-charts.com/chart?chs=150x150&cht=qr&choe=UTF-8&chl="&ENCODEURL(V14))
B18: FA419/V/02 | D18: FA420/V/02 | F18: FA421/III/01 | H18: FA422/I/01 | J18: FA423/I/01 | N18: FA016/III/01 | P18: FA023/I/01 | R18: FA026/III/01 | T18: FA026.1/III/01 | V18: FA026.2/III/01
B19: =image("https://image-charts.com/chart?chs=150x150&cht=qr&choe=UTF-8&chl="&ENCODEURL(B18)) | D19: =image("https://image-charts.com/chart?chs=150x150&cht=qr&choe=UTF-8&chl="&ENCODEURL(D18)) | F19: =image("https://image-charts.com/chart?chs=150x150&cht=qr&choe=UTF-8&chl="&ENCODEURL(F18)) | H19: =image("https://image-charts.com/chart?chs=150x150&cht=qr&choe=UTF-8&chl="&ENCODEURL(H18)) | J19: =image("https://image-charts.com/chart?chs=150x150&cht=qr&choe=UTF-8&chl="&ENCODEURL(J18)) | N19: =image("https://image-charts.com/chart?chs=150x150&cht=qr&choe=UTF-8&chl="&ENCODEURL(N18)) | P19: =image("https://image-charts.com/chart?chs=150x150&cht=qr&choe=UTF-8&chl="&ENCODEURL(P18)) | R19: =image("https://image-charts.com/chart?chs=150x150&cht=qr&choe=UTF-8&chl="&ENCODEURL(R18)) | T19: =image("https://image-charts.com/chart?chs=150x150&cht=qr&choe=UTF-8&chl="&ENCODEURL(T18)) | V19: =image("https://image-charts.com/chart?chs=150x150&cht=qr&choe=UTF-8&chl="&ENCODEURL(V18))
B22: FA424/V/01 | D22: FA425/III/01 | F22: FA426/I/01 | H22: FA428/II/01 | J22: FA429/II/01 | N22: FA034/III/02 | P22: FA052.1/II/03 | R22: FA252/I/01 | T22: FA094/III/01 | V22: FA465/V/02
B23: =image("https://image-charts.com/chart?chs=150x150&cht=qr&choe=UTF-8&chl="&ENCODEURL(B22)) | D23: =image("https://image-charts.com/chart?chs=150x150&cht=qr&choe=UTF-8&chl="&ENCODEURL(D22)) | F23: =image("https://image-charts.com/chart?chs=150x150&cht=qr&choe=UTF-8&chl="&ENCODEURL(F22)) | H23: =image("https://image-charts.com/chart?chs=150x150&cht=qr&choe=UTF-8&chl="&ENCODEURL(H22)) | J23: =image("https://image-charts.com/chart?chs=150x150&cht=qr&choe=UTF-8&chl="&ENCODEURL(J22)) | N23: =image("https://image-charts.com/chart?chs=150x150&cht=qr&choe=UTF-8&chl="&ENCODEURL(N22)) | P23: =image("https://image-charts.com/chart?chs=150x150&cht=qr&choe=UTF-8&chl="&ENCODEURL(P22)) | R23: =image("https://image-charts.com/chart?chs=150x150&cht=qr&choe=UTF-8&chl="&ENCODEURL(R22)) | T23: =image("https://image-charts.com/chart?chs=150x150&cht=qr&choe=UTF-8&chl="&ENCODEURL(T22)) | V23: =image("https://image-charts.com/chart?chs=150x150&cht=qr&choe=UTF-8&chl="&ENCODEURL(V22))
B26: FA430/II/01 | D26: FA437/III/01 | F26: FA438/III/03 | H26: FA439/III/03 | J26: FA440/I/02 | N26: FA466/V/01 | P26: FA467/V/02 | R26: FA468/V/02 | T26: FA469/V/02 | V26: FA470/V/02
B27: =image("https://image-charts.com/chart?chs=150x150&cht=qr&choe=UTF-8&chl="&ENCODEURL(B26)) | D27: =image("https://image-charts.com/chart?chs=150x150&cht=qr&choe=UTF-8&chl="&ENCODEURL(D26)) | F27: =image("https://image-charts.com/chart?chs=150x150&cht=qr&choe=UTF-8&chl="&ENCODEURL(F26)) | H27: =image("https://image-charts.com/chart?chs=150x150&cht=qr&choe=UTF-8&chl="&ENCODEURL(H26)) | J27: =image("https://image-charts.com/chart?chs=150x150&cht=qr&choe=UTF-8&chl="&ENCODEURL(J26)) | N27: =image("https://image-charts.com/chart?chs=150x150&cht=qr&choe=UTF-8&chl="&ENCODEURL(N26)) | P27: =image("https://image-charts.com/chart?chs=150x150&cht=qr&choe=UTF-8&chl="&ENCODEURL(P26)) | R27: =image("https://image-charts.com/chart?chs=150x150&cht=qr&choe=UTF-8&chl="&ENCODEURL(R26)) | T27: =image("https://image-charts.com/chart?chs=150x150&cht=qr&choe=UTF-8&chl="&ENCODEURL(T26)) | V27: =image("https://image-charts.com/chart?chs=150x150&cht=qr&choe=UTF-8&chl="&ENCODEURL(V26))
N30: FA471/V/02 | P30: FA472/V/02 | R30: FA473/V/02 | T30: FA474/V/02 | V30: FA475/V/02
B31: =image("https://image-charts.com/chart?chs=150x150&cht=qr&choe=UTF-8&chl="&ENCODEURL(B30)) | D31: =image("https://image-charts.com/chart?chs=150x150&cht=qr&choe=UTF-8&chl="&ENCODEURL(D30)) | F31: =image("https://image-charts.com/chart?chs=150x150&cht=qr&choe=UTF-8&chl="&ENCODEURL(F30)) | H31: =image("https://image-charts.com/chart?chs=150x150&cht=qr&choe=UTF-8&chl="&ENCODEURL(H30)) | J31: =image("https://image-charts.com/chart?chs=150x150&cht=qr&choe=UTF-8&chl="&ENCODEURL(J30)) | N31: =image("https://image-charts.com/chart?chs=150x150&cht=qr&choe=UTF-8&chl="&ENCODEURL(N30)) | P31: =image("https://image-charts.com/chart?chs=150x150&cht=qr&choe=UTF-8&chl="&ENCODEURL(P30)) | R31: =image("https://image-charts.com/chart?chs=150x150&cht=qr&choe=UTF-8&chl="&ENCODEURL(R30)) | T31: =image("https://image-charts.com/chart?chs=150x150&cht=qr&choe=UTF-8&chl="&ENCODEURL(T30)) | V31: =image("https://image-charts.com/chart?chs=150x150&cht=qr&choe=UTF-8&chl="&ENCODEURL(V30))
B36: FA476/V/02 | D36: FA477/V/02 | F36: FA478/V/02 | H36: FA479/V/02 | J36: FA480/V/02 | N36: FA481/V/02 | P36: FA482/V/02 | R36: FA483/V/02 | T36: FA484/V/02 | V36: FA485/V/02
B37: =image("https://image-charts.com/chart?chs=150x150&cht=qr&choe=UTF-8&chl="&ENCODEURL(B36)) | D37: =image("https://image-charts.com/chart?chs=150x150&cht=qr&choe=UTF-8&chl="&ENCODEURL(D36)) | F37: =image("https://image-charts.com/chart?chs=150x150&cht=qr&choe=UTF-8&chl="&ENCODEURL(F36)) | H37: =image("https://image-charts.com/chart?chs=150x150&cht=qr&choe=UTF-8&chl="&ENCODEURL(H36)) | J37: =image("https://image-charts.com/chart?chs=150x150&cht=qr&choe=UTF-8&chl="&ENCODEURL(J36)) | N37: =image("https://image-charts.com/chart?chs=150x150&cht=qr&choe=UTF-8&chl="&ENCODEURL(N36)) | P37: =image("https://image-charts.com/chart?chs=150x150&cht=qr&choe=UTF-8&chl="&ENCODEURL(P36)) | R37: =image("https://image-charts.com/chart?chs=150x150&cht=qr&choe=UTF-8&chl="&ENCODEURL(R36)) | T37: =image("https://image-charts.com/chart?chs=150x150&cht=qr&choe=UTF-8&chl="&ENCODEURL(T36)) | V37: =image("https://image-charts.com/chart?chs=150x150&cht=qr&choe=UTF-8&chl="&ENCODEURL(V36))
B40: FA486/V/02 | D40: FA487/V/02 | F40: FA488/V/02 | H40: FA489/V/02 | J40: FA490/V/02 | N40: FA491/V/02 | P40: FA492/V/02 | R40: FA493/V/02 | T40: FA494/V/02 | V40: FA495/V/02
B41: =image("https://image-charts.com/chart?chs=150x150&cht=qr&choe=UTF-8&chl="&ENCODEURL(B40)) | D41: =image("https://image-charts.com/chart?chs=150x150&cht=qr&choe=UTF-8&chl="&ENCODEURL(D40)) | F41: =image("https://image-charts.com/chart?chs=150x150&cht=qr&choe=UTF-8&chl="&ENCODEURL(F40)) | H41: =image("https://image-charts.com/chart?chs=150x150&cht=qr&choe=UTF-8&chl="&ENCODEURL(H40)) | J41: =image("https://image-charts.com/chart?chs=150x150&cht=qr&choe=UTF-8&chl="&ENCODEURL(J40)) | N41: =image("https://image-charts.com/chart?chs=150x150&cht=qr&choe=UTF-8&chl="&ENCODEURL(N40)) | P41: =image("https://image-charts.com/chart?chs=150x150&cht=qr&choe=UTF-8&chl="&ENCODEURL(P40)) | R41: =image("https://image-charts.com/chart?chs=150x150&cht=qr&choe=UTF-8&chl="&ENCODEURL(R40)) | T41: =image("https://image-charts.com/chart?chs=150x150&cht=qr&choe=UTF-8&chl="&ENCODEURL(T40)) | V41: =image("https://image-charts.com/chart?chs=150x150&cht=qr&choe=UTF-8&chl="&ENCODEURL(V40))
B44: FA496/V/02 | D44: FA497/V/02 | F44: FA498/V/02 | H44: FA499/V/02 | J44: FA500/V/02 | N44: FA501/V/02
B45: =image("https://image-charts.com/chart?chs=150x150&cht=qr&choe=UTF-8&chl="&ENCODEURL(B44)) | D45: =image("https://image-charts.com/chart?chs=150x150&cht=qr&choe=UTF-8&chl="&ENCODEURL(D44)) | F45: =image("https://image-charts.com/chart?chs=150x150&cht=qr&choe=UTF-8&chl="&ENCODEURL(F44)) | H45: =image("https://image-charts.com/chart?chs=150x150&cht=qr&choe=UTF-8&chl="&ENCODEURL(H44)) | J45: =image("https://image-charts.com/chart?chs=150x150&cht=qr&choe=UTF-8&chl="&ENCODEURL(J44)) | N45: =image("https://image-charts.com/chart?chs=150x150&cht=qr&choe=UTF-8&chl="&ENCODEURL(N44)) | P45: =image("https://image-charts.com/chart?chs=150x150&cht=qr&choe=UTF-8&chl="&ENCODEURL(P44)) | R45: =image("https://image-charts.com/chart?chs=150x150&cht=qr&choe=UTF-8&chl="&ENCODEURL(R44)) | T45: =image("https://image-charts.com/chart?chs=150x150&cht=qr&choe=UTF-8&chl="&ENCODEURL(T44)) | V45: =image("https://image-charts.com/chart?chs=150x150&cht=qr&choe=UTF-8&chl="&ENCODEURL(V44))
B49: =image("https://image-charts.com/chart?chs=150x150&cht=qr&choe=UTF-8&chl="&ENCODEURL(B48)) | D49: =image("https://image-charts.com/chart?chs=150x150&cht=qr&choe=UTF-8&chl="&ENCODEURL(D48)) | F49: =image("https://image-charts.com/chart?chs=150x150&cht=qr&choe=UTF-8&chl="&ENCODEURL(F48)) | H49: =image("https://image-charts.com/chart?chs=150x150&cht=qr&choe=UTF-8&chl="&ENCODEURL(H48)) | J49: =image("https://image-charts.com/chart?chs=150x150&cht=qr&choe=UTF-8&chl="&ENCODEURL(J48)) | N49: =image("https://image-charts.com/chart?chs=150x150&cht=qr&choe=UTF-8&chl="&ENCODEURL(N48)) | P49: =image("https://image-charts.com/chart?chs=150x150&cht=qr&choe=UTF-8&chl="&ENCODEURL(P48)) | R49: =image("https://image-charts.com/chart?chs=150x150&cht=qr&choe=UTF-8&chl="&ENCODEURL(R48)) | T49: =image("https://image-charts.com/chart?chs=150x150&cht=qr&choe=UTF-8&chl="&ENCODEURL(T48)) | V49: =image("https://image-charts.com/chart?chs=150x150&cht=qr&choe=UTF-8&chl="&ENCODEURL(V48))
B53: =image("https://image-charts.com/chart?chs=150x150&cht=qr&choe=UTF-8&chl="&ENCODEURL(B52)) | D53: =image("https://image-charts.com/chart?chs=150x150&cht=qr&choe=UTF-8&chl="&ENCODEURL(D52)) | F53: =image("https://image-charts.com/chart?chs=150x150&cht=qr&choe=UTF-8&chl="&ENCODEURL(F52)) | H53: =image("https://image-charts.com/chart?chs=150x150&cht=qr&choe=UTF-8&chl="&ENCODEURL(H52)) | J53: =image("https://image-charts.com/chart?chs=150x150&cht=qr&choe=UTF-8&chl="&ENCODEURL(J52)) | N53: =image("https://image-charts.com/chart?chs=150x150&cht=qr&choe=UTF-8&chl="&ENCODEURL(N52)) | P53: =image("https://image-charts.com/chart?chs=150x150&cht=qr&choe=UTF-8&chl="&ENCODEURL(P52)) | R53: =image("https://image-charts.com/chart?chs=150x150&cht=qr&choe=UTF-8&chl="&ENCODEURL(R52)) | T53: =image("https://image-charts.com/chart?chs=150x150&cht=qr&choe=UTF-8&chl="&ENCODEURL(T52)) | V53: =image("https://image-charts.com/chart?chs=150x150&cht=qr&choe=UTF-8&chl="&ENCODEURL(V52))
B57: =image("https://image-charts.com/chart?chs=150x150&cht=qr&choe=UTF-8&chl="&ENCODEURL(B56)) | D57: =image("https://image-charts.com/chart?chs=150x150&cht=qr&choe=UTF-8&chl="&ENCODEURL(D56)) | F57: =image("https://image-charts.com/chart?chs=150x150&cht=qr&choe=UTF-8&chl="&ENCODEURL(F56)) | H57: =image("https://image-charts.com/chart?chs=150x150&cht=qr&choe=UTF-8&chl="&ENCODEURL(H56)) | J57: =image("https://image-charts.com/chart?chs=150x150&cht=qr&choe=UTF-8&chl="&ENCODEURL(J56)) | N57: =image("https://image-charts.com/chart?chs=150x150&cht=qr&choe=UTF-8&chl="&ENCODEURL(N56)) | P57: =image("https://image-charts.com/chart?chs=150x150&cht=qr&choe=UTF-8&chl="&ENCODEURL(P56)) | R57: =image("https://image-charts.com/chart?chs=150x150&cht=qr&choe=UTF-8&chl="&ENCODEURL(R56)) | T57: =image("https://image-charts.com/chart?chs=150x150&cht=qr&choe=UTF-8&chl="&ENCODEURL(T56)) | V57: =image("https://image-charts.com/chart?chs=150x150&cht=qr&choe=UTF-8&chl="&ENCODEURL(V56))
B61: =image("https://image-charts.com/chart?chs=150x150&cht=qr&choe=UTF-8&chl="&ENCODEURL(B60)) | D61: =image("https://image-charts.com/chart?chs=150x150&cht=qr&choe=UTF-8&chl="&ENCODEURL(D60)) | F61: =image("https://image-charts.com/chart?chs=150x150&cht=qr&choe=UTF-8&chl="&ENCODEURL(F60)) | H61: =image("https://image-charts.com/chart?chs=150x150&cht=qr&choe=UTF-8&chl="&ENCODEURL(H60)) | J61: =image("https://image-charts.com/chart?chs=150x150&cht=qr&choe=UTF-8&chl="&ENCODEURL(J60)) | N61: =image("https://image-charts.com/chart?chs=150x150&cht=qr&choe=UTF-8&chl="&ENCODEURL(N60)) | P61: =image("https://image-charts.com/chart?chs=150x150&cht=qr&choe=UTF-8&chl="&ENCODEURL(P60)) | R61: =image("https://image-charts.com/chart?chs=150x150&cht=qr&choe=UTF-8&chl="&ENCODEURL(R60)) | T61: =image("https://image-charts.com/chart?chs=150x150&cht=qr&choe=UTF-8&chl="&ENCODEURL(T60)) | V61: =image("https://image-charts.com/chart?chs=150x150&cht=qr&choe=UTF-8&chl="&ENCODEURL(V60))
B65: =image("https://image-charts.com/chart?chs=150x150&cht=qr&choe=UTF-8&chl="&ENCODEURL(B64)) | D65: =image("https://image-charts.com/chart?chs=150x150&cht=qr&choe=UTF-8&chl="&ENCODEURL(D64)) | F65: =image("https://image-charts.com/chart?chs=150x150&cht=qr&choe=UTF-8&chl="&ENCODEURL(F64)) | H65: =image("https://image-charts.com/chart?chs=150x150&cht=qr&choe=UTF-8&chl="&ENCODEURL(H64)) | J65: =image("https://image-charts.com/chart?chs=150x150&cht=qr&choe=UTF-8&chl="&ENCODEURL(J64)) | N65: =image("https://image-charts.com/chart?chs=150x150&cht=qr&choe=UTF-8&chl="&ENCODEURL(N64)) | P65: =image("https://image-charts.com/chart?chs=150x150&cht=qr&choe=UTF-8&chl="&ENCODEURL(P64)) | R65: =image("https://image-charts.com/chart?chs=150x150&cht=qr&choe=UTF-8&chl="&ENCODEURL(R64)) | T65: =image("https://image-charts.com/chart?chs=150x150&cht=qr&choe=UTF-8&chl="&ENCODEURL(T64)) | V65: =image("https://image-charts.com/chart?chs=150x150&cht=qr&choe=UTF-8&chl="&ENCODEURL(V64))

Sheet Project Deltamas 2
A1: No | B1: Item | C1: Qty | D1: UOM | E1: Price 1 | F1: Product Information | G1: Price 2 | H1: Product Information | I1: Price 3 | J1: Product Information | K1: Notes | L1: First Purchase | S1: Second Purchase
L2: Actual Qty | M2: Actual Price | N2: Shipping Fee | O2: Sub Total | P2: Total | Q2: Status | R2: Remain Qty | S2: Actual Qty | T2: Actual Price | U2: Shipping Fee | V2: Sub Total | W2: Total | X2: Status
A3: OFFICE
A4: 1 | B4: Meja Kerja Office Lt. 2 | C4: 4 | D4: Pcs | E4: 300000 | F4: https://tk.tokopedia.com/ZSSc5DEfp/ | G4: Rp345.000 | H4: https://tk.tokopedia.com/ZSScaCX99/ | I4: Rp325.000 | J4: https://tk.tokopedia.com/ZSScmrg2n/ | L4: 1 | M4: 300000 | N4: 42000 | O4: =L4*M4+N4 -> 342000 | P4: =sum(O4:O21) -> 1587600 | Q4: Proposed | R4: =C4-L4 -> 3 | W4: =sum(V4:V21) -> 0
A5: 2 | B5: Kursi Kerja Office Lt. 2 | C5: 5 | D5: Pcs | E5: Rp299.000 | F5: https://www.ruparupa.com/p/selma-lyon-kursi-kantor-sandaran-rendah-abu-abu.html?itm_source=search&itm_campaign=direct_search&itm_term=kursi-kantor-%26-10605782&itm_device=desktop&queryId=106cf15159825ae1f370f09b142a6a4d&sid=ETFj5JgBdpC1r0iu7vd0 | G5: Rp299.800 | H5: https://tk.tokopedia.com/ZSScmMRaD/ | I5: 230900 | J5: https://tk.tokopedia.com/ZSScmS1TT/ | L5: 4 | M5: 230900 | N5: 58000 | O5: =L5*M5+N5 -> 981600 | Q5: Proposed | R5: =C5-L5 -> 1
A6: 3 | B6: Utilities service (Toilet dan pantry) | C6: 1 | D6: Lot | O6: =L6*M6+N6 -> 0 | R6: =C6-L6 -> 1
A7: 4 | B7: Internet (Instalasi) | C7: 1 | D7: Lot | E7: Rp980.000 | F7: Indibiz | G7: 10000000 | H7: PT MORATELINDO | J7: PT. SMT | O7: =L7*M7+N7 -> 0 | R7: =C7-L7 -> 1
A8: 5 | B8: TV Ruang Meeting | C8: 1 | D8: Pcs | E8: 2397000 | F8: https://tk.tokopedia.com/ZSAUkDvqt/ | G8: 2339900 | H8: https://tk.tokopedia.com/ZSAUk7TTv/ | I8: 2519000 | J8: https://tk.tokopedia.com/ZSAUknwUY/ | K8: TV Android 40" | O8: =L8*M8+N8 -> 0 | R8: =C8-L8 -> 1
A9: 6 | B9: Renovasi lantai 2 (Partisi Ruang meeting) | C9: 1 | D9: Lot | E9: Rp27.563.800 | F9: Designstudio | G9: Rp47.100.000 | H9: Intan Safety Glass | O9: =L9*M9+N9 -> 0 | R9: =C9-L9 -> 1
A10: 7 | B10: AC Office 1/2 pk | C10: 2 | D10: Unit | L10: 2 | O10: =L10*M10+N10 -> 0 | Q10: Installed | R10: =C10-L10 -> 0
A11: 8 | B11: Instalasi AC | C11: 3 | D11: Lot | E11: - | G11: - | I11: - | L11: 3 | O11: =L11*M11+N11 -> 0 | Q11: Installed | R11: =C11-L11 -> 0
A12: 9 | B12: Roller Blind | C12: 1 | D12: Lot | E12: Rp550.000 | F12: CGG Works | O12: =L12*M12+N12 -> 0 | R12: =C12-L12 -> 1
A13: 10 | B13: Meja Ruang Meeting | C13: 1 | D13: Pcs | E13: 1750000 | F13: https://tk.tokopedia.com/ZSAUByWJR/ | G13: 5099000 | H13: https://www.ruparupa.com/informastore/p/sieben-i-i-i-meja-rapat-2012-iw-putih.html | I13: 4199000 | J13: https://www.ruparupa.com/p/informa-maven-meja-rapat-220-abu-abu-cokelat-oak.html?itm_source=product-recommendation-search-result-rr&itm_campaign=direct-search&itm_term=10591345&itm_device=desktop | O13: =L13*M13+N13 -> 0 | R13: =C13-L13 -> 1
A14: 11 | B14: Kursi Ruang Meeting | C14: 5 | D14: Pcs | E14: Rp299.000 | F14: https://www.ruparupa.com/p/selma-lyon-kursi-kantor-sandaran-rendah-abu-abu.html?itm_source=search&itm_campaign=direct_search&itm_term=kursi-kantor-%26-10605782&itm_device=desktop&queryId=106cf15159825ae1f370f09b142a6a4d&sid=ETFj5JgBdpC1r0iu7vd0 | G14: Rp299.800 | H14: https://tk.tokopedia.com/ZSScmMRaD/ | I14: Rp228.900 | J14: https://tk.tokopedia.com/ZSScmS1TT/ | O14: =L14*M14+N14 -> 0 | R14: =C14-L14 -> 5
A15: 12 | B15: Lemari Arsip | C15: 5 | D15: Pcs | E15: 1375000 | F15: https://tk.tokopedia.com/ZSAUS8MTv/ | G15: 1399000 | H15: https://www.ruparupa.com/p/kiev-lemari-arsip-dengan-pintu-kaca-80x40x180-cm-cokelat.html?itm_source=search&itm_campaign=direct_search&itm_term=lemari-arsip-%26-10450019&itm_device=desktop&queryId=d8a62aa5a3480b2e1405fbfbfde2b9b0&sid=hYfv35gBSC0oiPerAXbg | I15: Rp2.331.900 | J15: https://www.tokopedia.com/informa/informa-lemari-arsip-kantor-metal-4-pintu-high-putih-1729857549483148897?extParam=ivf%3Dfalse%26keyword%3Dlemari+arsip+informa%26search_id%3D2025082604364111B9842E0A271F2ADNOG%26src%3Dsearch%26whid%3D17430154&t_id=1756182822447&t_st=5&t_pp=search_result&t_efo=search_pure_goods_card&t_ef=goods_search&t_sm=&t_spt=search_result | O15: =L15*M15+N15 -> 0 | R15: =C15-L15 -> 5
A16: 13 | B16: Printer | C16: 1 | D16: Unit | E16: 2097600 | F16: https://www.tokopedia.com/metroelektro/jkt-printer-epson-l3210-l-3210-l-3210-l3211-l-3211-l-3211-3-in-1-pengganti-epson-l3110-print-scan-copy-a4-all-in-one-garansi-resmi-1731966599558694489?extParam=ivf%3Dfalse%26keyword%3Dprinter+epson+l3210%26search_id%3D20250827072908D947BF06A885DB0214OJ%26src%3Dsearch | G16: 1976000 | H16: https://www.tokopedia.com/fixprint-indonesia/printer-epson-l3210-l3250-print-scan-copy-multifungsi-wifi-wireless-l3210-no-wifi-xantri-ink-deba9?extParam=ivf%3Dtrue%26keyword%3Dprinter+epson+l3210%26search_id%3D20250827072908D947BF06A885DB0214OJ%26src%3Dsearch%26whid%3D12813586 | I16: 1870550 | J16: https://www.tokopedia.com/ciptakaryashop/epson-l3210-all-in-one-ink-tank-printer-hitam-putih-original-tinta-1-set-garansi-resmi-2-tahun-1729826990812267912?extParam=ivf%3Dfalse%26keyword%3Dprinter+epson+l3210%26search_id%3D20250827072908D947BF06A885DB0214OJ%26src%3Dsearch | O16: =L16*M16+N16 -> 0 | R16: =C16-L16 -> 1
A17: 14 | B17: PC Komputer Admin | C17: 1 | D17: Set | E17: 2469050 | F17: https://tk.tokopedia.com/ZSAadebyn/ | G17: 2411100 | H17: https://tk.tokopedia.com/ZSAaewdp9/ | I17: 2193550 | J17: https://tk.tokopedia.com/ZSAadRMky/ | O17: =L17*M17+N17 -> 0 | R17: =C17-L17 -> 1
A18: 15 | B18: Mesin absensi (attendance) | C18: 1 | D18: Pcs | E18: 1306000 | F18: https://tk.tokopedia.com/ZSA6L5q9J/ | G18: 1083000 | H18: https://tk.tokopedia.com/ZSA6BrEFw/ | I18: Rp1.679.000 | J18: https://www.tokopedia.com/solutionofficial/mesin-absensi-fingerprint-solution-x100-c?extParam=ivf%3Dfalse%26keyword%3Dmeisn+absensi+%26search_id%3D20250826043741577BCC914F9E55011N2C%26src%3Dsearch&t_id=1756182822447&t_st=6&t_pp=search_result&t_efo=search_pure_goods_card&t_ef=goods_search&t_sm=&t_spt=search_result | K18: Ambil dari Delta 1 | O18: =L18*M18+N18 -> 0 | R18: =C18-L18 -> 1
A19: 16 | B19: Tempat sampah Kecil | C19: 6 | D19: Pcs | E19: 14012 | F19: https://tk.tokopedia.com/ZSAadnVkK/ | G19: 19950 | H19: https://tk.tokopedia.com/ZSAaR1TQW/ | I19: 29999 | J19: https://tk.tokopedia.com/ZSApgnuQr/ | M19: 29999 | N19: 0 | O19: =L19*M19+N19 -> 0 | R19: =C19-L19 -> 6
A20: 17 | B20: Tempat sampah Sedang | C20: 2 | D20: Pcs | E20: 117000 | F20: https://tk.tokopedia.com/ZSApbJAQB/ | G20: 95000 | H20: https://tk.tokopedia.com/ZSApqK96f/ | K20: >60 Liter | L20: 2 | M20: 117000 | N20: 30000 | O20: =L20*M20+N20 -> 264000 | Q20: Proposed | R20: =C20-L20 -> 0
A21: 18 | B21: Tempat sampah area | C21: 1 | D21: Pcs | O21: =L21*M21+N21 -> 0 | R21: =C21-L21 -> 1
A22: SURVEILANCE
A23: 1 | B23: Magnetic Door | C23: 6 | D23: Unit | E23: Rp650.000 | F23: https://www.tokopedia.com/buditronik/m-loock-solution-magnetic-door-sliding-door-full-set?extParam=ivf%3Dfalse%26keyword%3Dmagnetic+door%26search_id%3D2025082604491637BC2F75BF1BCF296A71%26src%3Dsearch&t_id=1756183763009&t_st=1&t_pp=search_result&t_efo=search_pure_goods_card&t_ef=goods_search&t_sm=&t_spt=search_result | G23: Rp925.252 | H23: https://www.tokopedia.com/dur-elektronik/solution-magnetic-door-model-em-600?extParam=ivf%3Dfalse%26keyword%3Dmagnetic+door%26search_id%3D2025082604491637BC2F75BF1BCF296A71%26src%3Dsearch&t_id=1756183763009&t_st=2&t_pp=search_result&t_efo=search_pure_goods_card&t_ef=goods_search&t_sm=&t_spt=search_result | I23: Rp880.000 | J23: https://www.tokopedia.com/data-online-system/solution-magnetic-door?extParam=ivf%3Dfalse%26keyword%3Dmagnetic+door%26search_id%3D2025082604491637BC2F75BF1BCF296A71%26src%3Dsearch&t_id=1756183763009&t_st=3&t_pp=search_result&t_efo=search_pure_goods_card&t_ef=goods_search&t_sm=&t_spt=search_result | O23: =L23*M23+N23 -> 0 | P23: =sum(O23:O29) -> 0 | R23: =C23-L23 -> 6 | W23: =sum(V23:V29) -> 0
A24: 2 | B24: Automatic Door Closer | C24: 6 | D24: Unit | E24: Rp81,700 | F24: https://tk.tokopedia.com/ZSAaNML5S/ | G24: Rp85,498 | H24: https://tk.tokopedia.com/ZSAaNjCDk/ | I24: Rp120,650 | J24: https://tk.tokopedia.com/ZSAaNY2us/ | O24: =L24*M24+N24 -> 0 | R24: =C24-L24 -> 6
A25: 3 | B25: Akses Door | C25: 1 | D25: Unit | E25: Rp559.000 | F25: https://tk.tokopedia.com/ZSAfB18Jv/ | G25: Rp2.132.000 | H25: Putra Teknologi Mandiri | O25: =L25*M25+N25 -> 0 | R25: =C25-L25 -> 1
A26: 4 | B26: Instalasi Door Akses | C26: 1 | D26: Unit | E26: Rp550.000 | F26: https://tk.tokopedia.com/ZSAfBBaCj/ | G26: Rp0 | H26: Include Putra Teknologi Mandiri | O26: =L26*M26+N26 -> 0 | R26: =C26-L26 -> 1
A27: 5 | B27: Monitor CCTV | C27: 1 | D27: Pcs | E27: Rp2.397.000 | F27: https://tk.tokopedia.com/ZSAUkDvqt/ | G27: Rp2.339.900 | H27: https://tk.tokopedia.com/ZSAUk7TTv/ | I27: Rp2.519.000 | J27: https://tk.tokopedia.com/ZSAUknwUY/ | K27: TV HDMI 40" | O27: =L27*M27+N27 -> 0 | R27: =C27-L27 -> 1
A28: 6 | B28: CCTV 12 titik | C28: 1 | D28: Lot | E28: Rp10.750.000 | F28: https://tk.tokopedia.com/ZSAfBQaxd/ | G28: Rp39.594.599 | H28: Cendana Teknik | I28: Rp11.523.000 | J28: https://www.tokopedia.com/cctvcom10/paket-cctv-hikvision-5mp-8-channel-8-camera-turbo-hd-kamera-cctv-infrared-1730179095987193151?extParam=ivf%3Dfalse%26keyword%3Dcctv+krisbow%26search_id%3D2025082606201611B9842E0A271F284857%26src%3Dsearch | L28: 1 | O28: =L28*M28+N28 -> 0 | R28: =C28-L28 -> 0
A29: 7 | B29: Instalasi CCTV | C29: 1 | D29: Lot | G29: Rp0 | H29: Include Cendana Teknik | O29: =L29*M29+N29 -> 0 | R29: =C29-L29 -> 1
A30: LISTRIK OFFICE
A31: 1 | B31: Kabel TC 6 | C31: 10 | D31: Pcs | E31: 9975 | F31: https://tk.tokopedia.com/ZSAaLexsA/ | G31: 9025 | H31: https://tk.tokopedia.com/ZSAa8t6f3/ | I31: 8550 | J31: https://tk.tokopedia.com/ZSAa8ga7X/ | O31: =L31*M31+N31 -> 0 | P31: =sum(O31:O40) -> 2500000 | R31: =C31-L31 -> 10 | W31: =sum(V31:V40) -> 0
A32: 2 | B32: Bracket Standing TV | C32: 1 | D32: Pcs | E32: 485000 | F32: https://tk.tokopedia.com/ZSA61PyUP/ | G32: 465000 | H32: https://tk.tokopedia.com/ZSA61PP7k/ | I32: 425625 | J32: https://tk.tokopedia.com/ZSA61kbCf/ | K32: 32 - 55 inch | O32: =L32*M32+N32 -> 0 | R32: =C32-L32 -> 1
A33: 3 | B33: Kabel HDMI 2.0 3 Meter | C33: 2 | D33: Pcs | E33: 68305 | F33: https://tk.tokopedia.com/ZSAa87kx9/ | G33: 33250 | H33: https://tk.tokopedia.com/ZSAa8gfLx/ | I33: 66500 | J33: https://tk.tokopedia.com/ZSAaLLwjx/ | K33: Vention, Ugreen, Bafo | O33: =L33*M33+N33 -> 0 | R33: =C33-L33 -> 2
A34: 4 | B34: Bracket Dinding TV | C34: 1 | D34: Pcs | E34: 37524 | F34: https://tk.tokopedia.com/ZSAaLAgoE/ | G34: 25555 | H34: https://tk.tokopedia.com/ZSAaLBEbE/ | I34: 61655 | J34: https://tk.tokopedia.com/ZSAaLaJfx/ | K34: 42" | O34: =L34*M34+N34 -> 0 | R34: =C34-L34 -> 1
A35: 5 | B35: Locker Besi 12 Pintu | C35: 1 | D35: Pcs | E35: 2199000 | F35: https://www.ruparupa.com/p/informa-kiev-loker-12-pintu-cokelat-muda.html?itm_source=search&itm_campaign=direct_search&itm_term=loker-besi-12-pintu-%26-10507509&itm_device=desktop&queryId=b0164af4e6ca5e2197c284e491c63c8b&sid=ryC4CZkBeHn2cx7nL1Z4 | G35: 1995000 | H35: https://tk.tokopedia.com/ZSAaL2t8T/ | I35: 2283100 | J35: https://tk.tokopedia.com/ZSAaLUSho/ | M35: 1995000 | O35: =L35*M35+N35 -> 0 | Q35: Proposed | R35: =C35-L35 -> 1
A36: 6 | B36: Stekker Arde Broco | C36: 12 | D36: Pcs | E36: 8835 | F36: https://tk.tokopedia.com/ZSAaLF5Yp/ | G36: 10640 | H36: https://tk.tokopedia.com/ZSAaLBW9G/ | I36: 9310 | J36: https://tk.tokopedia.com/ZSAaLT4sM/ | O36: =L36*M36+N36 -> 0 | R36: =C36-L36 -> 12
A37: 7 | B37: Stekker T Broco | C37: 3 | D37: Pcs | E37: 19950 | F37: https://tk.tokopedia.com/ZSAaLGWe2/ | G37: 25441 | H37: https://tk.tokopedia.com/ZSAaL3VFp/ | I37: 19760 | J37: https://tk.tokopedia.com/ZSAaLWPy2/ | O37: =L37*M37+N37 -> 0 | R37: =C37-L37 -> 3
A38: 8 | B38: Colokan 5 Lubang | C38: 12 | D38: Pcs | E38: 61636 | F38: https://tk.tokopedia.com/ZSAaLVDxW/ | G38: 58235 | H38: https://tk.tokopedia.com/ZSAaLs52k/ | I38: 61190 | J38: https://tk.tokopedia.com/ZSAaLcrTe/ | O38: =L38*M38+N38 -> 0 | R38: =C38-L38 -> 12
A39: 9 | B39: Lampu LED Philips | C39: 4 | D39: Pcs | E39: 122857 | F39: https://tk.tokopedia.com/ZSAMc7KB6/ | G39: 109990 | H39: https://tk.tokopedia.com/ZSAM3M9Qs/ | K39: 10 Watt | O39: =L39*M39+N39 -> 0 | R39: =C39-L39 -> 4
A40: 10 | B40: Sertifikasi Instalasi Listrik | C40: 1 | D40: Pc | E40: 2500000 | F40: CV IAM HERE INSPIRATION | L40: 1 | M40: 2500000 | N40: 0 | O40: =L40*M40+N40 -> 2500000 | Q40: On Process | R40: =C40-L40 -> 0
A41: APAR
A42: 1 | B42: Sertifikasi APAR | C42: 1 | D42: Pc | E42: - | G42: 0 | H42: PT GLOBAL MITRA PROTEKSINDO (Include) | K42: PT GLOBAL MITRA PROTEKSINDO (Include) | L42: 1 | M42: 0 | N42: 0 | O42: =L42*M42+N42 -> 0 | P42: =sum(O42:O44) -> 3030000 | Q42: On Process | R42: =C42-L42 -> 0 | W42: =sum(V42:V44) -> 0
A43: 2 | B43: APAR 9 KG | C43: 3 | D43: Pcs | E43: 550000 | F43: PT Sinar Proteksindo Optimal | G43: 2500000 | H43: PT GLOBAL MITRA PROTEKSINDO | L43: 3 | M43: 550000 | N43: 0 | O43: =L43*M43+N43 -> 1650000 | Q43: Delivered | R43: =C43-L43 -> 0
A44: 3 | B44: APAR 6 KG | C44: 3 | D44: Pcs | E44: 460000 | F44: PT Sinar Proteksindo Optimal | G44: 2100000 | H44: PT GLOBAL MITRA PROTEKSINDO | L44: 3 | M44: 460000 | N44: 0 | O44: =L44*M44+N44 -> 1380000 | Q44: Delivered | R44: =C44-L44 -> 0
A45: PANTRY & CONSUMABLE
A46: 1 | B46: Cangkir Kaca (1 Lusin) | C46: 1 | D46: Lusin | E46: 110000 | F46: https://tk.tokopedia.com/ZSA6SsrXB/ | G46: 70000 | H46: https://tk.tokopedia.com/ZSA6A9ax8/ | I46: Rp100.610 | J46: https://www.tokopedia.com/gelas5saudara/1-set-6-pcs-maxim-gelas-mug-beer-gelas-mug-tempered-glass-mug-kaca-mug?extParam=ivf%3Dfalse%26keyword%3Dcangkir+kaca%26search_id%3D20250826045158577BCC914F9E55064Q56%26src%3Dsearch&t_id=1756183763009&t_st=4&t_pp=search_result&t_efo=search_pure_goods_card&t_ef=goods_search&t_sm=&t_spt=search_result | O46: =L46*M46+N46 -> 0 | P46: =sum(O46:O52) -> 1144288 | R46: =C46-L46 -> 1 | W46: =sum(V46:V52) -> 0
A47: 2 | B47: Sendok Garpu (1 Lusin) | C47: 1 | D47: Lusin | E47: 18905 | F47: https://tk.tokopedia.com/ZSAaRMQfd/ | G47: 10440 | H47: https://tk.tokopedia.com/ZSAaRrQQ4/ | I47: 9500 | J47: https://tk.tokopedia.com/ZSAaRmMUk/ | O47: =L47*M47+N47 -> 0 | R47: =C47-L47 -> 1
A48: 3 | B48: Piring makan | C48: 1 | D48: Lusin | E48: 47500 | F48: https://tk.tokopedia.com/ZSAaRXeVU/ | G48: 68305 | H48: https://tk.tokopedia.com/ZSAaRm4du/ | I48: 67260 | J48: https://tk.tokopedia.com/ZSAaRhd1c/ | O48: =L48*M48+N48 -> 0 | R48: =C48-L48 -> 1
A49: 4 | B49: Dispenser Otomatis | C49: 2 | D49: Unit | E49: Rp1.799.000 | F49: https://www.tokopedia.com/satu-elektronik/philips-add4948-dispenser-galon-bawah-add-4948-add4948-hitam?extParam=ivf%3Dfalse%26keyword%3Ddispenser%26search_id%3D2025082602463437BC2F75BF1BCF3ABPCO%26src%3Dsearch&t_id=1756176155674&t_st=7&t_pp=search_result&t_efo=search_pure_goods_card&t_ef=goods_search&t_sm=&t_spt=search_result | G49: 1122288 | H49: https://tk.tokopedia.com/ZSA6S6rdG/ | I49: Rp1.489.000 | J49: https://www.tokopedia.com/mideaofficial/midea-dispenser-air-galon-bawah-yd-1634w-bottom-loading?extParam=ivf%3Dfalse%26keyword%3Ddispenser%26search_id%3D2025082602463437BC2F75BF1BCF3ABPCO%26src%3Dsearch&t_id=1756176155674&t_st=11&t_pp=search_result&t_efo=search_pure_goods_card&t_ef=goods_search&t_sm=&t_spt=search_result | L49: 1 | M49: 1122288 | N49: 22000 | O49: =L49*M49+N49 -> 1144288 | Q49: Proposed | R49: =C49-L49 -> 1
A50: 5 | B50: Nampan minuman | C50: 1 | D50: Pc | E50: 15200 | F50: https://tk.tokopedia.com/ZSAaRQM4V/ | G50: 51300 | H50: https://tk.tokopedia.com/ZSAaRkUCT/ | I50: 56050 | J50: https://tk.tokopedia.com/ZSAaRQDfq/ | O50: =L50*M50+N50 -> 0 | R50: =C50-L50 -> 1
A51: 6 | B51: Kulkas (if necessary) | C51: 1 | D51: Pc | E51: 1790500 | F51: https://tk.tokopedia.com/ZSAaRgUwP/ | G51: 1234050 | H51: https://tk.tokopedia.com/ZSAaRsQ7T/ | I51: 1281050 | J51: https://tk.tokopedia.com/ZSAaRtKjs/ | O51: =L51*M51+N51 -> 0 | R51: =C51-L51 -> 1
A52: 7 | B52: Rak peralatan | C52: 1 | D52: Pc | E52: 35149 | F52: https://tk.tokopedia.com/ZSAaRo7qy/ | G52: 60515 | H52: https://tk.tokopedia.com/ZSAaRcDPk/ | I52: 22686 | J52: https://tk.tokopedia.com/ZSAaRcDPk/ | O52: =L52*M52+N52 -> 0 | R52: =C52-L52 -> 1
A53: 8 | B53: Dispenser Lapangan | C53: 1 | D53: Pc
A54: CLEANING & SANITARY
A55: 1 | B55: Sapu Produksi | C55: 3 | D55: Pc | E55: Rp25.475 | F55: https://www.tokopedia.com/pamosroom-living/pamosroom-dragon-sapu-ijuk-besar-sapu-lantai-rumah-sapu-kipas-besar-1731349345081132181?extParam=ivf%3Dfalse%26keyword%3Dsapu%26search_id%3D2025081109544206EB61B839A0CE048EN8%26src%3Dsearch&t_id=1754906032843&t_st=1&t_pp=search_result&t_efo=search_pure_goods_card&t_ef=goods_search&t_sm=&t_spt=search_result | G55: Rp8.075 | H55: https://www.tokopedia.com/ghrcolection/sapu-lantai-ijuk-dengan-gagang-panjang-tidak-mudah-patah-1729557113027659814?extParam=ivf%3Dfalse%26keyword%3Dsapu%26search_id%3D2025081109544206EB61B839A0CE048EN8%26src%3Dsearch&t_id=1754906195226&t_st=1&t_pp=search_result&t_efo=search_pure_goods_card&t_ef=goods_search&t_sm=&t_spt=search_result | I55: Rp9.499 | J55: https://www.tokopedia.com/anova-indonesia/broom-sapu-ijuk-hitam-dragon-plus-gagang-kumbo-standar-733a5?extParam=ivf%3Dfalse%26keyword%3Dsapu%26search_id%3D2025081109544206EB61B839A0CE048EN8%26src%3Dsearch&t_id=1754906251638&t_st=1&t_pp=search_result&t_efo=search_pure_goods_card&t_ef=goods_search&t_sm=&t_spt=search_result | L55: 1 | M55: 11499 | N55: 3500 | O55: =L55*M55+N55 -> 14999 | P55: =sum(O55:O65)+2800 -> 352631 | Q55: Delivered | R55: =C55-L55 -> 2 | W55: =sum(V55:V65) -> 0
A56: 2 | B56: Pel Produksi | C56: 3 | D56: Pc | E56: Rp21.375 | F56: https://www.tokopedia.com/athirashop-1/pelan-pel-lantai-dragon-ukuran-besar-18-cm-original-include-gagang?extParam=ivf%3Dfalse%26keyword%3Dpel%26search_id%3D2025081109591737BC2F75BF1BCF2D4QS5%26src%3Dsearch&t_id=1754906251638&t_st=2&t_pp=search_result&t_efo=search_pure_goods_card&t_ef=goods_search&t_sm=&t_spt=search_result | G56: Rp23.132 | H56: https://www.tokopedia.com/8jayahengky/pel-nagoya-pel-lantai-lebar-pel-kain-pel-pembersih-mop-lantai-1731421579575658230?extParam=ivf%3Dfalse%26keyword%3Dpel%26search_id%3D2025081109591737BC2F75BF1BCF2D4QS5%26src%3Dsearch&t_id=1754906251638&t_st=3&t_pp=search_result&t_efo=search_pure_goods_card&t_ef=goods_search&t_sm=&t_spt=search_result | I56: Rp20.900 | J56: https://www.tokopedia.com/felisacollection24/nagoya-pel-lantai-medium-702-alat-pel-lantai-kuat-dan-berkualitas-gagang-panjang?extParam=ivf%3Dfalse%26keyword%3Dpel%26search_id%3D2025081109591737BC2F75BF1BCF2D4QS5%26src%3Dsearch&t_id=1754906251638&t_st=4&t_pp=search_result&t_efo=search_pure_goods_card&t_ef=goods_search&t_sm=&t_spt=search_result | L56: 1 | M56: 22000 | N56: 3500 | O56: =L56*M56+N56 -> 25500 | Q56: Delivered | R56: =C56-L56 -> 2
A57: 3 | B57: Ember Cat | C57: 2 | D57: Pc | E57: Rp11.875 | F57: https://www.tokopedia.com/syulthon/ember-bekas-cat-ember-plastik-pot-tanaman-tempat-sampah-tong-air?extParam=ivf%3Dfalse%26keyword%3Dember+cat%26search_id%3D202508111001335B8ADD2A5D98B1028XNH%26src%3Dsearch | G57: Rp19.000 | H57: https://www.tokopedia.com/arsenmart-1/ember-cat-25kg-non-tutup-pail-plastik?extParam=ivf%3Dfalse%26keyword%3Dember+cat%26search_id%3D202508111001335B8ADD2A5D98B1028XNH%26src%3Dsearch | I57: Rp22.800 | J57: https://www.tokopedia.com/arsenmart-1/ember-cat-25-kg-putih-polos-lengkap-tutup?extParam=ivf%3Dfalse%26keyword%3Dember+cat%26search_id%3D202508111001335B8ADD2A5D98B1028XNH%26src%3Dsearch | L57: 1 | M57: 24000 | N57: 7000 | O57: =L57*M57+N57 -> 31000 | Q57: Delivered | R57: =C57-L57 -> 1
A58: 4 | B58: Sapu Kantor | C58: 1 | D58: Pc | E58: Rp25.475 | F58: https://www.tokopedia.com/pamosroom-living/pamosroom-dragon-sapu-ijuk-besar-sapu-lantai-rumah-sapu-kipas-besar-1731349345081132181?extParam=ivf%3Dfalse%26keyword%3Dsapu%26search_id%3D2025081109544206EB61B839A0CE048EN8%26src%3Dsearch&t_id=1754906032843&t_st=1&t_pp=search_result&t_efo=search_pure_goods_card&t_ef=goods_search&t_sm=&t_spt=search_result | G58: Rp8.075 | H58: https://www.tokopedia.com/ghrcolection/sapu-lantai-ijuk-dengan-gagang-panjang-tidak-mudah-patah-1729557113027659814?extParam=ivf%3Dfalse%26keyword%3Dsapu%26search_id%3D2025081109544206EB61B839A0CE048EN8%26src%3Dsearch&t_id=1754906195226&t_st=1&t_pp=search_result&t_efo=search_pure_goods_card&t_ef=goods_search&t_sm=&t_spt=search_result | I58: Rp9.499 | J58: https://www.tokopedia.com/anova-indonesia/broom-sapu-ijuk-hitam-dragon-plus-gagang-kumbo-standar-733a5?extParam=ivf%3Dfalse%26keyword%3Dsapu%26search_id%3D2025081109544206EB61B839A0CE048EN8%26src%3Dsearch&t_id=1754906251638&t_st=1&t_pp=search_result&t_efo=search_pure_goods_card&t_ef=goods_search&t_sm=&t_spt=search_result | L58: 1 | M58: 11499 | N58: 3500 | O58: =L58*M58+N58 -> 14999 | Q58: Delivered | R58: =C58-L58 -> 0
A59: 5 | B59: Pel Kantor | C59: 1 | D59: Pc | E59: Rp21.375 | F59: https://www.tokopedia.com/athirashop-1/pelan-pel-lantai-dragon-ukuran-besar-18-cm-original-include-gagang?extParam=ivf%3Dfalse%26keyword%3Dpel%26search_id%3D2025081109591737BC2F75BF1BCF2D4QS5%26src%3Dsearch&t_id=1754906251638&t_st=2&t_pp=search_result&t_efo=search_pure_goods_card&t_ef=goods_search&t_sm=&t_spt=search_result | G59: Rp23.132 | H59: https://www.tokopedia.com/8jayahengky/pel-nagoya-pel-lantai-lebar-pel-kain-pel-pembersih-mop-lantai-1731421579575658230?extParam=ivf%3Dfalse%26keyword%3Dpel%26search_id%3D2025081109591737BC2F75BF1BCF2D4QS5%26src%3Dsearch&t_id=1754906251638&t_st=3&t_pp=search_result&t_efo=search_pure_goods_card&t_ef=goods_search&t_sm=&t_spt=search_result | I59: Rp20.900 | J59: https://www.tokopedia.com/felisacollection24/nagoya-pel-lantai-medium-702-alat-pel-lantai-kuat-dan-berkualitas-gagang-panjang?extParam=ivf%3Dfalse%26keyword%3Dpel%26search_id%3D2025081109591737BC2F75BF1BCF2D4QS5%26src%3Dsearch&t_id=1754906251638&t_st=4&t_pp=search_result&t_efo=search_pure_goods_card&t_ef=goods_search&t_sm=&t_spt=search_result | L59: 1 | M59: 22000 | N59: 3500 | O59: =L59*M59+N59 -> 25500 | Q59: Delivered | R59: =C59-L59 -> 0
A60: 6 | B60: Rinso | C60: 1 | D60: Dus | E60: Rp97.676 | F60: https://shopee.co.id/RINSO-BUBUK-40-GR-(126-PCS)-DUS-i.336396557.26955833416 | L60: 1 | M60: 112900 | N60: =116332-112900 -> 3432 | O60: =L60*M60+N60 -> 116332 | Q60: Delivered | R60: =C60-L60 -> 0
A61: 7 | B61: Liquid Pel | C61: 5 | D61: Liter | E61: Rp45.000 | F61: https://shopee.co.id/Karbol-Wangi-Sereh-(Pembersih-Lantai-dan-Kamar-Mandi)-5-LITER-Jerigen-i.1053187645.21896322729?xptdk=37b3de05-6993-455c-b678-ac739f22f111 | L61: 1 | M61: 58109 | N61: 0 | O61: =L61*M61+N61 -> 58109 | Q61: Delivered | R61: =C61-L61 -> 4
A62: 8 | B62: Liquid Cuci Tangan | C62: 5 | D62: Liter | E62: Rp41.250 | F62: https://shopee.co.id/CLEAN-CLEAN-Sabun-Cuci-Tangan-Antiseptik-Antibacterial-Hand-Soap-5L-AROMA-DETTOL-i.1053187645.24164566389 | L62: 1 | O62: =L62*M62+N62 -> 0 | R62: =C62-L62 -> 4
A63: 9 | B63: Kemoceng | C63: 1 | D63: Pcs | E63: Rp18.900 | F63: https://shopee.co.id/Kemoceng-Teleskopik-2.8-Meter-Microfiber-Magnet-Debu-Bisa-Tekuk-Adjustable-Alat-Pembersih-Rumah-i.1405216909.26630563257?xptdk=d66c4291-cd92-4416-95a3-eb801859c3b8 | L63: 1 | M63: 18863 | N63: =22058-18863 -> 3195 | O63: =L63*M63+N63 -> 22058 | Q63: Delivered | R63: =C63-L63 -> 0
A64: 10 | B64: Lap Kaca | C64: 1 | D64: Pcs | E64: Rp10.000 | F64: https://shopee.co.id/PREMIUM-Microfiber-Kain-Lap-Multifungsi-Serbaguna-611-GSM-30-x-30-cm-i.192635131.20994736339?xptdk=c48075e0-9579-4c6e-8020-67249c682543 | L64: 1 | M64: 10000 | N64: 3644 | O64: =L64*M64+N64 -> 13644 | Q64: Delivered | R64: =C64-L64 -> 0
A65: 11 | B65: Liquid Pembersih Kaca | C65: 5 | D65: Liter | E65: Rp26.555 | F65: https://shopee.co.id/Glass-Cleaner-Pembersih-Kaca-i.19073520.262539389?xptdk=47df84c1-bdc7-4feb-9828-5f5a601dc6fc | L65: 1 | M65: 26555 | N65: =27690-26555 -> 1135 | O65: =L65*M65+N65 -> 27690 | Q65: Delivered | R65: =C65-L65 -> 4
A66: AREA LUAR & POS SECURITY
A67: 1 | B67: Asbak Standing | C67: 1 | D67: Pc | E67: 156750 | F67: https://tk.tokopedia.com/ZSAa8SGRu/ | G67: 304000 | H67: https://tk.tokopedia.com/ZSAa8jg8n/ | I67: 299250 | J67: https://tk.tokopedia.com/ZSAa8H9oc/ | O67: =L67*M67+N67 -> 0 | P67: =sum(O67:O73) -> 0 | R67: =C67-L67 -> 1 | W67: =sum(V67:V73) -> 0
A68: 2 | B68: Kipas Angin Industri | C68: 4 | D68: Pcs | E68: 323900 | F68: https://tk.tokopedia.com/ZSAGr1SfY/ | G68: 500500 | H68: https://tk.tokopedia.com/ZSAGrpUWa/ | I68: 388200 | J68: https://tk.tokopedia.com/ZSAGhnqMJ/ | K68: Lapangan | O68: =L68*M68+N68 -> 0 | R68: =C68-L68 -> 4
A69: 3 | B69: Bendera Merah Putih | C69: 2 | D69: Pcs | E69: Rp23.900 | F69: https://www.tokopedia.com/topping-bag-shop/bendera-merah-putih-80-x-120-bahan-katun-asli-100-ukuran-real-bendera-merah-putih-bahan-katun-1731603471061320833?extParam=ivf%3Dfalse%26keyword%3Dbendera%26search_id%3D2025082601391737BC2F75BF1BCF136OBS%26src%3Dsearch&t_id=1756172367635&t_st=1&t_pp=search_result&t_efo=search_pure_goods_card&t_ef=goods_search&t_sm=&t_spt=search_result | G69: Rp44.100 | H69: https://www.tokopedia.com/kheyra-colection-15/bendera-merah-putih-150x200cm-merah-1729624981151124431?extParam=ivf%3Dfalse%26keyword%3Dbendera%26search_id%3D2025082601391737BC2F75BF1BCF136OBS%26src%3Dsearch&t_id=1756172367635&t_st=2&t_pp=search_result&t_efo=search_pure_goods_card&t_ef=goods_search&t_sm=&t_spt=search_result | I69: Rp28.900 | J69: https://www.tokopedia.com/jashujansuroboyo/termurah-bendera-merah-putih-katun-tebal-80-x-120?extParam=ivf%3Dfalse%26keyword%3Dbendera%26search_id%3D2025082601391737BC2F75BF1BCF136OBS%26src%3Dsearch&t_id=1756172367635&t_st=3&t_pp=search_result&t_efo=search_pure_goods_card&t_ef=goods_search&t_sm=&t_spt=search_result | O69: =L69*M69+N69 -> 0 | R69: =C69-L69 -> 2
A70: 4 | B70: Bendera K3 | C70: 2 | D70: Pcs | E70: Rp23.900 | F70: https://www.tokopedia.com/jashujansuroboyo/bendera-k3-kesehatan-keselamatan-dan-kerja-90-x-120-k-k-k-k-3-f7297?extParam=ivf%3Dfalse%26keyword%3Dbendera+k3%26search_id%3D2025082601422711B9842E0A271F02065F%26src%3Dsearch&t_id=1756172367635&t_st=4&t_pp=search_result&t_efo=search_pure_goods_card&t_ef=goods_search&t_sm=&t_spt=search_result | G70: Rp24.990 | H70: https://www.tokopedia.com/kakascout/bendera-k3-90x120-cm?extParam=ivf%3Dfalse%26keyword%3Dbendera+k3%26search_id%3D2025082601422711B9842E0A271F02065F%26src%3Dsearch&t_id=1756172367635&t_st=5&t_pp=search_result&t_efo=search_pure_goods_card&t_ef=goods_search&t_sm=&t_spt=search_result | I70: Rp30.000 | J70: https://www.tokopedia.com/tkcahaya-utama-adv/cahaya-olshop-bendera-k3-standar-depnaker-bahan-satin-asahi-90x135cm-utamakan-keselamatan-dan-kesehatan-kerja-1731612670626727344?extParam=ivf%3Dfalse%26keyword%3Dbendera+k3%26search_id%3D2025082601422711B9842E0A271F02065F%26src%3Dsearch&t_id=1756172367635&t_st=6&t_pp=search_result&t_efo=search_pure_goods_card&t_ef=goods_search&t_sm=&t_spt=search_result | O70: =L70*M70+N70 -> 0 | R70: =C70-L70 -> 2
A71: 5 | B71: PEST Control | C71: 1 | D71: Pcs | E71: Rp1.250.000 | F71: Proton | G71: - | I71: - | O71: =L71*M71+N71 -> 0 | R71: =C71-L71 -> 1
A72: 6 | B72: Meja Makan Karyawan | C72: 2 | D72: Pcs | E72: Rp1.299.000 | F72: https://www.ruparupa.com/p/zoe-set-meja-dan-kursi-makan-1-meja-dan-4-kursi.html?itm_source=search&itm_campaign=direct_search&itm_term=meja-makan-%26-10061281&itm_device=desktop&queryId=217487d5e7b512dbf8843573e1b11234&sid=m4dm5JgBSC0oiPerg6dT | G72: Rp1.300.000 | H72: https://tk.tokopedia.com/ZSAfhEg5o/ | I72: Rp650.000 | J72: https://tk.tokopedia.com/ZSAfk84B9/ | K72: Meja sudah include 4 kursi | O72: =L72*M72+N72 -> 0 | R72: =C72-L72 -> 2
A73: 7 | B73: Kursi Makan Karyawan (bisa pakai kursi bakso) | C73: 8 | D73: Pcs | E73: Rp23.300 | F73: https://www.tokopedia.com/ngobral/kursi-bakso-rotan-kursi-bakso-tikar-plastik-bangku-anyam-tinggi-coklat-coklat?extParam=ivf%3Dfalse%26keyword%3Dkursi+bakso%26search_id%3D202508260144204734BA6F3DE83D1A4MYS%26src%3Dsearch&t_id=1756172367635&t_st=7&t_pp=search_result&t_efo=search_pure_goods_card&t_ef=goods_search&t_sm=&t_spt=search_result | G73: Rp69.900 | H73: https://www.tokopedia.com/salsaashop-1/kursi-bakso-kursi-baso-kursi-kafe-kursi-cafe-besi-kayu-t-50-cm?extParam=ivf%3Dfalse%26keyword%3Dkursi+bakso%26search_id%3D202508260144204734BA6F3DE83D1A4MYS%26src%3Dsearch&t_id=1756172367635&t_st=8&t_pp=search_result&t_efo=search_pure_goods_card&t_ef=goods_search&t_sm=&t_spt=search_result | I73: Rp30.975 | J73: https://www.tokopedia.com/tokopantes/kursi-tinggi-bakso-warna-dx-gmp-coklat-random?extParam=ivf%3Dfalse%26keyword%3Dkursi+bakso%26search_id%3D202508260144204734BA6F3DE83D1A4MYS%26src%3Dsearch&t_id=1756172367635&t_st=11&t_pp=search_result&t_efo=search_pure_goods_card&t_ef=goods_search&t_sm=&t_spt=search_result | O73: =L73*M73+N73 -> 0 | R73: =C73-L73 -> 8
A74: 8 | B74: Kipas Angin Meja | C74: 1 | D74: Pc | E74: 85500 | F74: https://tk.tokopedia.com/ZSAGAHP9a/ | G74: 96000 | H74: https://tk.tokopedia.com/ZSAGAKfYT/ | I74: 80000 | J74: https://tk.tokopedia.com/ZSAGD8qDj/ | K74: Security | O74: =L74*M74+N74 -> 0

Sheet Tools Akinawa
A1: Category | B1: No | C1: Type | D1: Qty | E1: Unit | F1: Kondisi | G1: Tanggal Keluar | H1: Dokumen Surat Keluar
H2: Dokumen di upload pada folder berikut Dokumen Surat Keluar - Tools Akinawa
A3: ARBOR BT 50 | B3: 1 | C3: Arbor Angle Head | D3: 2 | E3: PCS | F3: Belum terpakai
B4: 2 | C4: Arbor L400 Shank 48 | D4: 1 | E4: PCS | F4: Ok
B5: 3 | C5: Arbor L350 Shank 48 | D5: 1 | E5: PCS | F5: Ok
B6: 4 | C6: Arbor L200 Shank 48 | D6: 1 | E6: PCS | F6: Ok
B7: 5 | C7: Arbor Facemill 200 | D7: 1 | E7: PCS | F7: Ok
B8: 6 | C8: Arbor Drill Tapper | D8: 1 | E8: PCS | F8: Belum terpakai
B9: 7 | C9: Arbor L70 Shank 72 | D9: 1 | E9: PCS | F9: Ok
B10: 8 | C10: Arbor Drill Tapper | D10: 1 | E10: PCS | F10: Ok
B11: 9 | C11: Arbor L100 Shank 34 | D11: 1 | E11: PCS | F11: Ok
B12: 10 | C12: Arbor L80 Shank 48 | D12: 1 | E12: PCS | F12: Ok
B13: 11 | C13: Arbor Drill Tapper | D13: 1 | E13: PCS | F13: Ok
B14: 12 | C14: Arbor L100 Shank 35 | D14: 1 | E14: PCS | F14: Ok
B15: 13 | C15: Arbor L100 Shank 44 | D15: 1 | E15: PCS | F15: Ok
... B43: 41 | C43: Arbor ER 40 | D43: 2 | E43: PCS | F43: Ok
A44: ARBOR BT 40 | B44: 1 | C44: Arbor Rusak / Tidak Terpakai dari pertama datang Qty 23 Pcs
C45: Arbor BT 30 / Milling Manual 4 Pcs
B46: 2 | C46: Arbor L 100 Shank 34 | D46: 1 | E46: PCS | F46: OK
B47: 3 | C47: Arbor L100 Shank 50 | D47: 4 | E47: PCS | F47: OK
B48: 4 | C48: Arbor L50 | D48: 5 | E48: PCS | F48: OK
B49: 5 | C49: Arbor Chuck Drill | D49: 2 | E49: PCS | F49: OK
B50: 6 | C50: Arbor L50 Shank 48 | D50: 1 | E50: PCS | F50: OK
B51: 7 | C51: Arbor L130 Shank 48 | D51: 1 | E51: PCS | F51: OK
B52: 8 | C52: Arbor Type C | D52: 1 | E52: PCS | F52: OK
A53: ALAT BANTU | B53: 1 | C53: Ragum Vise Hidrolik | D53: 1 | E53: Pcs | F53: OK
B54: 2 | C54: Rotary Table | D54: 1 | E54: Set | F54: Belum Dipakai
B55: 3 | C55: Ragum manual kotak | D55: 10 | E55: Pcs | F55: Tidak terpakai
B56: 4 | C56: Ragum manual kotak | D56: 1 | E56: Pcs | F56: Ok
B57: 5 | C57: Ragum Bulat | D57: 6 | E57: Pcs | F57: Tidak terpakai
B58: 6 | C58: Dongkrak Hijau | D58: 1 | E58: Pcs | F58: OK
B59: 7 | C59: Kepala Takel / Crane | D59: 1 | E59: Pcs | F59: Tidak terpakai
B60: 8 | C60: Adjuster | D60: 13 | E60: Pcs | F60: OK
B61: 9 | C61: Kepala Boring Head | D61: 4 | E61: Pcs | F61: OK
B62: 10 | C62: Kepala Facemill 80 Apmt | D62: 1 | E62: Pcs | F62: OK
B63: 11 | C63: Kepala Facemill 63 Apmt | D63: 1 | E63: Pcs | F63: OK
B64: 12 | C64: Kepala Facemill 50 Apmt | D64: 1 | E64: Pcs | F64: OK
B65: 13 | C65: Collet ER 40 | D65: 32 | E65: Pcs | F65: OK
... B74: 22 | C74: Chuck Drill Bubut Manual | D74: 1 | E74: Pcs | F74: OK
A75: DRILL | B75: 1 | C75: Drill Ø 49 | D75: 1 | E75: Pcs | F75: Ok (Tidak Terpakai)
B76: 2 | C76: Drill Ø 31 | D76: 1 | E76: Pcs | F76: Ok (Tidak Terpakai)
B77: 3 | C77: Drill Ø 40 | D77: 1 | E77: Pcs | F77: Ok (Tidak Terpakai)
B78: 4 | C78: Drill Ø 43 | D78: 1 | E78: Pcs | F78: Ok (Tidak Terpakai)
B79: 5 | C79: Drill Ø 30 | D79: 1 | E79: Pcs | F79: Ok (Tidak Terpakai)
B80: 6 | C80: U-Drill Ø 48 | D80: 2 | E80: Pcs | F80: Tidak Terpakai
B81: 7 | C81: U-Drill Ø 47 | D81: 2 | E81: Pcs | F81: Tidak Terpakai
B82: 8 | C82: U-Drill Ø 36 | D82: 1 | E82: Pcs | F82: Tidak Terpakai
B83: 9 | C83: U-Drill Ø 50 | D83: 3 | E83: Pcs | F83: Tidak Terpakai
B84: 10 | C84: Chuck Drill Bubut manual | D84: 1 | E84: Pcs | F84: Tidak Terpakai
B85: 11 | C85: Drill Extention | D85: 7 | E85: Pcs | F85: Tidak Terpakai
B86: 12 | C86: Bushing CNC Bubut | D86: 9 | E86: Pcs | F86: Tidak Terpakai
A87: OTHERS | B87: 1 | C87: Drill Extentension | D87: 3 | E87: Pcs | F87: OK
B88: 2 | C88: Facemill Ø 50-63-80 Moldino + APMT | D88: 7 | E88: Pcs | F88: Rusak / Tidak Terpakai Sejak Datang
B89: 3 | C89: Meja Troly Arbor | D89: 2 | E89: Pcs | F89: OK | G89: 45968 | H89: 2025-11-07_SJ MANUAL_AKINAWA_PENGAMBILAN BARANG.pdf
B90: 4 | C90: Meja Ragum Manual | D90: 1 | E90: Pcs | F90: OK
B91: 5 | C91: Meja Open / Lock Arbor BT 40 | D91: 1 | E91: Pcs | F91: OK
B92: 6 | C92: Kunci Ragum Manual | D92: 3 | E92: Pcs | F92: OK
B93: 7 | C93: Bucket Pindad | D93: 2 | E93: Pcs | F93: OK
B94: 8 | C94: Chuck Drill | D94: 3 | E94: Pcs | F94: Tidak Terpakai
B95: 9 | C95: Boring Head | D95: 2 | E95: Pcs | F95: Ok
B96: 10 | C96: Pull Stud Mazak | D96: 16 | E96: Pcs | F96: OK
B97: 11 | C97: Head Heimer | D97: 1 | E97: Pcs | F97: Tidak Terpakai
B98: 12 | C98: Marking Angka | D98: 1 | E98: Set | F98: Tidak Terpakai
B99: 13 | C99: Meja Open / Lock Arbor BT 50 | D99: 1 | E99: Pcs | F99: Ok | G99: 45968 | H99: 2025-11-07_SJ MANUAL_AKINAWA_PENGAMBILAN BARANG.pdf
B100: 14 | C100: Box Tools | D100: 5 | E100: Pcs | F100: Ok
B101: 15 | C101: Mata Bor | D101: 1 | E101: Paket | F101: Ok
B102: 16 | C102: Holder 32 | D102: 3 | E102: Pcs | F102: Tidak Terpakai
B103: 17 | C103: Holder Chamfer | D103: 1 | E103: Pcs | F103: OK
B104: 18 | C104: Holder 25 APMT | D104: 1 | E104: Pcs | F104: OK
B105: 19 | C105: Holder 20 APMT | D105: 1 | E105: Pcs | F105: OK
B106: 20 | C106: Boring Head Kecil | D106: 1 | E106: Pcs | F106: OK
B107: 21 | C107: Holder 45 | D107: 1 | E107: Pcs | F107: OK
B108: 22 | C108: Holder Nanas | D108: 1 | E108: Pcs | F108: Tidak Terpakai
B109: 23 | C109: Holder T Slot 45 | D109: 1 | E109: Pcs | F109: Tidak Terpakai
B110: 24 | C110: U Drill 26 | D110: 1 | E110: Pcs | F110: Tidak Terpakai
B111: 25 | C111: U Drill 22 | D111: 1 | E111: Pcs | F111: Tidak Terpakai
... B113: 27 | C113: Holder DNMG 32 | D113: 1 | E113: Pcs | F113: Tidak Terpakai
B114: 28 | C114: Rak Susun | D114: 3 | E114: Unit | F114: - | G114: 45968 | H114: 2025-11-07_SJ MANUAL_AKINAWA_PENGAMBILAN BARANG.pdf
A115: MESIN | B115: 29 | C115: Mesin Milling Manual | D115: 1 | E115: Unit | F115: - | G115: 45968 | H115: 2025-11-07_SJ MANUAL_AKINAWA_PENGAMBILAN BARANG.pdf
B116: 30 | C116: Mesin Bubut Manual | D116: 1 | E116: Unit | F116: - | G116: 45968 | H116: 2025-11-07_SJ MANUAL_AKINAWA_PENGAMBILAN BARANG.pdf
B117: 31 | C117: Mesin Okuma | D117: 1 | E117: Unit | G117: 45971 | H117: 2025-11-10_SJ MANUAL_PT AKINAWA_PENGAMBILAN MESIN.pdf
B118: 32 | C118: Mesin Doosan | D118: 1 | E118: Unit | G118: 45971 | H118: 2025-11-10_SJ MANUAL_PT AKINAWA_PENGAMBILAN MESIN.pdf
B119: 33 | C119: Mesin CNC YCM | D119: 1 | E119: Unit | G119: 45971 | H119: 2025-11-10_SJ MANUAL_PT AKINAWA_PENGAMBILAN MESIN.pdf
B120: 34 | C120: Mesin CNC Tongtai | D120: 1 | E120: Unit | G120: 45971 | H120: 2025-11-10_SJ MANUAL_PT AKINAWA_PENGAMBILAN MESIN.pdf
B121: 35 | C121: Mesin CNC Bubut Leadwey | D121: 1 | E121: Unit | G121: 45971 | H121: 2025-11-10_SJ MANUAL_PT AKINAWA_PENGAMBILAN MESIN.pdf
B122: 36 | C122: Mesin CNC Mazak | D122: 1 | E122: Unit | G122: 45972 | H122: 2025-11-11_SJ MANUAL_AKINAWA MESIN MAZAK.pdf
B123: 37 | C123: Mesin CNC Vtec | D123: 1 | E123: Unit | G123: 45972 | H123: 2025-11-11_SJ MANUAL_AKINAWA MESIN VTEC.pdf

Sheet Sheet9
C1: PT Imajin Manufaktur Indonesia
A3: Biaya Tambahan Instalasi CCTV
A4: No | B4: Item | C4: Qty | D4: Price | E4: Shipping Fee | F4: Sub Total | G4: Notes | I4: *Harga tidak termasuk ongkir
A5: 1 | B5: Connector BNC | C5: 24 | D5: 15000 | E5: 0 | F5: =C5*D5+E5 -> 360000 | G5: Dibayarkan ke teknisi | I5: No | J5: Item | K5: Volume (L) | L5: Price 1 | M5: Supplier 1 | N5: Price 2 | O5: Supplier 2
A6: 2 | B6: Connector DC | C6: 12 | D6: 10000 | E6: 0 | F6: =C6*D6+E6 -> 120000 | I6: 1 | J6: Polytron | K6: 190 | L6: 3455700 | M6: https://tk.tokopedia.com/ZSUPneQQa/
A7: 3 | B7: Power Supply 20A | C7: 1 | D7: 320000 | E7: 0 | F7: =C7*D7+E7 -> 320000 | I7: 2 | J7: Polytron | K7: 230 | L7: 3673800 | M7: https://tk.tokopedia.com/ZSUPnrGT2/
A8: 4 | B8: Isolasi | C8: 2 | D8: 15000 | E8: 0 | F8: =C8*D8+E8 -> 30000 | I8: 3 | J8: GEA | K8: 222 | L8: 4090100 | M8: https://tk.tokopedia.com/ZSUPnLTne/ | N8: 4015000 | O8: https://tk.tokopedia.com/ZSUPWVoT2/
A9: 5 | B9: Cable Ties | C9: 2 | D9: 25000 | E9: 0 | F9: =C9*D9+E9 -> 50000 | I9: 4 | J9: GEA | K9: 192 | L9: 3625000 | M9: https://tk.tokopedia.com/ZSUPnGATg/ | N9: 3550000 | O9: https://tk.tokopedia.com/ZSUP7jSSp/
A10: 6 | B10: Doradus | C10: 8 | D10: 20000 | E10: 0 | F10: =C10*D10+E10 -> 160000 | I10: 5 | J10: Sanken | K10: 180 | L10: 3424000 | M10: https://tk.tokopedia.com/ZSUPnv8VW/
A11: 7 | B11: Kabel HDMI | C11: 1 | D11: 270000 | E11: 0 | F11: =C11*D11+E11 -> 270000 | I11: 6 | J11: Sanken | K11: 220 | L11: 3789000 | M11: https://tk.tokopedia.com/ZSUPnW3YT/
A12: 8 | B12: Biaya Tarikan Kabel | C12: 170 | D12: 5000 | E12: 0 | F12: =C12*D12+E12 -> 850000 | I12: 7 | J12: RSA | K12: 240 | L12: 3320000 | M12: https://tk.tokopedia.com/ZSUPWtAJU/
A13: 9 | B13: Kabel RG6 | C13: 300 | D13: =798000/300 -> 2660 | E13: 38000 | F13: =C13*D13+E13 -> 836000 | G13: https://tk.tokopedia.com/ZSUUK2r1S/
A14: 10 | B14: Monitor Dahua 22 inch | C14: 1 | D14: 941000 | E14: 28000 | F14: =C14*D14+E14 -> 969000 | G14: https://tk.tokopedia.com/ZSUUKRS77/
A15: 11 | B15: Sewa Tangga | C15: 2 | D15: 150000 | E15: 0 | F15: =(C15*D15)+E15 -> 300000
A16: Grand Total | F16: =SUM(F5:F15) -> 4265000
A18: Catatan | D18: Disetujui Oleh
D19: Shela Oktania | F19: Harmoko

Sheet Maintenance Asset
A1: Access Link Maintenance Report
A2: Maintenance Report
A4: No | B4: Tanggal Maintenance | C4: Nomor Asset | D4: Nama Asset | E4: Identitas Asset | F4: Komponen Perbaikan | G4: Person in Charge | H4: Maintenance Fee
A5: 1 | B5: 45668 | C5: FA322/IV/01 | D5: HONDA VARIO 125 | F5: Pembayaran pajak tahunan | G5: Rispandi
A6: 2 | B6: 45677 | C6: FA323/IV/02 | D6: ALL NEW AVANZA 1.3 E CVT | E6: F 1310 FBM | F6: Pembayaran pajak tahunan | G6: Mahmudin
A7: 3 | B7: 45700 | C7: FA322/IV/01 | D7: HONDA VARIO 125 | F7: Perpanjangan asuransi | G7: Della
A8: 4 | B8: 45755 | C8: FA073/IV/01 | D8: Daihatsu Granmax | E8: F 82526 HS | F8: Perpanjangan izin KIR | G8: Rispandi | H8: 100000
A9: 5 | B9: 45756 | C9: FA247/IV/02 | D9: Truk Isuzu Elf NKR 55 CC E2-1 | E9: F 8298 MC | F9: Pembayaran pajak tahunan | G9: Mahmudin
A10: 6 | B10: 45776 | C10: FA323/IV/02 | D10: ALL NEW AVANZA 1.3 E CVT | E10: F 1310 FBM | F10: Service Rutin Avanza Auto2000 | G10: Mahmudin | H10: 0
A11: 7 | B11: 45802 | C11: FA247/IV/02 | D11: Truk Isuzu Elf NKR 55 CC E2-1 | E11: F 8298 MC | F11: Ganti oli mesin, Filter Solar, Filter Oli | G11: Mahmudin | H11: 576000
A12: 8 | B12: 45832 | C12: FA247/IV/02 | D12: Truk Isuzu Elf NKR 55 CC E2-1 | E12: F 8298 MC | F12: Service radiator. perbaikan Bocor Ganti tutup atas + Ganti Air coolant | G12: Mahmudin | H12: 550000
A13: 9 | B13: 45838 | C13: FA322/IV/01 | D13: Honda Vario 125 CC | E13: F 5469 FJD | F13: Vanbelt, Roller, Oli Mesin, CVT | G13: Rispandi | H13: 384500
A14: 10 | B14: 45848 | C14: FA354/I/01 | D14: Printer Canon PIXMA G4770 All in One ADF WiFi FAX pengganti G4010 | E14: - | F14: Network | G14: Dimas | H14: 0
A15: 11 | B15: 45864 | C15: FA073/IV/01 | D15: Daihatsu Granmax | E15: F 8526 HS | F15: Busi, Oli Mesin, Filter Oli, Air Cleaner, Filter AC, Brake Fluid, Radiator Coolant + Flushing | G15: Rispandi | H15: 2990500
A16: 12 | B16: 45890 | C16: FA073/IV/01 | D16: Daihatsu Granmax | E16: F 8526 HS | F16: Ban | G16: Rispandi | H16: 2342500
A17: 13 | B17: 45913 | C17: FA073/IV/02 | D17: Daihatsu Granmax | E17: F 8526 HS | F17: AC | G17: Hendra | H17: 1500000
A18: 14 | B18: 45975 | C18: FA116/III/01 | D18: LENOVO IDEAPAD 3 14 i5 1035G1 8GB 256SSD W10 14.0FHD | F18: Maintenance & repasta | G18: Dimas | H18: 50000
A19: 15 | B19: 45978 | C19: FA116/III/01 | D19: LENOVO IDEAPAD 3 14 i5 1035G1 8GB 256SSD W10 14.0FHD | F19: Mainboard | G19: Dimas | H19: 0
A20: 16 | B20: 45973 | C20: FA398/III/01 | D20: Laptop Acer Nitro V 15 ANV15-51 i9-13900H RTX4060 512G 15.6”FHD 144Hz W11 OHS - Ram 64GB | F20: BIOS Password & Instal Ulang | G20: Dimas | H20: 0
A21: 17 | C21: FA066/III/01 | D21: ASUS TUF | FX506HC | I535B6TO11 |8GB 512SSD RTX3050 4GB GRY | F21: Instal Ulang Windows | G21: Dimas | H21: 0
A22: 18 | C22: FA318/III/01 | D22: HP PAVILION 14-DV2000TX I7-1255U 16GB 512GB SSD MX550 14" FHD IPS BACKLIT W11 OHS SILVER FINGERPRINT BAG 5CD242B8K2 | F22: Instal Ulang Windows | G22: Dimas | H22: 0
A23: 19 | B23: 45968 | C23: FA026/III/01 | D23: 3 MONITOR + KEYBOARD 2 + MOUSE 2 + ACC + KABEL VGA + KABEL USG EXT STD | F23: Repasta dan Intal Ulang Windows | G23: Dimas | H23: 75000
A24: 20 | B24: 45957 | C24: FA118/III/02 | D24: LENOVO IDEAPAD SLIM 3I I5-1235U 512GB SSD 8GB ABYSS BLUE | F24: Instal Ulang Windows | G24: Dimas | H24: 0
A25: 21 | B25: 45958 | C25: FA298/III/01 | D25: HP PAVILION 14-DV2000TX-I7-1255U 16GB 512 SSD MX550 | F25: Instal Ulang Windows | G25: Dimas | H25: 0
A26: 22
A27: 23
A28: 24
A29: 25
A30: 26
A31: 27
A32: 28
A33: 29
A34: 30
A35: 31
A36: 32
A37: 33
... A120: 116

Sheet Database
A2: Chendy Martika Jaya | B2: Chendy
A3: Joseline Olivia | B3: Joseline
A4: Stefanus Hodir | B4: Stefanus
A5: Shela Oktania | B5: Shela Oktania
A6: Silmi Khoiriyah | B6: Silmi
A7: Adi Kusumah | B7: Adi Kusumah
A8: Rafida Afnan | B8: Rafida
A9: Rispandi Mandala Putra | B9: Rispandi
A10: Fitria | B10: Fitria
A11: Corneleo Dimas Yulendra Wasisto | B11: Corneleo
A12: Harmoko | B12: Harmoko
A13: Melisa Aprilia | B13: Melisa
... A53: Carissa Christybella | B53: Carissa

Sheet Planning SO Asset 2024
A1: Planning SO Asset 2024
A3: PIC | C3: Activity | D3: Duration | E3: Start Date | F3: End Date | G3: Progress | H3: Notes
A4: Lead | B4: Support
A5: Dimas | B5: Rino, Kevin, Della | C5: Retagging All Asset | D5: 3 weeks | E5: 28/10/2024 | F5: 15/11/2024 | G5: Identified 263/269 Asset (BSD) Identified 136/142 Asset (Deltamas 1) Identified 19/21 Asset (Deltamas 2) Identified 16 assets not yet recorded | H5: 6 tidak teridentifikasi karena tidak ditemukan barangnya. (BSD) 4 odd | 3 lost (dari so tahun kemarin) | 123 active (tagged & identified) | 1 sold (2023) | 13 broken (deltamas 1) 203 Done | 9 Broken | 19 Missing | 15 not identified | 21 belum di tag | 3
A6: Arina | B6: Della | C6: Document Preparation | D6: 1 day | E6: 18/11/2024 | F6: 18/11/2024 | G6: Done (19/11/2024)
A7: Arina | B7: Della | C7: Team Briefing | D7: 1 day | E7: 18/11/2024 | F7: 18/11/2024 | G7: Done (20/11/2024)
A8: Dimas (BSD) Rino (Deltamas) | B8: Rispandi (BSD) Diki (Deltamas) | C8: Stock Opname Batch 1 | D8: 3 days | E8: 19/11/2024 | F8: 21/11/2024 | G8: Done
A9: Dimas (BSD) Rino (Deltamas) | B9: Arina, Della (BSD) Diki (Deltamas) | C9: Stock Opname Batch 2 | D9: 3 days | E9: 22/11/2024 | F9: 26/11/2024 | G9: Done
A10: Dimas (BSD) Rino (Deltamas) | B10: Rispandi, Agus RH (BSD) Wahyu QC (Deltamas) | C10: Stock Opname Batch 3 | D10: 3 days | E10: 27/11/2024 | F10: 29/11/2024 | G10: Done
A11: Della | B11: Rino | C11: Buffer Stock Opname | D11: 1 week | E11: 45334 | F11: 45455 | G11: In Progress | H11: Handover Inventory
A12: Arina | B12: Della | C12: Team Briefing | D12: 1 day | E12: 45547 | F12: 45547
A13: Arina | B13: Della | C13: Compile Stock Opname Report | D13: 2 days | E13: 45577 | F13: 45608
A14: Arina | B14: Della | C14: Report Stock Opname | D14: 1 day | E14: 45638 | F14: 45638
A15: Dimas (BSD) Rino (Deltamas) | B15: Arina, Della | C15: Reconciliation | D15: 3 days | E15: 13/12/2024 | F15: 17/12/2024
A16: Arina | B16: Della | C16: Meeting dg Purchasing & Finance | D16: 1 day | E16: 17/12/2024 | F16: 17/12/2024
A17: Arina | B17: Della | C17: Final Report Stock Opname | D17: 1 day | E17: 18/12/2024 | F17: 18/12/2024

Sheet Planning SO Asset 2025
A1: Planning SO Asset 2025
A3: PIC | C3: Activity | D3: Duration | E3: Start Date | F3: End Date | G3: Description
A4: Lead | B4: Support
A5: Dimas | B5: Arina, Della, Rino | C5: Development of Stock Opname Platform | D5: 10 Days | E5: 13/10/2025 | F5: 28/10/2025 | G5: Proses development platform asset management dengan fitur utama Stock Opname
A6: Dimas | B6: Arina, Della, Rino | C6: Data Optimalization on Stock Opname Platform | D6: 5 Days | E6: 20/10/2025 | F6: 28/10/2025 | G6: Proses optimalisasi data dan upload seluruh asset yang telah tercatat dari awal pembelian hingga asset yang dibeli pada September 2025
A7: Dimas | B7: Arina, Della, Rino, Rispandi, Andi | C7: Presentation of new Asset Management Platform | D7: 1 Day | E7: 29/10/2025 | F7: 29/10/2025
A8: Della | B8: Arina | C8: Team Briefing | D8: 1 Day | E8: 29/10/2025 | F8: 29/10/2025 | G8: Briefing informasi proses SO
A9: Della | B9: Rino, Dimas, Rispandi, Andi | C9: Tag Checking & Tagging New Asset | D9: 5 Days | E9: 45727 | F9: 45849 | G9: Proses checking setiap asset yang sudah diberi tag pada SO sebelumnya dan tagging asset baru 2025 sampai bulan September
A10: Dimas (BSD) Rino (Business Unit) | B10: Arina, Della, Rispandi, Andi | C10: Stock Opname | D10: 5 Days | E10: 45941 | F10: 14/11/2025
A11: Della | B11: Rino, Dimas, Rispandi, Andi | C11: Tagging New Asset | D11: 3 Days | E11: 45941 | F11: 46002 | G11: Proses tagging asset yang dibeli pada bulan Oktober 2025
A12: Della | B12: Arina, Dimas, Rispandi, Rino, Andi | C12: Maintenance Process for 'Broken' Assets | D12: 32 Days | E12: 45941 | F12: 46003
A13: Dimas (BSD) Rino (Business Unit) | B13: Arina, Della, Rispandi, Andi | C13: Buffer Stock Opname | D13: 5 Days | E13: 17/11/2025 | F13: 21/11/2025
A14: Della | B14: Arina, Rino | C14: Compile Stock Opname Report | D14: 5 Days | E14: 24/11/2025 | F14: 28/11/2025
A15: Della | B15: Rino, Dimas, Rispandi, Andi | C15: Tagging New Asset | D15: 3 Days | E15: 45669 | F15: 45728 | G15: Proses tagging asset yang dibeli pada bulan November 2025
A16: Della | B16: Arina, Dimas, Rispandi, Rino, Andi | C16: Finalization of Stock Opname | D16: 5 Days | E16: 45669 | F16: 45789
A17: Della | B17: Arina, Rino | C17: Report Stock Opname | D17: 3 Days | E17: 45728 | F17: 45789
A18: Della | B18: Arina | C18: Reconciliation | D18: 2 Days | E18: 45881 | F18: 46003
A19: Della | B19: Arina, Rino | C19: Final Report Stock Opname | D19: 1 Day | E19: 22/12/2025 | F19: 22/12/2025

Sheet Sheet10
B2: STOCK OPNAME TIMELINE
B5: PHASE | C5: DETAILS | H5: October | W5: November | AQ5: December | BI5: PIC
H7: 13 | I7: 14 | J7: 15 | K7: 16 | L7: 17 | M7: 20 | N7: 21 | O7: 22 | P7: 23 | Q7: 24 | R7: 27 | S7: 28 | T7: 29 | U7: 30 | V7: 31 | W7: 3 | X7: 4 | Y7: 5 | Z7: 6 | AA7: 7 | AB7: 10 | AC7: 11 | AD7: 12 | AE7: 13 | AF7: 14 | AG7: 17 | AH7: 18 | AI7: 19 | AJ7: 20 | AK7: 21 | AL7: 24 | AM7: 25 | AN7: 26 | AO7: 27 | AP7: 28 | AQ7: 1 | AR7: 2 | AS7: 3 | AT7: 4 | AU7: 5 | AV7: 8 | AW7: 9 | AX7: 10 | AY7: 11 | AZ7: 12 | BA7: 15 | BB7: 16 | BC7: 17 | BD7: 18 | BE7: 19 | BF7: 22 | BG7: 23 | BH7: 24
B8: 1 | C8: Development | F8: Development of Asset Management Platform | H8: Main Feature for Stock Opname | T8: Additional Feature | BH8: S O C O M P L E T E | BI8: Dimas
F9: Optimalization of new Asset Management Platform | M9: Main data for Stock Opname | T9: Additional Data and New Data of Fixed Asset | BI9: Dimas
F10: Presentation of new Asset Management Platform | BI10: Dimas
B11: 2 | C11: Administration | F11: Team Briefing | BI11: Della
F12: Administrative Fullfilment | H12: Pull data from Supply Chain & Crosscheck with Finance (Main Data) | W12: Pull data from Supply Chain & Crosscheck with Finance (Additional Data & New Assets) | BI12: Della
B13: 3 | C13: Stock Opname | F13: Tag Checking | BI13: Dimas, Rino
F14: Tagging New Asset | W14: New Asset from Jan to Sep | AB14: New Asset Oct | BI14: Dimas, Rino
F15: Stock Opname | AB15: SO Asset until Sep 25 | BI15: Dimas, Rino
F16: Buffer Stock Opname | AG16: SO Asset Oct 25 | BI16: Dimas, Rino
F17: Finalization Stock Opname | AQ17: Finalization for New Asset Nov 25 | BI17: Dimas, Rino
B18: 4 | C18: Maintenance | F18: Identification Process for 'Broken' Assets | AB18: Identification for Asset until Sep 25 | BI18: Arina, Della
F19: Assigning each Broken Assets to PIC | BI19: Arina, Della
F20: Maintenance Process for Broken Assets | BI20: Rino
B21: 5 | C21: Closing | F21: Report of Stock Opname Result | BI21: Della
F22: Reconciliation | BI22: Della
F23: Release Final Report of Stock Opname Result | BI23: Della

Sheet Analysis
A2: Total Assets | B2: =COUNTA('List of Assets'!F10:F1075) -> 538
A3: Site | C3: Status | E3: Cost
A4: BSD | B4: =countif('List of Assets'!L:L,A4) -> 307 | C4: Active | D4: =countif('List of Assets'!R:R,C4) -> 442 | E4: Finance | F4: =sum('List of Assets'!H:H) -> 8821439227 | G4: GA | H4: =sum('List of Assets'!I:I) -> 137215306
A5: Deltamas 1 | B5: =countif('List of Assets'!L:L,A5) -> 207 | C5: Lost/ Missing | D5: =countif('List of Assets'!R:R,C5) -> 19 | E5: Active | F5: =sumif('List of Assets'!R:R,E5,'List of Assets (Old Data)'!E:E) -> 8209886709 | G5: Active | H5: =sumif('List of Assets'!R:R,G5,'List of Assets'!I:I) -> 118916156
A6: Deltamas 2 | B6: =countif('List of Assets'!L:L,A6) -> 24 | C6: Broken | D6: =countif('List of Assets'!R:R,C6) -> 21 | E6: Lost/ Missing | F6: =sumif('List of Assets'!R:R,E6,'List of Assets'!H:H) -> 87159900 | G6: Lost/ Missing | H6: =sumif('List of Assets'!R:R,G6,'List of Assets'!I:I) -> 0
A7: Not Identified Yet | B7: =B2-sum(B4:B6) -> 0 | C7: Sell | D7: =countif('List of Assets'!R:R,C7) -> 1 | E7: Broken | F7: =sumif('List of Assets'!R:R,E7,'List of Assets'!H:H) -> 69375387 | G7: Broken | H7: =sumif('List of Assets'!R:R,G7,'List of Assets'!I:I) -> 0
C8: Donate | D8: =countif('List of Assets'!R:R,C8) -> 0 | E8: Sell | F8: =sumif('List of Assets'!R:R,E8,'List of Assets'!H:H) -> 0 | G8: Sell | H8: =sumif('List of Assets (Old Data)'!N:N,G8,'List of Assets (Old Data)'!F:F) -> 0
C9: Dispose | D9: =countif('List of Assets'!R:R,C9) -> 0 | E9: Donate | F9: =sumif('List of Assets'!R:R,E9,'List of Assets'!H:H) -> 0 | G9: Donate | H9: =sumif('List of Assets (Old Data)'!N:N,G9,'List of Assets (Old Data)'!F:F) -> 0
C10: Not Identified Yet | D10: =B2-(sum(D4:D9)) -> 55 | E10: Dispose | F10: =sumif('List of Assets'!R:R,E10,'List of Assets'!H:H) -> 0 | G10: Dispose | H10: =sumif('List of Assets (Old Data)'!N:N,G10,'List of Assets (Old Data)'!F:F) -> 0
A12: 2024
A13: Total Assets | B13: =counta('List of Assets'!F371:F455) -> 85
A14: Site | C14: Status | E14: Cost
A15: BSD | B15: =countif('List of Assets'!L371:L455,A15) -> 62 | C15: Active | D15: =countif('List of Assets'!$R$371:$R$455,C15) -> 85 | E15: Total | F15: =sum('List of Assets'!H371:H455) -> 5228900577
A16: Deltamas 1 | B16: =countif('List of Assets'!L371:L455,A16) -> 12 | C16: Lost/ Missing | D16: =countif('List of Assets'!$R$371:$R$437,C16) -> 0 | E16: Active | F16: =sumif('List of Assets'!$R$371:$R$456,E16,'List of Assets'!$H$371:$H$456) -> 5230100577
A17: Deltamas 2 | B17: =countif('List of Assets'!L371:L455,A17) -> 11 | C17: Broken | D17: =countif('List of Assets'!$R$371:$R$437,C17) -> 0 | E17: Lost/ Missing | F17: =sumif('List of Assets'!$R$371:$R$456,E17,'List of Assets'!$H$371:$H$456) -> 0
C18: Sell | D18: =countif('List of Assets'!$R$371:$R$437,C18) -> 0 | E18: Broken | F18: =sumif('List of Assets'!$R$371:$R$456,E18,'List of Assets'!$H$371:$H$456) -> 0
C19: Donate | D19: =countif('List of Assets'!$R$371:$R$437,C19) -> 0 | E19: Sell | F19: =sumif('List of Assets'!$R$371:$R$456,E19,'List of Assets'!$H$371:$H$456) -> 0
C20: Dispose | D20: =countif('List of Assets'!$R$371:$R$437,C20) -> 0 | E20: Donate | F20: =sumif('List of Assets'!$R$371:$R$456,E20,'List of Assets'!$H$371:$H$456) -> 0
C21: Not Identified Yet | D21: =countif('List of Assets'!$R$371:$R$437,C21) -> 0 | E21: Dispose | F21: =sumif('List of Assets'!$R$371:$R$456,E21,'List of Assets'!$H$371:$H$456) -> 0

Sheet Catatan Dimas
A1: Tidak Ada di BSD | B1: Tidak Ada Sticker | D1: Nama Asset | E1: Site | F1: PIC
D2: 3D Printer - Anet e12 | E2: BSD | F2: Agus
D3: 3D Printer - Creality cr20pro | E3: BSD | F3: Agus
D4: 3D Printer - Creality Ender 3 pro | E4: BSD | F4: Agus
D5: 3D Printer - Creality Ender 3 pro | E5: BSD | F5: Agus
D6: 3D Printer - Creality crealityEnder 5 | E6: BSD | F6: Hari TM
D7: 3D Printer - Creality ld003 | E7: BSD | F7: Hari TM
D8: 3D Printer - IMA-2020 | E8: BSD | F8: Hari TM
D9: 3D Printer - Creality Ender 3 Pro | E9: Deltamas 1
D10: 3D Printer - Creality Ender 5 | E10: Deltamas 1
D11: 3D Printer Custom (Makerbase) | E11: Deltamas 1
D12: Tripod Akira | E12: BSD | F12: Yogie
D13: Tripod Akira | E13: BSD | F13: Fattah
D15: Monitor Sharp Aquos | E15: BSD | F15: Pak Agus
D16: Hector Office Table (Meja Ina) | E16: BSD
D17: Rak Wifi | E17: BSD
D18: Set Office Table (Meja) | E18: Deltamas 1 | F18: 2 Meja (3 Okt 23) 260rb x 2
D21: Laptop Pak Agus (Dell G5 5590) | E21: BSD | F21: Ok
E22: BSD

Sheet checking
A1: LEGENDA | G1: Category | H1: ID Category | J1: Site | K1: ID Site
B2: Lost/ Missing | G2: Elektronik | H2: I | J2: BSD | K2: 01
B3: Broken | G3: Furniture | H3: II | J3: Deltamas 1 | K3: 02
B4: Sell | G4: Laptop and Komp | H4: III | J4: Deltamas 2 | K4: 03
B5: Odd (See Comment) | G5: Kendaraan | H5: IV
B6: Belum diinput Finance | G6: Machine and Tooling | H6: V
B9: ID | C9: Category | D9: ID Category | E9: Asset ID | F9: Asset Name | G9: Purchase Date | H9: Cost (Finance) | I9: Cost (GA & Supply Chain) | J9: PIC | K9: Department | L9: Site | M9: ID Site | N9: Brand | O9: Model | P9: Serial Number | Q9: Notes [SO 2023] | R9: Status | S9: Price
A10: 1 | B10: FA001 | C10: Elektronik | D10: =if(C10=$G$2,$H$2, if(C10=$G$3,$H$3, if(C10=$G$4,$H$4, if(C10=$G$5,$H$5,if(C10=$G$6,$H$6, " "))))) -> I | E10: =CONCATENATE(B10,"/",D10,"/",M10) -> FA001/I/ | F10: MONITOR DELL P2314H 23 INC | G10: 42005 | H10: 3150000 | M10: =if(L10=$J$2,$K$2,if(L10=$J$3,$K$3,if(L10=$J$4,$K$4," "))) | N10: Dell | R10: Lost/ Missing
A11: 2 | B11: FA002 | C11: Elektronik | D11: =if(C11=$G$2,$H$2, if(C11=$G$3,$H$3, if(C11=$G$4,$H$4, if(C11=$G$5,$H$5,if(C11=$G$6,$H$6, " "))))) -> I | E11: =CONCATENATE(B11,"/",D11,"/",M11) -> FA002/I/01 | F11: LAPTOP | G11: 42135 | H11: 6900000 | L11: BSD | M11: =if(L11=$J$2,$K$2,if(L11=$J$3,$K$3,if(L11=$J$4,$K$4," "))) -> 01 | R11: Lost/ Missing
A12: 3 | B12: FA003 | C12: Elektronik | D12: =if(C12=$G$2,$H$2, if(C12=$G$3,$H$3, if(C12=$G$4,$H$4, if(C12=$G$5,$H$5,if(C12=$G$6,$H$6, " "))))) -> I | E12: =CONCATENATE(B12,"/",D12,"/",M12) -> FA003/I/01 | F12: HARDISK | G12: 42135 | H12: 580000 | L12: BSD | M12: =if(L12=$J$2,$K$2,if(L12=$J$3,$K$3,if(L12=$J$4,$K$4," "))) -> 01
A13: 4 | B13: FA004 | C13: Furniture | D13: =if(C13=$G$2,$H$2, if(C13=$G$3,$H$3, if(C13=$G$4,$H$4, if(C13=$G$5,$H$5,if(C13=$G$6,$H$6, " "))))) -> II | E13: =CONCATENATE(B13,"/",D13,"/",M13) -> FA004/II/01 | F13: BANGKU | G13: 42249 | H13: 2500000 | L13: BSD | M13: =if(L13=$J$2,$K$2,if(L13=$J$3,$K$3,if(L13=$J$4,$K$4," "))) -> 01 | R13: Lost/ Missing
A14: 5 | B14: FA005 | C14: Furniture | D14: =if(C14=$G$2,$H$2, if(C14=$G$3,$H$3, if(C14=$G$4,$H$4, if(C14=$G$5,$H$5,if(C14=$G$6,$H$6, " "))))) -> II | E14: =CONCATENATE(B14,"/",D14,"/",M14) -> FA005/II/01 | F14: RAK | G14: 42252 | H14: 1787190 | L14: BSD | M14: =if(L14=$J$2,$K$2,if(L14=$J$3,$K$3,if(L14=$J$4,$K$4," "))) -> 01 | R14: Broken
A15: 6 | B15: FA006 | C15: Furniture | D15: =if(C15=$G$2,$H$2, if(C15=$G$3,$H$3, if(C15=$G$4,$H$4, if(C15=$G$5,$H$5,if(C15=$G$6,$H$6, " "))))) -> II | E15: =CONCATENATE(B15,"/",D15,"/",M15) -> FA006/II/01 | F15: MEJA | G15: 42254 | H15: 3034500 | J15: Herfian Pradityo | K15: Engineering | L15: BSD | M15: =if(L15=$J$2,$K$2,if(L15=$J$3,$K$3,if(L15=$J$4,$K$4," "))) -> 01
A16: 7 | B16: FA007 | C16: Furniture | D16: =if(C16=$G$2,$H$2, if(C16=$G$3,$H$3, if(C16=$G$4,$H$4, if(C16=$G$5,$H$5,if(C16=$G$6,$H$6, " "))))) -> II | E16: =CONCATENATE(B16,"/",D16,"/",M16) -> FA007/II/01 | F16: LEMARI | G16: 42278 | H16: 570000 | L16: BSD | M16: =if(L16=$J$2,$K$2,if(L16=$J$3,$K$3,if(L16=$J$4,$K$4," "))) -> 01 | R16: Broken
A17: 8 | B17: FA008 | C17: Furniture | D17: =if(C17=$G$2,$H$2, if(C17=$G$3,$H$3, if(C17=$G$4,$H$4, if(C17=$G$5,$H$5,if(C17=$G$6,$H$6, " "))))) -> II | E17: =CONCATENATE(B17,"/",D17,"/",M17) -> FA008/II/01 | F17: KIPAS | G17: 42279 | H17: 220000 | L17: BSD | M17: =if(L17=$J$2,$K$2,if(L17=$J$3,$K$3,if(L17=$J$4,$K$4," "))) -> 01 | R17: Broken
A18: 9 | B18: FA009 | C18: Elektronik | D18: =if(C18=$G$2,$H$2, if(C18=$G$3,$H$3, if(C18=$G$4,$H$4, if(C18=$G$5,$H$5,if(C18=$G$6,$H$6, " "))))) -> I | E18: =CONCATENATE(B18,"/",D18,"/",M18) -> FA009/I/01 | F18: HP SAMSUNG GALAXY | G18: 42338 | H18: 2950000 | L18: BSD | M18: =if(L18=$J$2,$K$2,if(L18=$J$3,$K$3,if(L18=$J$4,$K$4," "))) -> 01 | N18: Samsung | R18: Lost/ Missing
A19: 10 | B19: FA010 | C19: Elektronik | D19: =if(C19=$G$2,$H$2, if(C19=$G$3,$H$3, if(C19=$G$4,$H$4, if(C19=$G$5,$H$5,if(C19=$G$6,$H$6, " "))))) -> I | E19: =CONCATENATE(B19,"/",D19,"/",M19) -> FA010/I/01 | F19: TV | G19: 42403 | H19: 300000 | L19: BSD | M19: =if(L19=$J$2,$K$2,if(L19=$J$3,$K$3,if(L19=$J$4,$K$4," "))) -> 01 | R19: Lost/ Missing
A20: 11 | B20: FA011 | C20: Laptop and Komp | D20: =if(C20=$G$2,$H$2, if(C20=$G$3,$H$3, if(C20=$G$4,$H$4, if(C20=$G$5,$H$5,if(C20=$G$6,$H$6, " "))))) -> III | E20: =CONCATENATE(B20,"/",D20,"/",M20) -> FA011/III/01 | F20: LAPTOP HP I3 | G20: 42675 | H20: 6540000 | L20: BSD | M20: =if(L20=$J$2,$K$2,if(L20=$J$3,$K$3,if(L20=$J$4,$K$4," "))) -> 01 | N20: HP
A21: 12 | B21: FA012 | C21: Elektronik | D21: =if(C21=$G$2,$H$2, if(C21=$G$3,$H$3, if(C21=$G$4,$H$4, if(C21=$G$5,$H$5,if(C21=$G$6,$H$6, " "))))) -> I | E21: =CONCATENATE(B21,"/",D21,"/",M21) -> FA012/I/01 | F21: MESIN ABSEN | G21: 42522 | H21: 1500000 | L21: BSD | M21: =if(L21=$J$2,$K$2,if(L21=$J$3,$K$3,if(L21=$J$4,$K$4," "))) -> 01 | R21: Lost/ Missing
A22: 13 | B22: FA013 | C22: Elektronik | D22: =if(C22=$G$2,$H$2, if(C22=$G$3,$H$3, if(C22=$G$4,$H$4, if(C22=$G$5,$H$5,if(C22=$G$6,$H$6, " "))))) -> I | E22: =CONCATENATE(B22,"/",D22,"/",M22) -> FA013/I/01 | F22: PRINTER | G22: 42566 | H22: 660000 | L22: BSD | M22: =if(L22=$J$2,$K$2,if(L22=$J$3,$K$3,if(L22=$J$4,$K$4," "))) -> 01 | R22: Lost/ Missing
A23: 14 | B23: FA014 | C23: Furniture | D23: =if(C23=$G$2,$H$2, if(C23=$G$3,$H$3, if(C23=$G$4,$H$4, if(C23=$G$5,$H$5,if(C23=$G$6,$H$6, " "))))) -> II | E23: =CONCATENATE(B23,"/",D23,"/",M23) -> FA014/II/01 | F23: KURSI STAFF | G23: 42466 | H23: 900000 | L23: BSD | M23: =if(L23=$J$2,$K$2,if(L23=$J$3,$K$3,if(L23=$J$4,$K$4," "))) -> 01 | R23: Lost/ Missing
A24: 15 | B24: FA015 | C24: Furniture | D24: =if(C24=$G$2,$H$2, if(C24=$G$3,$H$3, if(C24=$G$4,$H$4, if(C24=$G$5,$H$5,if(C24=$G$6,$H$6, " "))))) -> II | E24: =CONCATENATE(B24,"/",D24,"/",M24) -> FA015/II/01 | F24: HECTOR OFFICE TABLE WALNUT BLACK | G24: 42461 | H24: 750000 | J24: Corneleo | K24: Sales & Marketing | L24: BSD | M24: =if(L24=$J$2,$K$2,if(L24=$J$3,$K$3,if(L24=$J$4,$K$4," "))) -> 01
A25: 16 | B25: FA016 | C25: Laptop and Komp | D25: =if(C25=$G$2,$H$2, if(C25=$G$3,$H$3, if(C25=$G$4,$H$4, if(C25=$G$5,$H$5,if(C25=$G$6,$H$6, " "))))) -> III | E25: =CONCATENATE(B25,"/",D25,"/",M25) -> FA016/III/01 | F25: LAPTOP & MONITOR | G25: 42736 | H25: 21000000 | J25: Adi Kusuma | K25: Engineering | L25: BSD | M25: =if(L25=$J$2,$K$2,if(L25=$J$3,$K$3,if(L25=$J$4,$K$4," "))) -> 01 | R25: Lost/ Missing
A26: 17 | B26: FA017 | C26: Elektronik | D26: =if(C26=$G$2,$H$2, if(C26=$G$3,$H$3, if(C26=$G$4,$H$4, if(C26=$G$5,$H$5,if(C26=$G$6,$H$6, " "))))) -> I | E26: =CONCATENATE(B26,"/",D26,"/",M26) -> FA017/I/01 | F26: PC. DELL PRECISION TOWER 5810 | G26: 42736 | H26: 37505000 | J26: Hari Mulyanto | K26: Engineering | L26: BSD | M26: =if(L26=$J$2,$K$2,if(L26=$J$3,$K$3,if(L26=$J$4,$K$4," "))) -> 01 | N26: Dell | R26: Lost/ Missing
A27: 18 | B27: FA018 | C27: Laptop and Komp | D27: =if(C27=$G$2,$H$2, if(C27=$G$3,$H$3, if(C27=$G$4,$H$4, if(C27=$G$5,$H$5,if(C27=$G$6,$H$6, " "))))) -> III | E27: =CONCATENATE(B27,"/",D27,"/",M27) -> FA018/III/01 | F27: LAPTOP ROG GL552VX | G27: 42979 | H27: 13050000 | L27: BSD | M27: =if(L27=$J$2,$K$2,if(L27=$J$3,$K$3,if(L27=$J$4,$K$4," "))) -> 01 | N27: Asus
A28: 19 | B28: FA019 | C28: Machine and Tooling | D28: =if(C28=$G$2,$H$2, if(C28=$G$3,$H$3, if(C28=$G$4,$H$4, if(C28=$G$5,$H$5,if(C28=$G$6,$H$6, " "))))) -> V | E28: =CONCATENATE(B28,"/",D28,"/",M28) -> FA019/V/02 | F28: PRINTER 3D | G28: 42979 | H28: 3275000 | L28: Deltamas 1 | M28: =if(L28=$J$2,$K$2,if(L28=$J$3,$K$3,if(L28=$J$4,$K$4," "))) -> 02
A29: 20 | B29: FA020 | C29: Elektronik | D29: =if(C29=$G$2,$H$2, if(C29=$G$3,$H$3, if(C29=$G$4,$H$4, if(C29=$G$5,$H$5,if(C29=$G$6,$H$6, " "))))) -> I | E29: =CONCATENATE(B29,"/",D29,"/",M29) -> FA020/I/ | F29: AC POLYTRON | G29: 43049 | H29: 3000000 | M29: =if(L29=$J$2,$K$2,if(L29=$J$3,$K$3,if(L29=$J$4,$K$4," "))) | N29: Polytron | R29: Lost/ Missing
A30: 21 | B30: FA021 | C30: Furniture | D30: =if(C30=$G$2,$H$2, if(C30=$G$3,$H$3, if(C30=$G$4,$H$4, if(C30=$G$5,$H$5,if(C30=$G$6,$H$6, " "))))) -> II | E30: =CONCATENATE(B30,"/",D30,"/",M30) -> FA021/II/01 | F30: HECTOR OFFICE TABLE WALNUT BLA 15 | G30: 43132 | H30: 1400000 | J30: Gio Saputra | K30: HRGA & Legal | L30: BSD | M30: =if(L30=$J$2,$K$2,if(L30=$J$3,$K$3,if(L30=$J$4,$K$4," "))) -> 01
A31: 22 | B31: FA022 | C31: Laptop and Komp | D31: =if(C31=$G$2,$H$2, if(C31=$G$3,$H$3, if(C31=$G$4,$H$4, if(C31=$G$5,$H$5,if(C31=$G$6,$H$6, " "))))) -> III | E31: =CONCATENATE(B31,"/",D31,"/",M31) -> FA022/III/01 | F31: LAPTOP | G31: 43132 | H31: 14548800 | J31: Hari TM | K31: Engineering | L31: BSD | M31: =if(L31=$J$2,$K$2,if(L31=$J$3,$K$3,if(L31=$J$4,$K$4," "))) -> 01
A32: 23 | B32: FA023 | C32: Elektronik | D32: =if(C32=$G$2,$H$2, if(C32=$G$3,$H$3, if(C32=$G$4,$H$4, if(C32=$G$5,$H$5,if(C32=$G$6,$H$6, " "))))) -> I | E32: =CONCATENATE(B32,"/",D32,"/",M32) -> FA023/I/01 | F32: KOMPUTER VGA ASUS | G32: 43160 | H32: 31200000 | L32: BSD | M32: =if(L32=$J$2,$K$2,if(L32=$J$3,$K$3,if(L32=$J$4,$K$4," "))) -> 01 | N32: Asus | R32: Lost/ Missing
A33: 24 | B33: FA024 | C33: Laptop and Komp | D33: =if(C33=$G$2,$H$2, if(C33=$G$3,$H$3, if(C33=$G$4,$H$4, if(C33=$G$5,$H$5,if(C33=$G$6,$H$6, " "))))) -> III | E33: =CONCATENATE(B33,"/",D33,"/",M33) -> FA024/III/01 | F33: ACER PREDATOR NITRO | G33: 43160 | H33: 10999000 | L33: BSD | M33: =if(L33=$J$2,$K$2,if(L33=$J$3,$K$3,if(L33=$J$4,$K$4," "))) -> 01 | N33: Acer | R33: Lost/ Missing
A34: 25 | B34: FA025 | C34: Elektronik | D34: =if(C34=$G$2,$H$2, if(C34=$G$3,$H$3, if(C34=$G$4,$H$4, if(C34=$G$5,$H$5,if(C34=$G$6,$H$6, " "))))) -> I | E34: =CONCATENATE(B34,"/",D34,"/",M34) -> FA025/I/ | F34: AC POLYTRON | G34: 43221 | H34: 3000000 | M34: =if(L34=$J$2,$K$2,if(L34=$J$3,$K$3,if(L34=$J$4,$K$4," "))) | N34: Polytron | R34: Lost/ Missing
A35: 26 | B35: FA026 | C35: Elektronik | D35: =if(C35=$G$2,$H$2, if(C35=$G$3,$H$3, if(C35=$G$4,$H$4, if(C35=$G$5,$H$5,if(C35=$G$6,$H$6, " "))))) -> I | E35: =CONCATENATE(B35,"/",D35,"/",M35) -> FA026/I/01 | F35: 3 MONITOR + KEYBOARD 2 + MOUSE 2 + ACC + KABEL VGA + KABEL USG EXT STD | G35: 43221 | H35: 4920000 | L35: BSD | M35: =if(L35=$J$2,$K$2,if(L35=$J$3,$K$3,if(L35=$J$4,$K$4," "))) -> 01
A36: 27 | B36: FA027 | C36: Elektronik | D36: =if(C36=$G$2,$H$2, if(C36=$G$3,$H$3, if(C36=$G$4,$H$4, if(C36=$G$5,$H$5,if(C36=$G$6,$H$6, " "))))) -> I | E36: =CONCATENATE(B36,"/",D36,"/",M36) -> FA027/I/01 | F36: Camera Sony A6400 | G36: 43256 | H36: 9500032 | J36: Yogi | K36: Digital Marketing & Creative | L36: BSD | M36: =if(L36=$J$2,$K$2,if(L36=$J$3,$K$3,if(L36=$J$4,$K$4," "))) -> 01
A37: 28 | B37: FA028 | C37: Laptop and Komp | D37: =if(C37=$G$2,$H$2, if(C37=$G$3,$H$3, if(C37=$G$4,$H$4, if(C37=$G$5,$H$5,if(C37=$G$6,$H$6, " "))))) -> III | E37: =CONCATENATE(B37,"/",D37,"/",M37) -> FA028/III/01 | F37: Lenovo IP1205 | G37: 43287 | H37: 3900000 | K37: Finance & Accounting | L37: BSD | M37: =if(L37=$J$2,$K$2,if(L37=$J$3,$K$3,if(L37=$J$4,$K$4," "))) -> 01 | N37: Lenovo
A38: 29 | B38: FA029 | C38: Machine and Tooling | D38: =if(C38=$G$2,$H$2, if(C38=$G$3,$H$3, if(C38=$G$4,$H$4, if(C38=$G$5,$H$5,if(C38=$G$6,$H$6, " "))))) -> V | E38: =CONCATENATE(B38,"/",D38,"/",M38) -> FA029/V/02 | F38: 3D PRINTER | G38: 43314 | H38: 2953007 | L38: Deltamas 1 | M38: =if(L38=$J$2,$K$2,if(L38=$J$3,$K$3,if(L38=$J$4,$K$4," "))) -> 02
A39: 30 | B39: FA030 | C39: Elektronik | D39: =if(C39=$G$2,$H$2, if(C39=$G$3,$H$3, if(C39=$G$4,$H$4, if(C39=$G$5,$H$5,if(C39=$G$6,$H$6, " "))))) -> I | E39: =CONCATENATE(B39,"/",D39,"/",M39) -> FA030/I/01 | F39: HP XIAOMI | G39: 43313 | H39: 1320000 | K39: Engineering | L39: BSD | M39: =if(L39=$J$2,$K$2,if(L39=$J$3,$K$3,if(L39=$J$4,$K$4," "))) -> 01 | N39: Xiaomi | R39: Lost/ Missing
A40: 31 | B40: FA031 | C40: Machine and Tooling | D40: =if(C40=$G$2,$H$2, if(C40=$G$3,$H$3, if(C40=$G$4,$H$4, if(C40=$G$5,$H$5,if(C40=$G$6,$H$6, " "))))) -> V | E40: =CONCATENATE(B40,"/",D40,"/",M40) -> FA031/V/01 | F40: 3D PRINTER ANYCUBIC PHOTON | G40: 43378 | H40: 8190000 | K40: Engineering | L40: BSD | M40: =if(L40=$J$2,$K$2,if(L40=$J$3,$K$3,if(L40=$J$4,$K$4," "))) -> 01 | N40: Anycubic
A41: 32 | B41: FA032 | C41: Elektronik | D41: =if(C41=$G$2,$H$2, if(C41=$G$3,$H$3, if(C41=$G$4,$H$4, if(C41=$G$5,$H$5,if(C41=$G$6,$H$6, " "))))) -> I | E41: =CONCATENATE(B41,"/",D41,"/",M41) -> FA032/I/01 | F41: LEMARI & TURN TABLE U/ 3D SCANNING IMAJIN | G41: 43383 | H41: 898900 | L41: BSD | M41: =if(L41=$J$2,$K$2,if(L41=$J$3,$K$3,if(L41=$J$4,$K$4," "))) -> 01 | R41: Lost/ Missing
A42: 33 | B42: FA033 | C42: Elektronik | D42: =if(C42=$G$2,$H$2, if(C42=$G$3,$H$3, if(C42=$G$4,$H$4, if(C42=$G$5,$H$5,if(C42=$G$6,$H$6, " "))))) -> I | E42: =CONCATENATE(B42,"/",D42,"/",M42) -> FA033/I/01 | F42: MESIN ABSEN FINGER SPOA REVO 163BNC | G42: 43557 | H42: 1200000 | L42: BSD | M42: =if(L42=$J$2,$K$2,if(L42=$J$3,$K$3,if(L42=$J$4,$K$4," "))) -> 01 | N42: Revo | R42: Lost/ Missing
A43: 34 | B43: FA034 | C43: Laptop and Komp | D43: =if(C43=$G$2,$H$2, if(C43=$G$3,$H$3, if(C43=$G$4,$H$4, if(C43=$G$5,$H$5,if(C43=$G$6,$H$6, " "))))) -> III | E43: =CONCATENATE(B43,"/",D43,"/",M43) -> FA034/III/01 | F43: LAPTOP ASUS A407 MA N4000 4GB 128 SSD 14' | G43: 43563 | H43: 4116265 | J43: Hendra | K43: Supply Chain | L43: BSD | M43: =if(L43=$J$2,$K$2,if(L43=$J$3,$K$3,if(L43=$J$4,$K$4," "))) -> 01 | N43: Asus
A44: 35 | B44: FA035 | C44: Elektronik | D44: =if(C44=$G$2,$H$2, if(C44=$G$3,$H$3, if(C44=$G$4,$H$4, if(C44=$G$5,$H$5,if(C44=$G$6,$H$6, " "))))) -> I | E44: =CONCATENATE(B44,"/",D44,"/",M44) -> FA035/I/02 | F44: AC GREE GWC 05C3E INDOOR + OUTDOOR (1/2 PK) | G44: 43679 | H44: 2799000 | K44: HRGA & Legal | L44: Deltamas 1 | M44: =if(L44=$J$2,$K$2,if(L44=$J$3,$K$3,if(L44=$J$4,$K$4," "))) -> 02 | N44: Gree | R44: Active
A45: 36 | B45: FA036.1 | C45: Elektronik | D45: =if(C45=$G$2,$H$2, if(C45=$G$3,$H$3, if(C45=$G$4,$H$4, if(C45=$G$5,$H$5,if(C45=$G$6,$H$6, " "))))) -> I | E45: =CONCATENATE(B45,"/",D45,"/",M45) -> FA036.1/I/02 | F45: AC GREE GWC 09C3E INDOOR + OUTDOOR (1 PK) | G45: 43679 | H45: 3049000 | K45: HRGA & Legal | L45: Deltamas 1 | M45: =if(L45=$J$2,$K$2,if(L45=$J$3,$K$3,if(L45=$J$4,$K$4," "))) -> 02 | N45: Gree | R45: Active
A46: 37 | B46: FA036.2 | C46: Elektronik | D46: =if(C46=$G$2,$H$2, if(C46=$G$3,$H$3, if(C46=$G$4,$H$4, if(C46=$G$5,$H$5,if(C46=$G$6,$H$6, " "))))) -> I | E46: =CONCATENATE(B46,"/",D46,"/",M46) -> FA036.2/I/02 | F46: AC GREE GWC 09C3E INDOOR + OUTDOOR (1 PK) | G46: 43679 | H46: 3049000 | K46: HRGA & Legal | L46: Deltamas 1 | M46: =if(L46=$J$2,$K$2,if(L46=$J$3,$K$3,if(L46=$J$4,$K$4," "))) -> 02 | N46: Gree | R46: Active
A47: 38 | B47: FA036.3 | C47: Elektronik | D47: =if(C47=$G$2,$H$2, if(C47=$G$3,$H$3, if(C47=$G$4,$H$4, if(C47=$G$5,$H$5,if(C47=$G$6,$H$6, " "))))) -> I | E47: =CONCATENATE(B47,"/",D47,"/",M47) -> FA036.3/I/03 | F47: AC GREE GWC 09C3E INDOOR + OUTDOOR (1 PK) | G47: 43679 | H47: 3049000 | K47: HRGA & Legal | L47: Deltamas 2 | M47: =if(L47=$J$2,$K$2,if(L47=$J$3,$K$3,if(L47=$J$4,$K$4," "))) -> 03 | N47: Gree | R47: Active
A48: 39 | B48: FA037 | C48: Elektronik | D48: =if(C48=$G$2,$H$2, if(C48=$G$3,$H$3, if(C48=$G$4,$H$4, if(C48=$G$5,$H$5,if(C48=$G$6,$H$6, " "))))) -> I | E48: =CONCATENATE(B48,"/",D48,"/",M48) -> FA037/I/02 | F48: AC GREE GKH 48K3H INDDOOR + OUTDOOR (5 PK) | G48: 43679 | L48: Deltamas 1 | M48: =if(L48=$J$2,$K$2,if(L48=$J$3,$K$3,if(L48=$J$4,$K$4," "))) -> 02 | N48: Gree | R48: Sell | S48: 22500000
A49: 40 | B49: FA038.1 | C49: Furniture | D49: =if(C49=$G$2,$H$2, if(C49=$G$3,$H$3, if(C49=$G$4,$H$4, if(C49=$G$5,$H$5,if(C49=$G$6,$H$6, " "))))) -> II | E49: =CONCATENATE(B49,"/",D49,"/",M49) -> FA038.1/II/02 | F49: KNOXHULT BASE CB W DRS/DRW 120 WHI | G49: 43690 | H49: 2550000 | L49: Deltamas 1 | M49: =if(L49=$J$2,$K$2,if(L49=$J$3,$K$3,if(L49=$J$4,$K$4," "))) -> 02 | R49: Broken
A50: 41 | B50: FA038.2 | C50: Furniture | D50: =if(C50=$G$2,$H$2, if(C50=$G$3,$H$3, if(C50=$G$4,$H$4, if(C50=$G$5,$H$5,if(C50=$G$6,$H$6, " "))))) -> II | E50: =CONCATENATE(B50,"/",D50,"/",M50) -> FA038.2/II/03 | F50: KNOXHULT BASE CB W DOORS 80X85 WHITE AP | G50: 43690 | H50: 1500000 | K50: HRGA & Legal | L50: Deltamas 2 | M50: =if(L50=$J$2,$K$2,if(L50=$J$3,$K$3,if(L50=$J$4,$K$4," "))) -> 03 | N50: Knoxhult | R50: Active
A51: 42 | B51: FA039.1 | C51: Furniture | D51: =if(C51=$G$2,$H$2, if(C51=$G$3,$H$3, if(C51=$G$4,$H$4, if(C51=$G$5,$H$5,if(C51=$G$6,$H$6, " "))))) -> II | E51: =CONCATENATE(B51,"/",D51,"/",M51) -> FA039.1/II/01 | F51: LOMO STAFF CHAIR + NEWVY 4 TIER BLACK | G51: 43692 | H51: 799500 | J51: Herfian | K51: Engineering | L51: BSD | M51: =if(L51=$J$2,$K$2,if(L51=$J$3,$K$3,if(L51=$J$4,$K$4," "))) -> 01 | N51: Informa
A52: 43 | B52: FA039.2 | C52: Furniture | D52: =if(C52=$G$2,$H$2, if(C52=$G$3,$H$3, if(C52=$G$4,$H$4, if(C52=$G$5,$H$5,if(C52=$G$6,$H$6, " "))))) -> II | E52: =CONCATENATE(B52,"/",D52,"/",M52) -> FA039.2/II/01 | F52: LOMO STAFF CHAIR + NEWVY 4 TIER BLACK | G52: 43692 | H52: 799500 | J52: Bilkis | K52: PITD | L52: BSD | M52: =if(L52=$J$2,$K$2,if(L52=$J$3,$K$3,if(L52=$J$4,$K$4," "))) -> 01 | N52: Informa
A53: 44 | B53: FA039.3 | C53: Furniture | D53: =if(C53=$G$2,$H$2, if(C53=$G$3,$H$3, if(C53=$G$4,$H$4, if(C53=$G$5,$H$5,if(C53=$G$6,$H$6, " "))))) -> II | E53: =CONCATENATE(B53,"/",D53,"/",M53) -> FA039.3/II/01 | F53: LOMO STAFF CHAIR + NEWVY 4 TIER BLACK | G53: 43692 | H53: 799500 | J53: Adya | K53: Finance & Accounting | L53: BSD | M53: =if(L53=$J$2,$K$2,if(L53=$J$3,$K$3,if(L53=$J$4,$K$4," "))) -> 01 | N53: Informa
A54: 45 | B54: FA039.4 | C54: Furniture | D54: =if(C54=$G$2,$H$2, if(C54=$G$3,$H$3, if(C54=$G$4,$H$4, if(C54=$G$5,$H$5,if(C54=$G$6,$H$6, " "))))) -> II | E54: =CONCATENATE(B54,"/",D54,"/",M54) -> FA039.4/II/01 | F54: LOMO STAFF CHAIR + NEWVY 4 TIER BLACK | G54: 43692 | H54: 799500 | J54: Audrey | K54: Finance & Accounting | L54: BSD | M54: =if(L54=$J$2,$K$2,if(L54=$J$3,$K$3,if(L54=$J$4,$K$4," "))) -> 01 | N54: Informa
A55: 46 | B55: FA039.5 | C55: Furniture | D55: =if(C55=$G$2,$H$2, if(C55=$G$3,$H$3, if(C55=$G$4,$H$4, if(C55=$G$5,$H$5,if(C55=$G$6,$H$6, " "))))) -> II | E55: =CONCATENATE(B55,"/",D55,"/",M55) -> FA039.5/II/01 | F55: LOMO STAFF CHAIR + NEWVY 4 TIER BLACK | G55: 43692 | H55: 799500 | J55: Della | K55: HRGA & Legal | L55: BSD | M55: =if(L55=$J$2,$K$2,if(L55=$J$3,$K$3,if(L55=$J$4,$K$4," "))) -> 01 | N55: Informa
A56: 47 | B56: FA039.6 | C56: Furniture | D56: =if(C56=$G$2,$H$2, if(C56=$G$3,$H$3, if(C56=$G$4,$H$4, if(C56=$G$5,$H$5,if(C56=$G$6,$H$6, " "))))) -> II | E56: =CONCATENATE(B56,"/",D56,"/",M56) -> FA039.6/II/01 | F56: LOMO STAFF CHAIR + NEWVY 4 TIER BLACK | G56: 43692 | H56: 799500 | J56: Ardi | K56: PITD | L56: BSD | M56: =if(L56=$J$2,$K$2,if(L56=$J$3,$K$3,if(L56=$J$4,$K$4," "))) -> 01 | N56: Informa
A57: 48 | B57: FA039.7 | C57: Furniture | D57: =if(C57=$G$2,$H$2, if(C57=$G$3,$H$3, if(C57=$G$4,$H$4, if(C57=$G$5,$H$5,if(C57=$G$6,$H$6, " "))))) -> II | E57: =CONCATENATE(B57,"/",D57,"/",M57) -> FA039.7/II/01 | F57: LOMO STAFF CHAIR + NEWVY 4 TIER BLACK | G57: 43692 | H57: 799500 | L57: BSD | M57: =if(L57=$J$2,$K$2,if(L57=$J$3,$K$3,if(L57=$J$4,$K$4," "))) -> 01 | N57: Informa
A58: 49 | B58: FA039.8 | C58: Furniture | D58: =if(C58=$G$2,$H$2, if(C58=$G$3,$H$3, if(C58=$G$4,$H$4, if(C58=$G$5,$H$5,if(C58=$G$6,$H$6, " "))))) -> II | E58: =CONCATENATE(B58,"/",D58,"/",M58) -> FA039.8/II/01 | F58: LOMO STAFF CHAIR + NEWVY 4 TIER BLACK | G58: 43692 | H58: 799500 | J58: Arina | K58: HRGA & Legal | L58: BSD | M58: =if(L58=$J$2,$K$2,if(L58=$J$3,$K$3,if(L58=$J$4,$K$4," "))) -> 01 | N58: Informa
A59: 50 | B59: FA039.9 | C59: Furniture | D59: =if(C59=$G$2,$H$2, if(C59=$G$3,$H$3, if(C59=$G$4,$H$4, if(C59=$G$5,$H$5,if(C59=$G$6,$H$6, " "))))) -> II | E59: =CONCATENATE(B59,"/",D59,"/",M59) -> FA039.9/II/01 | F59: NEWVY 4 TIER BLACK | G59: 43692 | H59: 759000 | J59: Chendy | K59: BOD | L59: BSD | M59: =if(L59=$J$2,$K$2,if(L59=$J$3,$K$3,if(L59=$J$4,$K$4," "))) -> 01 | N59: Informa
A60: 51 | B60: FA040.1 | C60: Furniture | D60: =if(C60=$G$2,$H$2, if(C60=$G$3,$H$3, if(C60=$G$4,$H$4, if(C60=$G$5,$H$5,if(C60=$G$6,$H$6, " "))))) -> II | E60: =CONCATENATE(B60,"/",D60,"/",M60) -> FA040.1/II/01 | F60: ZEDD STAFF CHAIR LOW BACK GREY | G60: 43692 | H60: 899500 | J60: Gio Saputra | K60: HRGA & Legal | L60: BSD | M60: =if(L60=$J$2,$K$2,if(L60=$J$3,$K$3,if(L60=$J$4,$K$4," "))) -> 01 | N60: Informa
A61: 60 | B61: FA040.10 | C61: Furniture | D61: =if(C61=$G$2,$H$2, if(C61=$G$3,$H$3, if(C61=$G$4,$H$4, if(C61=$G$5,$H$5,if(C61=$G$6,$H$6, " "))))) -> II | E61: =CONCATENATE(B61,"/",D61,"/",M61) -> FA040.10/II/01 | F61: LAREDO BAR CHAIR BLACK | G61: 43692 | H61: 389000 | K61: HRGA & Legal | L61: BSD | M61: =if(L61=$J$2,$K$2,if(L61=$J$3,$K$3,if(L61=$J$4,$K$4," "))) -> 01 | N61: Informa
A62: 61 | B62: FA040.11 | C62: Furniture | D62: =if(C62=$G$2,$H$2, if(C62=$G$3,$H$3, if(C62=$G$4,$H$4, if(C62=$G$5,$H$5,if(C62=$G$6,$H$6, " "))))) -> II | E62: =CONCATENATE(B62,"/",D62,"/",M62) -> FA040.11/II/01 | F62: LAREDO BAR CHAIR BLACK | G62: 43692 | H62: 389000 | K62: HRGA & Legal | L62: BSD | M62: =if(L62=$J$2,$K$2,if(L62=$J$3,$K$3,if(L62=$J$4,$K$4," "))) -> 01 | N62: Informa
A63: 62 | B63: FA040.12 | C63: Furniture | D63: =if(C63=$G$2,$H$2, if(C63=$G$3,$H$3, if(C63=$G$4,$H$4, if(C63=$G$5,$H$5,if(C63=$G$6,$H$6, " "))))) -> II | E63: =CONCATENATE(B63,"/",D63,"/",M63) -> FA040.12/II/01 | F63: LAREDO BAR CHAIR BLACK | G63: 43692 | H63: 389000 | K63: HRGA & Legal | L63: BSD | M63: =if(L63=$J$2,$K$2,if(L63=$J$3,$K$3,if(L63=$J$4,$K$4," "))) -> 01 | N63: Informa
A64: 63 | B64: FA040.13 | C64: Furniture | D64: =if(C64=$G$2,$H$2, if(C64=$G$3,$H$3, if(C64=$G$4,$H$4, if(C64=$G$5,$H$5,if(C64=$G$6,$H$6, " "))))) -> II | E64: =CONCATENATE(B64,"/",D64,"/",M64) -> FA040.13/II/01 | F64: LAREDO BAR CHAIR BLACK | G64: 43692 | H64: 389000 | K64: HRGA & Legal | L64: BSD | M64: =if(L64=$J$2,$K$2,if(L64=$J$3,$K$3,if(L64=$J$4,$K$4," "))) -> 01 | N64: Informa
A65: 64 | B65: FA040.14 | C65: Furniture | D65: =if(C65=$G$2,$H$2, if(C65=$G$3,$H$3, if(C65=$G$4,$H$4, if(C65=$G$5,$H$5,if(C65=$G$6,$H$6, " "))))) -> II | E65: =CONCATENATE(B65,"/",D65,"/",M65) -> FA040.14/II/01 | F65: LAREDO BAR CHAIR BLACK | G65: 43692 | H65: 389000 | K65: HRGA & Legal | L65: BSD | M65: =if(L65=$J$2,$K$2,if(L65=$J$3,$K$3,if(L65=$J$4,$K$4," "))) -> 01 | N65: Informa
A66: 65 | B66: FA040.15 | C66: Furniture | D66: =if(C66=$G$2,$H$2, if(C66=$G$3,$H$3, if(C66=$G$4,$H$4, if(C66=$G$5,$H$5,if(C66=$G$6,$H$6, " "))))) -> II | E66: =CONCATENATE(B66,"/",D66,"/",M66) -> FA040.15/II/01 | F66: LAREDO BAR CHAIR BLACK | G66: 43692 | H66: 389000 | K66: HRGA & Legal | L66: BSD | M66: =if(L66=$J$2,$K$2,if(L66=$J$3,$K$3,if(L66=$J$4,$K$4," "))) -> 01 | N66: Informa
A67: 66 | B67: FA040.16 | C67: Furniture | D67: =if(C67=$G$2,$H$2, if(C67=$G$3,$H$3, if(C67=$G$4,$H$4, if(C67=$G$5,$H$5,if(C67=$G$6,$H$6, " "))))) -> II | E67: =CONCATENATE(B67,"/",D67,"/",M67) -> FA040.16/II/01 | F67: HECTOR OFFICE TABLE WALNUT BLACK | G67: 43692 | H67: 999000 | J67: Hari TM | K67: Engineering | L67: BSD | M67: =if(L67=$J$2,$K$2,if(L67=$J$3,$K$3,if(L67=$J$4,$K$4," "))) -> 01 | N67: Informa
A68: 67 | B68: FA040.17 | C68: Furniture | D68: =if(C68=$G$2,$H$2, if(C68=$G$3,$H$3, if(C68=$G$4,$H$4, if(C68=$G$5,$H$5,if(C68=$G$6,$H$6, " "))))) -> II | E68: =CONCATENATE(B68,"/",D68,"/",M68) -> FA040.17/II/01 | F68: HECTOR OFFICE TABLE WALNUT BLACK | G68: 43692 | H68: 999000 | J68: Aji | K68: PITD | L68: BSD | M68: =if(L68=$J$2,$K$2,if(L68=$J$3,$K$3,if(L68=$J$4,$K$4," "))) -> 01 | N68: Informa
A69: 68 | B69: FA040.18 | C69: Furniture | D69: =if(C69=$G$2,$H$2, if(C69=$G$3,$H$3, if(C69=$G$4,$H$4, if(C69=$G$5,$H$5,if(C69=$G$6,$H$6, " "))))) -> II | E69: =CONCATENATE(B69,"/",D69,"/",M69) -> FA040.18/II/01 | F69: HECTOR OFFICE TABLE WALNUT BLACK | G69: 43692 | H69: 999000 | J69: Adya | K69: Finance & Accounting | L69: BSD | M69: =if(L69=$J$2,$K$2,if(L69=$J$3,$K$3,if(L69=$J$4,$K$4," "))) -> 01 | N69: Informa
A70: 69 | B70: FA040.19 | C70: Furniture | D70: =if(C70=$G$2,$H$2, if(C70=$G$3,$H$3, if(C70=$G$4,$H$4, if(C70=$G$5,$H$5,if(C70=$G$6,$H$6, " "))))) -> II | E70: =CONCATENATE(B70,"/",D70,"/",M70) -> FA040.19/II/01 | F70: HECTOR OFFICE TABLE WALNUT BLACK | G70: 43692 | H70: 999000 | J70: Rubi | K70: PITD | L70: BSD | M70: =if(L70=$J$2,$K$2,if(L70=$J$3,$K$3,if(L70=$J$4,$K$4," "))) -> 01 | N70: Informa
A71: 52 | B71: FA040.2 | C71: Furniture | D71: =if(C71=$G$2,$H$2, if(C71=$G$3,$H$3, if(C71=$G$4,$H$4, if(C71=$G$5,$H$5,if(C71=$G$6,$H$6, " "))))) -> II | E71: =CONCATENATE(B71,"/",D71,"/",M71) -> FA040.2/II/01 | F71: ZEDD STAFF CHAIR LOW BACK GREY | G71: 43692 | H71: 899500 | J71: Chendy | K71: BOD | L71: BSD | M71: =if(L71=$J$2,$K$2,if(L71=$J$3,$K$3,if(L71=$J$4,$K$4," "))) -> 01 | N71: Informa
A72: 70 | B72: FA040.20 | C72: Furniture | D72: =if(C72=$G$2,$H$2, if(C72=$G$3,$H$3, if(C72=$G$4,$H$4, if(C72=$G$5,$H$5,if(C72=$G$6,$H$6, " "))))) -> II | E72: =CONCATENATE(B72,"/",D72,"/",M72) -> FA040.20/II/01 | F72: HECTOR OFFICE TABLE WALNUT BLACK | G72: 43692 | H72: 999000 | J72: Marcel | K72: PITD | L72: BSD | M72: =if(L72=$J$2,$K$2,if(L72=$J$3,$K$3,if(L72=$J$4,$K$4," "))) -> 01 | N72: Informa
A73: 71 | B73: FA040.21 | C73: Furniture | D73: =if(C73=$G$2,$H$2, if(C73=$G$3,$H$3, if(C73=$G$4,$H$4, if(C73=$G$5,$H$5,if(C73=$G$6,$H$6, " "))))) -> II | E73: =CONCATENATE(B73,"/",D73,"/",M73) -> FA040.21/II/01 | F73: HECTOR OFFICE TABLE WALNUT BLACK | G73: 43692 | H73: 999000 | J73: Rifky | K73: Engineering | L73: BSD | M73: =if(L73=$J$2,$K$2,if(L73=$J$3,$K$3,if(L73=$J$4,$K$4," "))) -> 01 | N73: Informa
A74: 72 | B74: FA040.22 | C74: Furniture | D74: =if(C74=$G$2,$H$2, if(C74=$G$3,$H$3, if(C74=$G$4,$H$4, if(C74=$G$5,$H$5,if(C74=$G$6,$H$6, " "))))) -> II | E74: =CONCATENATE(B74,"/",D74,"/",M74) -> FA040.22/II/01 | F74: HECTOR OFFICE TABLE WALNUT BLACK | G74: 43692 | H74: 999000 | J74: Fitria | K74: Finance & Accounting | L74: BSD | M74: =if(L74=$J$2,$K$2,if(L74=$J$3,$K$3,if(L74=$J$4,$K$4," "))) -> 01 | N74: Informa
A75: 73 | B75: FA040.23 | C75: Furniture | D75: =if(C75=$G$2,$H$2, if(C75=$G$3,$H$3, if(C75=$G$4,$H$4, if(C75=$G$5,$H$5,if(C75=$G$6,$H$6, " "))))) -> II | E75: =CONCATENATE(B75,"/",D75,"/",M75) -> FA040.23/II/01 | F75: MAINE DSTP+MDSTY MGR DESK 160 KW-R(P1/3) | G75: 43692 | H75: 1942000 | L75: BSD | M75: =if(L75=$J$2,$K$2,if(L75=$J$3,$K$3,if(L75=$J$4,$K$4," "))) -> 01
A76: 74 | B76: FA040.24 | C76: Furniture | D76: =if(C76=$G$2,$H$2, if(C76=$G$3,$H$3, if(C76=$G$4,$H$4, if(C76=$G$5,$H$5,if(C76=$G$6,$H$6, " "))))) -> II | E76: =CONCATENATE(B76,"/",D76,"/",M76) -> FA040.24/II/01 | F76: MAINE LEG+HRDWR MGR DESK 160 KW-R (P2/3) | G76: 43692 | H76: 771000 | L76: BSD | M76: =if(L76=$J$2,$K$2,if(L76=$J$3,$K$3,if(L76=$J$4,$K$4," "))) -> 01 | R76: Lost/ Missing
A77: 75 | B77: FA040.25 | C77: Furniture | D77: =if(C77=$G$2,$H$2, if(C77=$G$3,$H$3, if(C77=$G$4,$H$4, if(C77=$G$5,$H$5,if(C77=$G$6,$H$6, " "))))) -> II | E77: =CONCATENATE(B77,"/",D77,"/",M77) -> FA040.25/II/01 | F77: MAINE RETURN MANAGER DESK 160 KW-R(P3/3 | G77: 43692 | H77: 1286000 | L77: BSD | M77: =if(L77=$J$2,$K$2,if(L77=$J$3,$K$3,if(L77=$J$4,$K$4," "))) -> 01 | R77: Lost/ Missing
A78: 76 | B78: FA040.26 | C78: Furniture | D78: =if(C78=$G$2,$H$2, if(C78=$G$3,$H$3, if(C78=$G$4,$H$4, if(C78=$G$5,$H$5,if(C78=$G$6,$H$6, " "))))) -> II | E78: =CONCATENATE(B78,"/",D78,"/",M78) -> FA040.26/II/01 | F78: MAINE DESKTOP+MDSTY STFDSK 140KW (P1/3) | G78: 43692 | H78: 1016000 | J78: Joseline | K78: BOD | L78: BSD | M78: =if(L78=$J$2,$K$2,if(L78=$J$3,$K$3,if(L78=$J$4,$K$4," "))) -> 01
A79: 77 | B79: FA040.27 | C79: Furniture | D79: =if(C79=$G$2,$H$2, if(C79=$G$3,$H$3, if(C79=$G$4,$H$4, if(C79=$G$5,$H$5,if(C79=$G$6,$H$6, " "))))) -> II | E79: =CONCATENATE(B79,"/",D79,"/",M79) -> FA040.27/II/01 | F79: MAINE PEDESTAL STAFF DSK 140 KW (P3/3) | G79: 43692 | H79: 883000 | J79: Joseline | K79: BOD | L79: BSD | M79: =if(L79=$J$2,$K$2,if(L79=$J$3,$K$3,if(L79=$J$4,$K$4," "))) -> 01
A80: 78 | B80: FA040.28 | C80: Furniture | D80: =if(C80=$G$2,$H$2, if(C80=$G$3,$H$3, if(C80=$G$4,$H$4, if(C80=$G$5,$H$5,if(C80=$G$6,$H$6, " "))))) -> II | E80: =CONCATENATE(B80,"/",D80,"/",M80) -> FA040.28/II/01 | F80: MAINE LEG+HRDWR STF DESK 140 KW (P2/3) | G80: 43692 | H80: 800000 | J80: Joseline | K80: BOD | L80: BSD | M80: =if(L80=$J$2,$K$2,if(L80=$J$3,$K$3,if(L80=$J$4,$K$4," "))) -> 01
A81: 79 | B81: FA040.29 | C81: Furniture | D81: =if(C81=$G$2,$H$2, if(C81=$G$3,$H$3, if(C81=$G$4,$H$4, if(C81=$G$5,$H$5,if(C81=$G$6,$H$6, " "))))) -> II | E81: =CONCATENATE(B81,"/",D81,"/",M81) -> FA040.29/II/01 | F81: DESKTOP SIEBEN RECT MTG 2412 CO (P1/3) | G81: 43692 | H81: 2099000 | K81: Engineering | L81: BSD | M81: =if(L81=$J$2,$K$2,if(L81=$J$3,$K$3,if(L81=$J$4,$K$4," "))) -> 01
A82: 53 | B82: FA040.3 | C82: Furniture | D82: =if(C82=$G$2,$H$2, if(C82=$G$3,$H$3, if(C82=$G$4,$H$4, if(C82=$G$5,$H$5,if(C82=$G$6,$H$6, " "))))) -> II | E82: =CONCATENATE(B82,"/",D82,"/",M82) -> FA040.3/II/01 | F82: ZEDD STAFF CHAIR LOW BACK GREY | G82: 43692 | H82: 899500 | J82: Rubi | K82: PITD | L82: BSD | M82: =if(L82=$J$2,$K$2,if(L82=$J$3,$K$3,if(L82=$J$4,$K$4," "))) -> 01 | N82: Informa
A83: 80 | B83: FA040.30 | C83: Furniture | D83: =if(C83=$G$2,$H$2, if(C83=$G$3,$H$3, if(C83=$G$4,$H$4, if(C83=$G$5,$H$5,if(C83=$G$6,$H$6, " "))))) -> II | E83: =CONCATENATE(B83,"/",D83,"/",M83) -> FA040.30/II/01 | F83: LEG SIEBEN RECT MTG 2412 CO (P2/3) | G83: 43692 | H83: 1600000 | L83: BSD | M83: =if(L83=$J$2,$K$2,if(L83=$J$3,$K$3,if(L83=$J$4,$K$4," "))) -> 01 | R83: Lost/ Missing
A84: 81 | B84: FA040.31 | C84: Furniture | D84: =if(C84=$G$2,$H$2, if(C84=$G$3,$H$3, if(C84=$G$4,$H$4, if(C84=$G$5,$H$5,if(C84=$G$6,$H$6, " "))))) -> II | E84: =CONCATENATE(B84,"/",D84,"/",M84) -> FA040.31/II/01 | F84: BEAM SIEBEN RECT MTG 2412 CO (P3/3) | G84: 43692 | H84: 900000 | L84: BSD | M84: =if(L84=$J$2,$K$2,if(L84=$J$3,$K$3,if(L84=$J$4,$K$4," "))) -> 01 | R84: Lost/ Missing
A85: 54 | B85: FA040.4 | C85: Furniture | D85: =if(C85=$G$2,$H$2, if(C85=$G$3,$H$3, if(C85=$G$4,$H$4, if(C85=$G$5,$H$5,if(C85=$G$6,$H$6, " "))))) -> II | E85: =CONCATENATE(B85,"/",D85,"/",M85) -> FA040.4/II/01 | F85: ZEDD STAFF CHAIR LOW BACK GREY | G85: 43692 | H85: 899500 | J85: Ricardo | K85: Business Development | L85: BSD | M85: =if(L85=$J$2,$K$2,if(L85=$J$3,$K$3,if(L85=$J$4,$K$4," "))) -> 01 | N85: Informa
A86: 55 | B86: FA040.5 | C86: Furniture | D86: =if(C86=$G$2,$H$2, if(C86=$G$3,$H$3, if(C86=$G$4,$H$4, if(C86=$G$5,$H$5,if(C86=$G$6,$H$6, " "))))) -> II | E86: =CONCATENATE(B86,"/",D86,"/",M86) -> FA040.5/II/01 | F86: ZEDD STAFF CHAIR LOW BACK GREY | G86: 43692 | H86: 899500 | L86: BSD | M86: =if(L86=$J$2,$K$2,if(L86=$J$3,$K$3,if(L86=$J$4,$K$4," "))) -> 01 | N86: Informa | R86: Broken
A87: 56 | B87: FA040.6 | C87: Furniture | D87: =if(C87=$G$2,$H$2, if(C87=$G$3,$H$3, if(C87=$G$4,$H$4, if(C87=$G$5,$H$5,if(C87=$G$6,$H$6, " "))))) -> II | E87: =CONCATENATE(B87,"/",D87,"/",M87) -> FA040.6/II/01 | F87: ZEDD STAFF CHAIR LOW BACK GREY | G87: 43692 | H87: 899500 | L87: BSD | M87: =if(L87=$J$2,$K$2,if(L87=$J$3,$K$3,if(L87=$J$4,$K$4," "))) -> 01 | N87: Informa | R87: Broken
A88: 57 | B88: FA040.7 | C88: Furniture | D88: =if(C88=$G$2,$H$2, if(C88=$G$3,$H$3, if(C88=$G$4,$H$4, if(C88=$G$5,$H$5,if(C88=$G$6,$H$6, " "))))) -> II | E88: =CONCATENATE(B88,"/",D88,"/",M88) -> FA040.7/II/01 | F88: ZEDD STAFF CHAIR LOW BACK GREY | G88: 43692 | H88: 899500 | L88: BSD | M88: =if(L88=$J$2,$K$2,if(L88=$J$3,$K$3,if(L88=$J$4,$K$4," "))) -> 01 | N88: Informa | R88: Broken
A89: 58 | B89: FA040.8 | C89: Furniture | D89: =if(C89=$G$2,$H$2, if(C89=$G$3,$H$3, if(C89=$G$4,$H$4, if(C89=$G$5,$H$5,if(C89=$G$6,$H$6, " "))))) -> II | E89: =CONCATENATE(B89,"/",D89,"/",M89) -> FA040.8/II/01 | F89: ZEDD STAFF CHAIR LOW BACK GREY | G89: 43692 | H89: 899500 | L89: BSD | M89: =if(L89=$J$2,$K$2,if(L89=$J$3,$K$3,if(L89=$J$4,$K$4," "))) -> 01 | N89: Informa | R89: Broken
A90: 59 | B90: FA040.9 | C90: Furniture | D90: =if(C90=$G$2,$H$2, if(C90=$G$3,$H$3, if(C90=$G$4,$H$4, if(C90=$G$5,$H$5,if(C90=$G$6,$H$6, " "))))) -> II | E90: =CONCATENATE(B90,"/",D90,"/",M90) -> FA040.9/II/01 | F90: MELVILLE BAR TABLE 180X70X105 CM BROWN | G90: 43692 | H90: 2999000 | K90: HRGA & Legal | L90: BSD | M90: =if(L90=$J$2,$K$2,if(L90=$J$3,$K$3,if(L90=$J$4,$K$4," "))) -> 01
A91: 82 | B91: FA041 | C91: Elektronik | D91: =if(C91=$G$2,$H$2, if(C91=$G$3,$H$3, if(C91=$G$4,$H$4, if(C91=$G$5,$H$5,if(C91=$G$6,$H$6, " "))))) -> I | E91: =CONCATENATE(B91,"/",D91,"/",M91) -> FA041/I/01 | F91: MICROWAVE | G91: 43313 | H91: 1250000 | K91: HRGA & Legal | L91: BSD | M91: =if(L91=$J$2,$K$2,if(L91=$J$3,$K$3,if(L91=$J$4,$K$4," "))) -> 01
A92: 83 | B92: FA042 | C92: Elektronik | D92: =if(C92=$G$2,$H$2, if(C92=$G$3,$H$3, if(C92=$G$4,$H$4, if(C92=$G$5,$H$5,if(C92=$G$6,$H$6, " "))))) -> I | E92: =CONCATENATE(B92,"/",D92,"/",M92) -> FA042/I/01 | F92: DISPENSER | G92: 43678 | H92: 290000 | L92: BSD | M92: =if(L92=$J$2,$K$2,if(L92=$J$3,$K$3,if(L92=$J$4,$K$4," "))) -> 01 | R92: Broken
A93: 84 | B93: FA043 | C93: Elektronik | D93: =if(C93=$G$2,$H$2, if(C93=$G$3,$H$3, if(C93=$G$4,$H$4, if(C93=$G$5,$H$5,if(C93=$G$6,$H$6, " "))))) -> I | E93: =CONCATENATE(B93,"/",D93,"/",M93) -> FA043/I/02 | F93: CCTV CAMERA (6) + DVR 8 TITIK + HARDISK 500GB | G93: 43711 | H93: 3270000 | L93: Deltamas 1 | M93: =if(L93=$J$2,$K$2,if(L93=$J$3,$K$3,if(L93=$J$4,$K$4," "))) -> 02 | R93: Broken
A94: 85 | B94: FA044 | C94: Elektronik | D94: =if(C94=$G$2,$H$2, if(C94=$G$3,$H$3, if(C94=$G$4,$H$4, if(C94=$G$5,$H$5,if(C94=$G$6,$H$6, " "))))) -> I | E94: =CONCATENATE(B94,"/",D94,"/",M94) -> FA044/I/01 | F94: HP PRINTER 2135 | G94: 43711 | H94: 565000 | J94: Chendy | K94: BOD | L94: BSD | M94: =if(L94=$J$2,$K$2,if(L94=$J$3,$K$3,if(L94=$J$4,$K$4," "))) -> 01 | N94: HP | Q94: Rumah Pak Chendy
A95: 86 | B95: FA045 | C95: Machine and Tooling | D95: =if(C95=$G$2,$H$2, if(C95=$G$3,$H$3, if(C95=$G$4,$H$4, if(C95=$G$5,$H$5,if(C95=$G$6,$H$6, " "))))) -> V | E95: =CONCATENATE(B95,"/",D95,"/",M95) -> FA045/V/01 | F95: SHARK COMPRESSOR OIL FREE | G95: 43711 | H95: 1300000 | J95: Chendy | K95: BOD | L95: BSD | M95: =if(L95=$J$2,$K$2,if(L95=$J$3,$K$3,if(L95=$J$4,$K$4," "))) -> 01 | N95: Shark | Q95: Rumah Pak Chendy
A96: 87 | B96: FA046 | C96: Elektronik | D96: =if(C96=$G$2,$H$2, if(C96=$G$3,$H$3, if(C96=$G$4,$H$4, if(C96=$G$5,$H$5,if(C96=$G$6,$H$6, " "))))) -> I | E96: =CONCATENATE(B96,"/",D96,"/",M96) -> FA046/I/01 | F96: PHONE TAB A 8" + SILICON TAB A8" SAMSUNG | G96: 43713 | H96: 3860000 | J96: Dimas | K96: HRGA & Legal | L96: BSD | M96: =if(L96=$J$2,$K$2,if(L96=$J$3,$K$3,if(L96=$J$4,$K$4," "))) -> 01 | N96: Samsung | O96: Galaxy
A97: 88 | B97: FA047 | C97: Elektronik | D97: =if(C97=$G$2,$H$2, if(C97=$G$3,$H$3, if(C97=$G$4,$H$4, if(C97=$G$5,$H$5,if(C97=$G$6,$H$6, " "))))) -> I | E97: =CONCATENATE(B97,"/",D97,"/",M97) -> FA047/I/01 | F97: GIANT - TV LED 40 " (2UNIT) + BREKET (2PC) | G97: 43713 | H97: 4898000 | L97: BSD | M97: =if(L97=$J$2,$K$2,if(L97=$J$3,$K$3,if(L97=$J$4,$K$4," "))) -> 01 | R97: Lost/ Missing
A98: 89 | B98: FA048 | C98: Elektronik | D98: =if(C98=$G$2,$H$2, if(C98=$G$3,$H$3, if(C98=$G$4,$H$4, if(C98=$G$5,$H$5,if(C98=$G$6,$H$6, " "))))) -> I | E98: =CONCATENATE(B98,"/",D98,"/",M98) -> FA048/I/01 | F98: OCULUS QUEST 64 GB | G98: 43720 | H98: 7320000 | L98: BSD | M98: =if(L98=$J$2,$K$2,if(L98=$J$3,$K$3,if(L98=$J$4,$K$4," "))) -> 01 | N98: Oculus | R98: Lost/ Missing
A99: 90 | B99: FA049 | C99: Machine and Tooling | D99: =if(C99=$G$2,$H$2, if(C99=$G$3,$H$3, if(C99=$G$4,$H$4, if(C99=$G$5,$H$5,if(C99=$G$6,$H$6, " "))))) -> V | E99: =CONCATENATE(B99,"/",D99,"/",M99) -> FA049/V/02 | F99: MESIN CNC 3018 ENGRAVING MILLING ER11 | G99: 43709 | H99: 1775427 | K99: Engineering | L99: Deltamas 1 | M99: =if(L99=$J$2,$K$2,if(L99=$J$3,$K$3,if(L99=$J$4,$K$4," "))) -> 02 | Q99: Di Pak Hari | R99: Broken
A100: 91 | B100: FA050 | C100: Elektronik | D100: =if(C100=$G$2,$H$2, if(C100=$G$3,$H$3, if(C100=$G$4,$H$4, if(C100=$G$5,$H$5,if(C100=$G$6,$H$6, " "))))) -> I | E100: =CONCATENATE(B100,"/",D100,"/",M100) -> FA050/I/01 | F100: PRINTER THERMAL | G100: 43709 | H100: 1605000 | L100: BSD | M100: =if(L100=$J$2,$K$2,if(L100=$J$3,$K$3,if(L100=$J$4,$K$4," "))) -> 01
A101: 92 | B101: FA051 | C101: Furniture | D101: =if(C101=$G$2,$H$2, if(C101=$G$3,$H$3, if(C101=$G$4,$H$4, if(C101=$G$5,$H$5,if(C101=$G$6,$H$6, " "))))) -> II | E101: =CONCATENATE(B101,"/",D101,"/",M101) -> FA051/II/01 | F101: RAK STORAGE INFORMA | G101: 43770 | H101: 1099000 | K101: Sales & Marketing | L101: BSD | M101: =if(L101=$J$2,$K$2,if(L101=$J$3,$K$3,if(L101=$J$4,$K$4," "))) -> 01 | N101: Informa
A102: 93 | B102: FA052 | C102: Furniture | D102: =if(C102=$G$2,$H$2, if(C102=$G$3,$H$3, if(C102=$G$4,$H$4, if(C102=$G$5,$H$5,if(C102=$G$6,$H$6, " "))))) -> II | E102: =CONCATENATE(B102,"/",D102,"/",M102) -> FA052/II/02 | F102: RAK STORAGE INFORMA 2 UNIT | G102: 43809 | H102: =2198000/2 -> 1099000 | L102: Deltamas 1 | M102: =if(L102=$J$2,$K$2,if(L102=$J$3,$K$3,if(L102=$J$4,$K$4," "))) -> 02 | N102: Informa | Q102: Terguyur hujan saat pindah | R102: Broken
...

Sheet List of Assets (Old Data)
A1: LEGENDA
B2: Lost/ Missing
B3: Broken
B4: Sell
B5: Odd (See Comment)
B6: Belum diinput Finance
A9: No | B9: Asset ID | C9: Asset Name | D9: Purchase Date | E9: Cost (Finance) | F9: Cost (GA) | G9: PIC | H9: Department | I9: Site | J9: Brand | K9: Model | L9: Serial Number | M9: Notes [SO 2023] | N9: Status | O9: Price
A10: 1 | B10: FA001/I/02 | C10: MONITOR DELL P2314H 23 INC | D10: 42005 | E10: 3150000 | J10: Dell | N10: Lost/ Missing
A11: 2 | B11: FA002/I/01 | C11: LAPTOP | D11: 42135 | E11: 6900000 | N11: Lost/ Missing
A12: 3 | B12: FA003/I/01 | C12: HARDISK | D12: 42135 | E12: 580000 | F12: 580000
A13: 4 | B13: FA004/II/01 | C13: BANGKU | D13: 42249 | E13: 2500000 | N13: Lost/ Missing
A14: 5 | B14: FA005/II/01 | C14: RAK | D14: 42252 | E14: 1787190 | N14: Broken
A15: 6 | B15: FA006/II/01 | C15: MEJA | D15: 42254 | E15: 3034500 | F15: 3034500
A16: 7 | B16: FA007/II/01 | C16: LEMARI | D16: 42278 | E16: 570000 | N16: Broken
A17: 8 | B17: FA008/II/01 | C17: KIPAS | D17: 42279 | E17: 220000 | N17: Broken
A18: 9 | B18: FA009/I/01 | C18: HP SAMSUNG GALAXY | D18: 42338 | E18: 2950000 | J18: Samsung | N18: Lost/ Missing
A19: 10 | B19: FA010/I/01 | C19: TV | D19: 42403 | E19: 300000 | N19: Lost/ Missing
A20: 11 | B20: FA011/III/01 | C20: LAPTOP HP I3 | D20: 42675 | E20: 6540000 | F20: 6540000 | J20: HP
A21: 12 | B21: FA012/I/01 | C21: MESIN ABSEN | D21: 42522 | E21: 1500000 | N21: Lost/ Missing
A22: 13 | B22: FA013/I/01 | C22: PRINTER | D22: 42566 | E22: 660000 | N22: Lost/ Missing
A23: 14 | B23: FA014/II/01 | C23: KURSI STAFF | D23: 42466 | E23: 900000 | N23: Lost/ Missing
A24: 15 | B24: FA015/II/01 | C24: MEJA | D24: 42461 | E24: 750000 | F24: 750000
A25: 16 | B25: FA016/III/01 | C25: LAPTOP & MONITOR | D25: 42736 | E25: 21000000 | G25: Adi Kusuma | H25: Engineering | N25: Lost/ Missing
A26: 17 | B26: FA017/I/01 | C26: PC. DELL PRECISION TOWER 5810 | D26: 42736 | E26: 37505000 | G26: Hari Mulyanto | H26: Engineering | J26: Dell | N26: Lost/ Missing
A27: 18 | B27: FA018/III/01 | C27: LAPTOP ROG GL552VX | D27: 42979 | E27: 13050000 | F27: 13050000 | J27: Asus
A28: 19 | B28: FA019/I/02 | C28: PRINTER 3D | D28: 42979 | E28: 3275000 | F28: 3275000
A29: 20 | B29: FA020/I/02 | C29: AC POLYTRON | D29: 43049 | E29: 3000000 | I29: Deltamas | J29: Polytron | N29: Lost/ Missing
A30: 21 | B30: FA021/II/01 | C30: MEJA | D30: 43132 | E30: 1400000 | F30: 1400000
A31: 22 | B31: FA022/III/01 | C31: LAPTOP | D31: 43132 | E31: 14548800 | F31: 14548800 | G31: Hari TM | H31: Engineering
A32: 23 | B32: FA023/I/01 | C32: KOMPUTER VGA ASUS | D32: 43160 | E32: 31200000 | J32: Asus | N32: Lost/ Missing
A33: 24 | B33: FA024/III/01 | C33: ACER PREDATOR NITRO | D33: 43160 | E33: 10999000 | J33: Acer | N33: Lost/ Missing
A34: 25 | B34: FA025/I/02 | C34: AC POLYTRON | D34: 43221 | E34: 3000000 | J34: Polytron | N34: Lost/ Missing
A35: 26 | B35: FA026/I/01 | C35: 3 MONITOR + KEYBOARD 2 + MOUSE 2 + ACC + KABEL VGA + KABEL USG EXT STD | D35: 43221 | E35: 4920000 | F35: 4920000
A36: 27 | B36: FA027/I/01 | C36: CAMERA UTK IMAJIN | D36: 43256 | E36: 9500032 | F36: 9500032 | H36: HRGA & Legal | I36: BSD
A37: 28 | B37: FA028/I/01 | C37: Lenovo IP1205 | D37: 43287 | E37: 3900000 | F37: 3900000 | H37: Finance & Accounting | J37: Lenovo
A38: 29 | B38: FA029/I/02 | C38: 3D PRINTER | D38: 43314 | E38: 2953007 | F38: 2953007
A39: 30 | B39: FA030/I/01 | C39: HP XIAOMI | D39: 43313 | E39: 1320000 | I39: Deltamas | J39: Xiaomi | N39: Lost/ Missing
A40: 31 | B40: FA031/I/02 | C40: 3D PRINTER ANYCUBIC PHOTON | D40: 43378 | E40: 8190000 | F40: 8190000 | J40: Anycubic
A41: 32 | B41: FA032/I/01 | C41: LEMARI & TURN TABLE U/ 3D SCANNING IMAJIN | D41: 43383 | E41: 898900 | I41: BSD | N41: Lost/ Missing
A42: 33 | B42: FA033/I/01 | C42: MESIN ABSEN FINGER SPOA REVO 163BNC | D42: 43557 | E42: 1200000 | I42: BSD | J42: Revo | N42: Lost/ Missing
A43: 34 | B43: FA034/III/01 | C43: LAPTOP ASUS A407 MA N4000 4GB 128 SSD 14' | D43: 43563 | E43: 4116265 | F43: 4116265 | J43: Asus
A44: 35 | B44: FA035/I/02 | C44: AC GREE GWC 05C3E INDOOR + OUTDOOR (1/2 PK) | D44: 43679 | E44: 2799000 | F44: 2799000 | I44: Deltamas | J44: Gree
A45: 36 | B45: FA036.1/I/02 | C45: AC GREE GWC 09C3E INDOOR + OUTDOOR (1 PK) | D45: 43679 | E45: 3049000 | F45: 3049000 | I45: Deltamas | J45: Gree
A46: 37 | B46: FA036.2/I/02 | C46: AC GREE GWC 09C3E INDOOR + OUTDOOR (1 PK) | D46: 43679 | E46: 3049000 | F46: 3049000 | I46: Deltamas | J46: Gree
A47: 38 | B47: FA036.3/I/02 | C47: AC GREE GWC 09C3E INDOOR + OUTDOOR (1 PK) | D47: 43679 | E47: 3049000 | F47: 3049000 | I47: Deltamas | J47: Gree
A48: 39 | B48: FA037/I/01 | C48: AC GREE GKH 48K3H INDDOOR + OUTDOOR (5 PK) | D48: 43679 | I48: Deltamas | J48: Gree | N48: Sell | O48: 22500000
A49: 40 | B49: FA038.1/II/01 | C49: KNOXHULT BASE CB W DRS/DRW 120 WHI | D49: 43690 | E49: 2550000 | F49: 2550000 | I49: BSD
A50: 41 | B50: FA038.2/II/01 | C50: KNOXHULT BASE CB W DOORS 80X85 WHITE AP | D50: 43690 | E50: 1500000 | F50: 1500000 | I50: BSD
A51: 42 | B51: FA039.1/II/01 | C51: LOMO STAFF CHAIR + NEWVY 4 TIER BLACK | D51: 43692 | E51: 799500 | F51: 799500 | I51: BSD | J51: Informa
A52: 43 | B52: FA039.2/II/01 | C52: LOMO STAFF CHAIR + NEWVY 4 TIER BLACK | D52: 43692 | E52: 799500 | F52: 799500 | I52: BSD | J52: Informa
A53: 44 | B53: FA039.3/II/01 | C53: LOMO STAFF CHAIR + NEWVY 4 TIER BLACK | D53: 43692 | E53: 799500 | F53: 799500 | I53: BSD | J53: Informa
A54: 45 | B54: FA039.4/II/01 | C54: LOMO STAFF CHAIR + NEWVY 4 TIER BLACK | D54: 43692 | E54: 799500 | F54: 799500 | I54: BSD | J54: Informa
A55: 46 | B55: FA039.5/II/01 | C55: LOMO STAFF CHAIR + NEWVY 4 TIER BLACK | D55: 43692 | E55: 799500 | F55: 799500 | I55: BSD | J55: Informa
A56: 47 | B56: FA039.6/II/01 | C56: LOMO STAFF CHAIR + NEWVY 4 TIER BLACK | D56: 43692 | E56: 799500 | F56: 799500 | I56: BSD | J56: Informa
A57: 48 | B57: FA039.7/II/01 | C57: LOMO STAFF CHAIR + NEWVY 4 TIER BLACK | D57: 43692 | E57: 799500 | F57: 799500 | I57: BSD | J57: Informa
A58: 49 | B58: FA039.8/II/01 | C58: LOMO STAFF CHAIR + NEWVY 4 TIER BLACK | D58: 43692 | E58: 799500 | F58: 799500 | I58: BSD | J58: Informa
A59: 50 | B59: FA039.9/II/01 | C59: NEWVY 4 TIER BLACK | D59: 43692 | E59: 759000 | F59: 759000 | J59: Informa
A60: 51 | B60: FA040.1/II/01 | C60: ZEDD STAFF CHAIR LOW BACK GREY | D60: 43692 | E60: 899500 | F60: 899500 | I60: BSD | J60: Informa
A61: 52 | B61: FA040.2/II/01 | C61: ZEDD STAFF CHAIR LOW BACK GREY | D61: 43692 | E61: 899500 | F61: 899500 | I61: BSD | J61: Informa
A62: 53 | B62: FA040.3/II/01 | C62: ZEDD STAFF CHAIR LOW BACK GREY | D62: 43692 | E62: 899500 | F62: 899500 | I62: BSD | J62: Informa
A63: 54 | B63: FA040.4/II/01 | C63: ZEDD STAFF CHAIR LOW BACK GREY | D63: 43692 | E63: 899500 | F63: 899500 | I63: BSD | J63: Informa
A64: 55 | B64: FA040.5/II/01 | C64: ZEDD STAFF CHAIR LOW BACK GREY | D64: 43692 | E64: 899500 | I64: BSD | J64: Informa | N64: Broken
A65: 56 | B65: FA040.6/II/01 | C65: ZEDD STAFF CHAIR LOW BACK GREY | D65: 43692 | E65: 899500 | I65: BSD | J65: Informa | N65: Broken
A66: 57 | B66: FA040.7/II/01 | C66: ZEDD STAFF CHAIR LOW BACK GREY | D66: 43692 | E66: 899500 | I66: BSD | J66: Informa | N66: Broken
A67: 58 | B67: FA040.8/II/01 | C67: ZEDD STAFF CHAIR LOW BACK GREY | D67: 43692 | E67: 899500 | I67: BSD | J67: Informa | N67: Broken
A68: 59 | B68: FA040.9/II/01 | C68: MELVILLE BAR TABLE 180X70X105 CM BROWN | D68: 43692 | E68: 2999000 | F68: 2999000 | I68: BSD
A69: 60 | B69: FA040.10/II/01 | C69: LAREDO BAR CHAIR BLACK | D69: 43692 | E69: 389000 | F69: 389000 | I69: BSD | J69: Informa
A70: 61 | B70: FA040.11/II/01 | C70: LAREDO BAR CHAIR BLACK | D70: 43692 | E70: 389000 | F70: 389000 | I70: BSD | J70: Informa
A71: 62 | B71: FA040.12/II/01 | C71: LAREDO BAR CHAIR BLACK | D71: 43692 | E71: 389000 | F71: 389000 | I71: BSD | J71: Informa
A72: 63 | B72: FA040.13/II/01 | C72: LAREDO BAR CHAIR BLACK | D72: 43692 | E72: 389000 | F72: 389000 | I72: BSD | J72: Informa
A73: 64 | B73: FA040.14/II/01 | C73: LAREDO BAR CHAIR BLACK | D73: 43692 | E73: 389000 | F73: 389000 | I73: BSD | J73: Informa
A74: 65 | B74: FA040.15/II/01 | C74: LAREDO BAR CHAIR BLACK | D74: 43692 | E74: 389000 | F74: 389000 | I74: BSD | J74: Informa
A75: 66 | B75: FA040.16/II/01 | C75: HECTOR OFFICE TABLE WALNUT BLACK | D75: 43692 | E75: 999000 | F75: 999000 | J75: Informa
A76: 67 | B76: FA040.17/II/01 | C76: HECTOR OFFICE TABLE WALNUT BLACK | D76: 43692 | E76: 999000 | F76: 999000 | J76: Informa
A77: 68 | B77: FA040.18/II/01 | C77: HECTOR OFFICE TABLE WALNUT BLACK | D77: 43692 | E77: 999000 | F77: 999000 | J77: Informa
A78: 69 | B78: FA040.19/II/01 | C78: HECTOR OFFICE TABLE WALNUT BLACK | D78: 43692 | E78: 999000 | F78: 999000 | J78: Informa
A79: 70 | B79: FA040.20/II/01 | C79: HECTOR OFFICE TABLE WALNUT BLACK | D79: 43692 | E79: 999000 | F79: 999000 | J79: Informa
A80: 71 | B80: FA040.21/II/01 | C80: HECTOR OFFICE TABLE WALNUT BLACK | D80: 43692 | E80: 999000 | F80: 999000 | J80: Informa
A81: 72 | B81: FA040.22/II/01 | C81: HECTOR OFFICE TABLE WALNUT BLACK | D81: 43692 | E81: 999000 | F81: 999000 | J81: Informa
A82: 73 | B82: FA040.23/II/01 | C82: MAINE DSTP+MDSTY MGR DESK 160 KW-R(P1/3) | D82: 43692 | E82: 1942000 | F82: 1942000
A83: 74 | B83: FA040.24/II/01 | C83: MAINE LEG+HRDWR MGR DESK 160 KW-R (P2/3) | D83: 43692 | E83: 771000 | N83: Lost/ Missing
A84: 75 | B84: FA040.25/II/01 | C84: MAINE RETURN MANAGER DESK 160 KW-R(P3/3 | D84: 43692 | E84: 1286000 | N84: Lost/ Missing
A85: 76 | B85: FA040.26/II/01 | C85: MAINE DESKTOP+MDSTY STFDSK 140KW (P1/3) | D85: 43692 | E85: 1016000 | F85: 1016000
A86: 77 | B86: FA040.27/II/01 | C86: MAINE PEDESTAL STAFF DSK 140 KW (P3/3) | D86: 43692 | E86: 883000 | F86: 883000
A87: 78 | B87: FA040.28/II/01 | C87: MAINE LEG+HRDWR STF DESK 140 KW (P2/3) | D87: 43692 | E87: 800000 | F87: 800000
A88: 79 | B88: FA040.29/II/01 | C88: DESKTOP SIEBEN RECT MTG 2412 CO (P1/3) | D88: 43692 | E88: 2099000 | F88: 2099000
A89: 80 | B89: FA040.30/II/01 | C89: LEG SIEBEN RECT MTG 2412 CO (P2/3) | D89: 43692 | E89: 1600000 | N89: Lost/ Missing
A90: 81 | B90: FA040.31/II/01 | C90: BEAM SIEBEN RECT MTG 2412 CO (P3/3) | D90: 43692 | E90: 900000 | N90: Lost/ Missing
A91: 82 | B91: FA041/I/01 | C91: MICROWAVE | D91: 43313 | E91: 1250000 | F91: 1250000
A92: 83 | B92: FA042/I/01 | C92: DISPENSER | D92: 43678 | E92: 290000 | N92: Broken
A93: 84 | B93: FA043/I/01 | C93: CCTV CAMERA (6) + DVR 8 TITIK + HARDISK 500GB | D93: 43711 | E93: 3270000 | F93: 3270000
A94: 85 | B94: FA044/I/01 | C94: HP PRINTER 2135 | D94: 43711 | E94: 565000 | F94: 565000 | I94: BSD | J94: HP | M94: Rumah Pak Chendy
A95: 86 | B95: FA045/V/02 | C95: SHARK COMPRESSOR OIL FREE | D95: 43711 | E95: 1300000 | F95: 1300000 | I95: BSD | J95: Shark | M95: Rumah Pak Chendy
A96: 87 | B96: FA046/I/01 | C96: PHONE TAB A 8" + SILICON TAB A8" SAMSUNG | D96: 43713 | E96: 3860000 | F96: 3860000 | J96: Samsung | K96: Galaxy
A97: 88 | B97: FA047/I/01 | C97: GIANT - TV LED 40 " (2UNIT) + BREKET (2PC) | D97: 43713 | E97: 4898000 | N97: Lost/ Missing
A98: 89 | B98: FA048/I/01 | C98: OCULUS QUEST 64 GB | D98: 43720 | E98: 7320000 | J98: Oculus | N98: Lost/ Missing
A99: 90 | B99: FA049/V/02 | C99: MESIN CNC 3018 ENGRAVING MILLING ER11 | D99: 43709 | E99: 1775427 | F99: 1775427 | M99: Di Pak Hari
A100: 91 | B100: FA050/I/01 | C100: PRINTER THERMAL | D100: 43709 | E100: 1605000 | F100: 1605000 | I100: BSD
A101: 92 | B101: FA051/II/01 | C101: RAK STORAGE INFORMA | D101: 43770 | E101: 1099000 | F101: 1099000 | I101: BSD | J101: Informa
A102: 93 | B102: FA052/II/01 | C102: RAK STORAGE INFORMA 2 UNIT | D102: 43809 | E102: 2198000 | F102: 2198000 | J102: Informa
...

Sheet Assets 2024
A1: LEGENDA
B2: Lost/ Missing
B3: Broken
B4: Sell
B5: Odd (See Comment)
B6: Belum diinput Finance
B9: Asset ID | C9: Asset Name | D9: Purchase Date | E9: Cost (Finance) | F9: Cost (GA & Supply Chain) | G9: PIC | H9: Department | I9: Site | J9: Brand | K9: Model | L9: Serial Number | M9: Notes [SO 2023] | N9: Status | O9: Price
A10: 365 | B10: FA322/IV/01 | C10: HONDA VARIO 125 | D10: 45309 | E10: 21478311 | G10: Rispandi | H10: HRGA & Legal | I10: BSD | J10: Honda | N10: Active
A11: 375 | B11: FA331/II/01 | C11: Softboard Cork Pin Board / Papan Mading Standing Keiko 90 x 120 cm | D11: 45344 | E11: 777900 | H11: HRGA & Legal | I11: BSD | N11: Active
A12: 376 | B12: FA332/I/01 | C12: Seagate One Touch Hardisk Eksternal 1TB USB3.0 | D12: 45344 | E12: 963400 | G12: Fattah | H12: Digital Marketing & Creative | I12: BSD | J12: Seagate | N12: Active
A13: 377 | B13: FA333/I/01 | C13: Seagate One Touch Hardisk Eksternal 1TB USB3.0 | D13: 45344 | E13: 963400 | G13: Fattah | H13: Digital Marketing & Creative | I13: BSD | J13: Seagate | N13: Active
A14: 378 | B14: FA334/II/01 | C14: Lomo Working Chair Low Back | D14: 45345 | E14: 859000 | H14: HRGA & Legal | I14: BSD | J14: Informa | N14: Active
A15: 379 | B15: FA335/II/01 | C15: Lomo Working Chair Low Back | D15: 45345 | E15: 859000 | H15: HRGA & Legal | I15: BSD | J15: Informa | N15: Active
A16: 380 | B16: FA336/II/01 | C16: Lomo Working Chair Low Back | D16: 45345 | E16: 859000 | H16: HRGA & Legal | I16: BSD | J16: Informa | N16: Active
A17: 381 | B17: FA337/II/01 | C17: Hector Office Table | D17: 45345 | E17: 899000 | H17: HRGA & Legal | I17: BSD | J17: Informa
A18: 382 | B18: FA338/II/01 | C18: Hector Office Table | D18: 45345 | E18: 899000 | H18: HRGA & Legal | I18: BSD | J18: Informa
A19: 384 | B19: FA340/I/01 | C19: Xiaomi Redmi 12 8/128GB & 8/256GB Android 13 Garansi Resmi - Black, 8/128GB | D19: 45351 | E19: 2068400 | G19: Harmoko | H19: Engineering | I19: BSD | J19: Xiaomi | N19: Active
A20: 385 | B20: FA341/V/01 | C20: DN Solutions Compact, Simultaneous 5-axis Machining Center For High Speed Machining model DVF-5000 with Fanuc F31B5P | D20: 45355 | E20: 3100000000 | G20: Hari TM | H20: Engineering | I20: BSD | J20: DN Solutions | N20: Active
A21: 386 | B21: FA342/I/01 | C21: IP Phone Fanvil X303W Include adaptor | D21: 45365 | E21: 1370850.5 | G21: Della | H21: HRGA & Legal | I21: BSD | J21: Fanvil | N21: Active
A22: 387 | B22: FA343/I/01 | C22: IP Phone Fanvil X303W Include adaptor | D22: 45365 | E22: 1370850.5 | G22: Gio Saputra | H22: HRGA & Legal | I22: BSD | J22: Fanvil | N22: Active
A23: 388 | B23: FA344/I/01 | C23: IP Phone Fanvil X303W Include adaptor | D23: 45365 | E23: 1370850.5 | G23: Audrey | H23: Finance & Accounting | I23: BSD | J23: Fanvil | N23: Active
A24: 389 | B24: FA345/I/01 | C24: IP Phone Fanvil X303W Include adaptor | D24: 45365 | E24: 1370850.5 | G24: Nabila | H24: Supply Chain | I24: BSD | J24: Fanvil | N24: Active
A25: 390 | B25: FA346/I/01 | C25: IP Phone Fanvil X303W Include Adaptor | D25: 45365 | E25: 1370850.5 | G25: Khrisna | H25: Sales & Marketing | I25: BSD | J25: Fanvil | N25: Active
A26: 391 | B26: FA347/V/01 | C26: MITSUBISHI MV2400S D-CUBES Wire-cut EDM | D26: 45366 | E26: 1600000000 | G26: Hari TM | H26: Engineering | I26: BSD | J26: Mitsubishi | N26: Active
A27: 393 | B27: FA349/I/01 | C27: GPS Tracker SUPERSPRING tipe C40 (2G & 4G) + 6 Bulan (untuk di mobil operasional) | D27: 45366 | E27: 1531532 | G27: Rispandi | H27: HRGA & Legal | I27: BSD | J27: Superspring | N27: Active
A28: 394 | B28: FA350/V/01 | C28: Kompresor Screw 15 HP | Volume Flow Rate 1,8 M³/mm | Rated Discharged Pressure 0,8 Mpa | Motor Power 11 KW | Overall dimensions (LxWxH) 104x75x104MM | Net Weight 258 kg, Air Dry & Tangki | D28: 45378 | E28: 31000000 | G28: Hari TM | H28: Engineering | I28: BSD | N28: Active
A29: 395 | B29: FA351/V/01 | C29: Air Dryer 20 HP | D29: 45378 | E29: 7000000 | G29: Hari TM | H29: Engineering | I29: BSD | N29: Active
A30: 396 | B30: FA352/V/01 | C30: Tangki 300 Liter | D30: 45378 | E30: 7000000 | G30: Hari TM | H30: Engineering | I30: BSD | N30: Active
A31: 398 | B31: FA354/I/01 | C31: Printer Canon PIXMA G4770 All in One ADF WiFi FAX pengganti G4010 | D31: 45412 | E31: 3975000 | H31: HRGA & Legal | I31: BSD | J31: Canon | N31: Active
A32: 402 | B32: FA358/I/01 | C32: CCTV Ezviz C6N 2 MP Black Smart Home Wifi IP Camera CCTV Indoor 1080p | D32: 45420 | E32: 642100 | H32: HRGA & Legal | I32: BSD | J32: Ezviz | N32: Active
A33: 403 | B33: FA359/I/01 | C33: CCTV Ezviz C6N 2 MP Black Smart Home Wifi IP Camera CCTV Indoor 1080p | D33: 45420 | E33: 642100 | H33: HRGA & Legal | I33: BSD | J33: Ezviz | N33: Active
A34: 404 | B34: FA360/I/01 | C34: CCTV Ezviz C6N 2 MP Black Smart Home Wifi IP Camera CCTV Indoor 1080p | D34: 45420 | E34: 642100 | H34: HRGA & Legal | I34: BSD | J34: Ezviz | N34: Active
A35: 405 | B35: FA361/I/01 | C35: CCTV Ezviz C6N 2 MP Black Smart Home Wifi IP Camera CCTV Indoor 1080p | D35: 45420 | E35: 642100 | H35: HRGA & Legal | I35: BSD | J35: Ezviz | N35: Active
A36: 406 | B36: FA362/I/01 | C36: CCTV Ezviz C6N 2 MP Black Smart Home Wifi IP Camera CCTV Indoor 1080p | D36: 45420 | E36: 642100 | H36: HRGA & Legal | I36: BSD | J36: Ezviz | N36: Active
A37: 407 | B37: FA363/I/01 | C37: CCTV Ezviz C6N 2 MP Black Smart Home Wifi IP Camera CCTV Indoor 1080p | D37: 45420 | E37: 642100 | H37: HRGA & Legal | I37: BSD | J37: Ezviz | N37: Active
A38: 408 | B38: FA364/I/01 | C38: CCTV Ezviz C6N 2 MP Black Smart Home Wifi IP Camera CCTV Indoor 1080p | D38: 45420 | E38: 642100 | H38: HRGA & Legal | I38: BSD | J38: Ezviz | N38: Active
A39: 409 | B39: FA365/I/01 | C39: CCTV Ezviz C6N 2 MP Black Smart Home Wifi IP Camera CCTV Indoor 1080p | D39: 45420 | E39: 642100 | H39: HRGA & Legal | I39: BSD | J39: Ezviz | N39: Active
A40: 410 | B40: FA366/I/01 | C40: CCTV Ezviz C6N 2 MP Black Smart Home Wifi IP Camera CCTV Indoor 1080p | D40: 45420 | E40: 642100 | H40: HRGA & Legal | I40: BSD | J40: Ezviz | N40: Active
A41: 411 | B41: FA367/I/01 | C41: CCTV Ezviz C6N 2 MP Black Smart Home Wifi IP Camera CCTV Indoor 1080p | D41: 45420 | E41: 642100 | H41: HRGA & Legal | I41: BSD | J41: Ezviz | N41: Active
A42: 412 | B42: FA368/I/01 | C42: CCTV Ezviz C6N 2 MP Black Smart Home Wifi IP Camera CCTV Indoor 1080p | D42: 45420 | E42: 642100 | H42: HRGA & Legal | I42: BSD | J42: Ezviz | N42: Active
... A44: 414 | B44: FA370/I/01 | C44: Bardi Smart Door Lock with Handle (Lite Version) | D44: 45420 | E44: 1210200 | H44: HRGA & Legal | I44: BSD | J44: Bardi | N44: Active
A45: 415 | B45: FA371/I/01 | C45: Access control Access Door Akses Drop bolt lock RFID Card PIN - Dropbolt Lock, No Touch | D45: 45420 | E45: 816900 | G45: Della | H45: HRGA & Legal | I45: BSD | N45: Active
A46: 416 | B46: FA372/I/01 | C46: Access control Access Door Akses Drop bolt lock RFID Card PIN - Dropbolt Lock, No Touch | D46: 45420 | E46: 816900 | G46: Della | H46: Engineering | I46: BSD | N46: Active
A47: 417 | B47: FA373/II/01 | C47: Informa Hector Meja Kantor - Hitam/cokelat Walnut | D47: 45443 | E47: 799000 | G47: Eka | H47: HRGA & Legal | I47: BSD | J47: Informa | N47: Active
A48: 418 | B48: FA374/II/01 | C48: Informa Hector Meja Kantor - Hitam/cokelat Walnut | D48: 45443 | E48: 799000 | G48: Dina | H48: HRGA & Legal | I48: BSD | J48: Informa | N48: Active
A49: 419 | B49: FA375/II/01 | C49: Informa Hector Meja Kantor - Hitam/cokelat Walnut | D49: 45443 | E49: 799000 | G49: Rifqi Caesara | H49: HRGA & Legal | I49: BSD | J49: Informa | N49: Active
A50: 420 | B50: FA376/II/01 | C50: CCTV Ezviz C6N 2 MP Black Smart Home Wifi IP Camera CCTV Indoor 1080p | D50: 45447 | E50: 651200 | H50: HRGA & Legal | I50: BSD | J50: Ezviz | N50: Active
A51: 421 | B51: FA377/III/01 | C51: Laptop Lenovo V14 G3 i3 1215GU 8GB 256SSD 14.0HD Windows 11 Resmi - Unit, 8/256 GB | D51: 45450 | E51: 5396175 | G51: Gio Saputra | H51: HRGA & Legal | I51: BSD | J51: Lenovo | N51: Active
A52: 422 | B52: FA378/II/01 | C52: Bracket Standing TV | D52: 45462 | E52: 576340 | G52: Bagas | H52: Supply Chain | I52: BSD | N52: Active
A53: 423 | B53: FA379/V/01 | C53: MITUTOYO 103-139-10 OUTSIDE Micrometer Economy Design 50-75mm 0.01mm | D53: 45471 | E53: 983900 | H53: Engineering | I53: BSD | J53: Tokopedia | N53: Active
A54: 424 | B54: FA380/V/01 | C54: Clamping Kit M12 Claim Milling - Clamping Set M12 | D54: 45471 | E54: 563000 | H54: Engineering | I54: BSD | N54: Active
A55: 425 | B55: FA381/I/01 | C55: Dispenser Cosmos CWD-7601 (3 keran) | D55: 45478 | E55: 1150000 | H55: HRGA & Legal | I55: BSD | J55: Cosmos | N55: Active
A56: 426 | B56: FA382/II/01 | C56: Informa Carter Credenza Kabinet Kantor Metal 2 Pintu - Putih | D56: 45455 | E56: 1399000 | H56: HRGA & Legal | I56: BSD | J56: Informa | N56: Active
A57: 427 | B57: FA383/V/01 | C57: Magnetic Dial Holder 0,01 | Merk Mitutoyo | 1 Set | D57: 45476 | E57: 1350000 | H57: Engineering | I57: BSD | J57: Techo | N57: Active
A58: 428 | B58: FA384/V/01 | C58: MITUTOYO Micrometer / Micro meter 103-137 / 0-25mm / 0.01 mm | D58: 45485 | E58: 880000 | H58: Engineering | I58: BSD | J58: Tokopedia | N58: Active
A59: 429 | B59: FA385/V/01 | C59: Caliper Digital 200 mm | Mitutoyo | D59: 45492 | E59: 2500000 | H59: Engineering | I59: BSD | J59: Techo | N59: Active
A60: 430 | B60: FA386/II/01 | C60: Nakas laci minimalis/ rak kantor locker bedside table | D60: 45496 | E60: 424900 | G60: Arina | H60: HRGA & Legal | I60: BSD | N60: Active
A61: 431 | B61: FA387/I/01 | C61: Dispenser Cosmos CWD-7601 (3 keran) | D61: 45499 | E61: 1150000 | H61: HRGA & Legal | I61: BSD | J61: Cosmos | N61: Active
A62: 364 | B62: FA321/I/02 | C62: Lemari Es Deltamas (Kulkas LG GN-B202SQIB 202L Top Freezer Fridge in Dark Graphite Steel) | D62: 45295 | E62: 3128020 | G62: Rino | H62: HRGA & Legal | I62: Deltamas 1 | J62: LG | N62: Active
A63: 366 | B63: FA323/IV/02 | C63: ALL NEW AVANZA 1.3 E CVT | D63: 45309 | E63: 211756190 | G63: Mahmudin | H63: HRGA & Legal | I63: Deltamas 1 | J63: Avanza | N63: Active
A64: 367 | B64: FA324/I/02 | C64: Webcam Logitec C270 HD 720p | D64: 45310 | E64: 255000 | G64: Gedeon | H64: Supply Chain | I64: Deltamas 1 | N64: Active
A65: 368 | B65: FA325/I/02 | C65: Webcam Logitec C270 HD 720p | D65: 45310 | E65: 255000 | G65: Rino | H65: HRGA & Legal | I65: Deltamas 1 | N65: Active
A66: 369 | B66: FA326/II/02 | C66: Kuris Kantor / Kursi Jaring / Kursi Staf Black - White Frame | D66: 45335 | E66: 417500 | G66: Rino | H66: HRGA & Legal | I66: Deltamas 1 | N66: Active
A67: 370 | B67: FA327/II/02 | C67: Kuris Kantor / Kursi Jaring / Kursi Staf Black - White Frame | D67: 45335 | E67: 417500 | G67: Rino | H67: HRGA & Legal | I67: Deltamas 1 | N67: Active
A68: 371 | B68: FA328/II/02 | C68: Meja Kantor Minimalis Putih Sonoma Oak Light via Cargo - ATP-MTB-WHT-102 2 UNIT | D68: 45335 | E68: 587550 | G68: Rino | H68: HRGA & Legal | I68: Deltamas 1 | N68: Active
A69: 372 | B69: FA329/II/02 | C69: Meja Kantor Minimalis Putih Sonoma Oak Light via Cargo - ATP-MTB-WHT-102 2 UNIT | D69: 45335 | E69: 587550 | G69: Rino | H69: HRGA & Legal | I69: Deltamas 1 | N69: Active
A70: 374 | B70: FA330/V/02 | C70: Kompresor Screw 50 HP | D70: 45342 | E70: 60060000 | H70: Operational | I70: Deltamas 1 | N70: Active
A71: 383 | B71: FA339/III/02 | C71: Lenovo IdeaPad Slim 3i 14ITL6 (Intel Core i7 1165G7, Win11 Home, 8GB DDR4, 512GB SSD, 14" FHD IPS 45% NTSC Antiglare, NVIDIA GeForce MX450 2GB, Backlit, 2Y Premium Care + ADP) + OHS 2021 | D71: 45351 | E71: 12250000 | G71: Eko Wahyu | H71: QA/QC | I71: Deltamas 1 | J71: Lenovo | N71: Active
A72: 392 | B72: FA348/I/02 | C72: GPS Tracker SUPERSPRING tipe C40 (2G & 4G) + 6 Bulan (untuk di mobil operasional) | D72: 45365 | E72: 1531532 | G72: Rispandi | H72: HRGA & Legal | I72: Deltamas 1 | J72: Superspring | N72: Active
A73: 397 | B73: FA353/I/02 | C73: Printer Brother MFC-J3540DW A3 Inkjet AIO WIFI Duplex Garansi Resmi | D73: 45412 | E73: 6780000 | G73: Eko Wahyu | H73: Engineering | I73: Deltamas 1 | J73: Brother | N73: Active
A74: 399 | B74: FA355/II/02 | C74: Lemari Pajangan Kaca 2 Pintu | D74: 45412 | E74: 1600000 | G74: Eko Wahyu | H74: HRGA & Legal | I74: Deltamas 1 | N74: Active
A75: 400 | B75: FA356/II/02 | C75: Lemari Pajangan Kaca 2 Pintu | D75: 45412 | E75: 1600000 | G75: Eko Wahyu | H75: HRGA & Legal | I75: Deltamas 1 | N75: Active
A76: 401 | B76: FA357/V/02 | C76: Mitutoyo Caliper 300 MM China | D76: 45412 | E76: 1328700 | G76: Eko Wahyu | H76: QA/QC | I76: Deltamas 1 | J76: Mitutoyo | N76: Active
A77: 432 | C77: Air Tank 1000 Ltr | D77: 45513 | F77: 10500000 | H77: Engineering | I77: Deltamas 2 | N77: Active
A78: 433 | C78: Screw Air Compressor 50 HP | D78: 45513 | F78: 56000000 | H78: Engineering | I78: Deltamas 2 | N78: Active
A79: 434 | C79: Air Dryer Screw 50 HP | D79: 45513 | F79: 12500000 | H79: Engineering | I79: Deltamas 2 | N79: Active
A80: 435 | C80: Hand Pallet 3 ton 'Carlift' | D80: 45524 | F80: 2700000 | H80: Engineering | I80: Deltamas 2 | N80: Active
A81: 436 | C81: Handi Lift 1 ton 'Carlift' | D81: 45524 | F81: 7000000 | H81: Engineering | I81: Deltamas 2 | N81: Active
A82: 437 | C82: Pallet Plastik tye NPJ-1111 "Hitam" | D82: 45524 | F82: 484500 | H82: Engineering | I82: Deltamas 2 | N82: Active
A83: 438 | C83: Kunci Sok Set (6-24mm) "Tekiro" | D83: 45530 | F83: 683375 | H83: Engineering | I83: Deltamas 2 | N83: Active
